Workbook

Sheet README
B2: REVII · VOICE CARE STANDALONE FINANCIAL MODEL
B3: Five-year plan for a real launch of Voice Care only — Portugal first, Spain from month 17
B6: PURPOSE
B7: What this is | C7: A practical sizing model for launching Voice Care as a standalone business: how much founders' equity it needs, when it turns cash-positive, and what the return looks like. It is a decision tool, not a statutory set of accounts.
B8: What it is not | C8: Not an accounting model. No deferred tax, no lease accounting, no monthly VAT settlement timing. Working capital is approximated with days ratios.
B10: HOW TO USE IT
B11: 1. Pick a scenario | C11: On 'Inputs' cell C6, enter 1 (Conservative), 2 (Base) or 3 (Optimistic). Every sheet updates. The three input sets live on the 'Scenarios' tab and can be edited there.
B12: 2. Override anything | C12: Every blue cell on 'Inputs' is editable. Blue cells fed by the scenario selector are on 'Scenarios'; all other blue cells are direct inputs.
B13: 3. Read the answer | C13: 'Dashboard' carries the headline: equity required, break-even month, Year 5 scale, and the return on the founders' money.
B15: COLOUR LEGEND
B16: Blue text | C16: A hardcoded input. Change these.
B17: Black text | C17: A formula. Do not overwrite.
B18: Green text | C18: A link pulled from another sheet.
B19: Yellow fill | C19: A key assumption that most deserves challenge.
B21: STRUCTURE
B22: Scenarios | C22: The three scenario input sets. Ten levers that swing the business.
B23: Inputs | C23: Every other assumption, with the source of each one noted alongside.
B24: Model PT / Model ES | C24: The monthly engine for each market: customers, revenue, cost of service, acquisition. Kept separate so the two revenue streams are never blended.
B25: P&L Monthly | C25: 60 months consolidated: P&L, working capital, capex, cash flow, and the founders' equity injection.
B26: Annual | C26: Years 1-5 P&L, cash flow and a light balance sheet.
B27: Dashboard | C27: Headline KPIs, unit economics and the return calculation.
B29: KEY DECISIONS BEHIND THE BASE CASE
B30: Prices are VAT-inclusive | C30: Neither the business plan nor the deck mentions VAT anywhere. Per instruction, the listed price is what the customer pays, so net revenue is the price divided by (1 + VAT). This costs ~19% of headline revenue in Portugal and is the single largest correction against the MBA model.
B31: Voice minutes drive everything | C31: The MBA model's EUR 11.28 cost per user is 75 minutes/month at EUR 0.15/min, i.e. 2.5 min/day — even though its own note says '~5 minutes/day'. At 5 min/day the product has a negative gross margin. Base case uses 1 call/day x 2.5 min. Test this first.
B32: Founders take no salary | C32: Per instruction. OPEX therefore excludes founder compensation in all five years, which flatters EBITDA relative to a normally-staffed company.
B33: 100% founders' equity | C33: No debt, no grant. The model injects equity monthly, only as needed to hold the minimum cash buffer. Total injected is the investment figure.
B34: Portugal builds first | C34: Months 1-4 are product build with no revenue. Portugal launches month 5, Spain month 17 (twelve months later), Preventive Care month 29 (+24 months, per the deck).
B36: SOURCES
B37: Financials_Revii_v3_full_product.xlsx | C37: Voice Care price, COGS build-up, COCA, churn, CAPEX, growth curve shape, OPEX structure.
B38: Lisbon MBA BP report (.docx) | C38: Preventive Care pricing and cost, market sequencing, operating model, team structure.
B39: Final version deck (.pdf) | C39: Launch sequencing (Spain +12 months, Preventive +24 months), unit economics per tier. Where the deck and the Excel disagree, the deck wins.
B41: Built for the Revii founding team · all figures in euros unless stated

Sheet Dashboard
B2: VOICE CARE — DASHBOARD
B3: ="Scenario in force: "&Inputs!C8&" · change it on Inputs!C7 (1 Conservative / 2 Base / 3 Optimistic)"
B5: THE INVESTMENT
B6: Total founders' equity required | C6: =MAX('P&L Monthly'!$D$63:$BK$63) | J6: Peak cumulative cash the founders must put in. This is the number to raise among yourselves.
B7: Of which, spent before Portugal launches | C7: ='P&L Monthly'!D63 | J7: Equity injected in month 1 — the build period. See Inputs section 2 for the build length.
B8: Deepest cash position (cumulative free cash flow) | C8: =MIN('P&L Monthly'!$D$60:$BK$60) | J8: The trough. The gap between this and zero is what the business has to earn back.
B9: Month of the deepest cash position | C9: ="Month "&INDEX('P&L Monthly'!$D$4:$BK$4,1,MATCH(MIN('P&L Monthly'!$D$60:$BK$60),'P&L Monthly'!$D$60:$BK$60,0))
B11: WHEN IT TURNS
B12: EBITDA turns positive (and stays) | C12: =IF(MIN('P&L Monthly'!$D$79:$BK$79)>=9999,"beyond year 5","Month "&MIN('P&L Monthly'!$D$79:$BK$79)) | J12: Operating profit before depreciation.
B13: Net income turns positive (and stays) | C13: =IF(MIN('P&L Monthly'!$D$81:$BK$81)>=9999,"beyond year 5","Month "&MIN('P&L Monthly'!$D$81:$BK$81))
B14: Free cash flow turns positive (and stays) | C14: =IF(MIN('P&L Monthly'!$D$80:$BK$80)>=9999,"beyond year 5","Month "&MIN('P&L Monthly'!$D$80:$BK$80)) | J14: The month the business stops consuming founders' money.
B15: Cumulative free cash flow back above zero | C15: =IF(MIN('P&L Monthly'!$D$82:$BK$82)>=9999,"beyond year 5","Month "&MIN('P&L Monthly'!$D$82:$BK$82)) | J15: The month the founders are, in cash terms, whole again.
B17: SCALE AT YEAR 5
B18: Net revenue | C18: =Annual!H10 | J18: After VAT, payment leakage and channel fees.
B19: Gross billings (what customers pay) | C19: =SUM('Model PT'!AZ23:BK23)+SUM('Model ES'!AZ23:BK23) | J19: The headline number. The gap to net revenue is VAT and leakage.
B20: EBITDA | C20: =Annual!H20
B21: EBITDA margin | C21: =Annual!H21
B22: Active customers — Portugal | C22: =Annual!H29
B23: Active customers — Spain | C23: =Annual!H30
B24: Active customers — total | C24: =Annual!H31
B25: Cumulative net income, years 1-5 | C25: =Annual!I25
B27: UNIT ECONOMICS (per customer)
C28: Portugal Y1 | D28: Portugal Y5 | E28: Spain Y2 | F28: Spain Y5 | J28: Portugal Y1 and Spain Y2 are each market's first trading year — Spain launches in month 17, so it has no Year 1.
B29: Net revenue per month | C29: =IFERROR(SUM('Model PT'!D24:O25)/SUM('Model PT'!D14:O14),0) | D29: =IFERROR(SUM('Model PT'!AZ24:BK25)/SUM('Model PT'!AZ14:BK14),0) | E29: =IFERROR(SUM('Model ES'!P24:AA25)/SUM('Model ES'!P14:AA14),0) | F29: =IFERROR(SUM('Model ES'!AZ24:BK25)/SUM('Model ES'!AZ14:BK14),0) | J29: Net revenue is after VAT, leakage and channel fees, so these are the real economics — not the headline price.
B30: Cost of service per month | C30: =IFERROR(SUM('Model PT'!D34:O34)/SUM('Model PT'!D14:O14),0) | D30: =IFERROR(SUM('Model PT'!AZ34:BK34)/SUM('Model PT'!AZ14:BK14),0) | E30: =IFERROR(SUM('Model ES'!P34:AA34)/SUM('Model ES'!P14:AA14),0) | F30: =IFERROR(SUM('Model ES'!AZ34:BK34)/SUM('Model ES'!AZ14:BK14),0)
B31: Gross profit per month | C31: =C29-C30 | D31: =D29-D30 | E31: =E29-E30 | F31: =F29-F30
B32: Gross margin | C32: =IFERROR(C31/C29,0) | D32: =IFERROR(D31/D29,0) | E32: =IFERROR(E31/E29,0) | F32: =IFERROR(F31/F29,0)
B33: Average customer life (months, capped for LTV) | C33: =MIN(Inputs!$C$43,Inputs!$C$105) | D33: =MIN(Inputs!$C$43,Inputs!$C$105) | E33: =MIN(Inputs!$D$43,Inputs!$C$105) | F33: =MIN(Inputs!$D$43,Inputs!$C$105)
B34: Lifetime value (gross profit basis) | C34: =C31*C33 | D34: =D31*D33 | E34: =E31*E33 | F34: =F31*F33
B35: Cost per acquired customer | C35: =Inputs!$C$68*Inputs!$C$70 | D35: =Inputs!$G$68*Inputs!$C$70 | E35: =Inputs!$C$69*Inputs!$C$70 | F35: =Inputs!$G$69*Inputs!$C$70
B36: LTV / COCA | C36: =IFERROR(C34/C35,0) | D36: =IFERROR(D34/D35,0) | E36: =IFERROR(E34/E35,0) | F36: =IFERROR(F34/F35,0) | J36: A LTV/COCA above 3.0x is the usual threshold for a healthy subscription business. A negative figure means the customer loses money over their life at these assumptions.
B37: Months to pay back the acquisition cost | C37: =IF(C31<=0,"never",C35/C31) | D37: =IF(D31<=0,"never",D35/D31) | E37: =IF(E31<=0,"never",E35/E31) | F37: =IF(F31<=0,"never",F35/F31)
B39: RETURN ON THE FOUNDERS' MONEY
B40: Annual equity cash flow (negative = money in) | C40: Year 1 | D40: Year 2 | E40: Year 3 | F40: Year 4 | G40: Year 5 | H40: Exit
B41: Equity in / exit proceeds out | C41: =-Annual!D42 | D41: =-Annual!E42 | E41: =-Annual!F42 | F41: =-Annual!G42 | G41: =-Annual!H42 | H41: =C48
B43: Total founders' equity invested | C43: =SUM(Annual!D42:H42)
B44: Year 5 net revenue | C44: =Annual!H10
B45: Year 5 EBITDA | C45: =Annual!H20
B46: Exit enterprise value | C46: =IF(Inputs!$C$102=1,Annual!H10*Inputs!$C$103,Annual!H20*Inputs!$C$104) | J46: A convention for framing the return, not a valuation. Set the basis and multiple on Inputs section 11.
B47: Plus year 5 cash, less debt | C47: =Annual!H47 | J47: No debt in this plan — funding is 100% founders' equity.
B48: Exit equity value | C48: =MAX(0,C46+C47)
B49: Money multiple on invested equity | C49: =IFERROR(C48/C43,0) | J49: The money multiple and IRR are driven almost entirely by the exit multiple on Inputs!C103. Treat them as a framing device, not a forecast.
B50: IRR to the founders | C50: =IFERROR(IRR(C41:H41),0) | J50: Injections are treated as start-of-year, the exit as end of year 5.
B51: NPV of the equity cash flows | C51: =C41+NPV(Inputs!$C$101,D41:H41) | J51: Discounted at the rate on Inputs!C101.
B53: YEAR BY YEAR
C54: Year 1 | D54: Year 2 | E54: Year 3 | F54: Year 4 | G54: Year 5
B55: Net revenue | C55: =Annual!D10 | D55: =Annual!E10 | E55: =Annual!F10 | F55: =Annual!G10 | G55: =Annual!H10
B56: EBITDA | C56: =Annual!D20 | D56: =Annual!E20 | E56: =Annual!F20 | F56: =Annual!G20 | G56: =Annual!H20
B57: Net income | C57: =Annual!D25 | D57: =Annual!E25 | E57: =Annual!F25 | F57: =Annual!G25 | G57: =Annual!H25
B58: Free cash flow | C58: =Annual!D40 | D58: =Annual!E40 | E58: =Annual!F40 | F58: =Annual!G40 | G58: =Annual!H40
B59: Founders' equity injected | C59: =Annual!D42 | D59: =Annual!E42 | E59: =Annual!F42 | F59: =Annual!G42 | G59: =Annual!H42
B60: Cash at year end | C60: =Annual!D47 | D60: =Annual!E47 | E60: =Annual!F47 | F60: =Annual!G47 | G60: =Annual!H47
B61: Active customers | C61: =Annual!D31 | D61: =Annual!E31 | E61: =Annual!F31 | F61: =Annual!G31 | G61: =Annual!H31
B63: READ THIS BEFORE QUOTING ANY NUMBER ABOVE
B64: VAT is the biggest change from the MBA model | C64: Neither the plan nor the deck mentions VAT. Treating the listed price as VAT-inclusive removes about 19% of headline revenue in Portugal before any cost. If Revii intends to quote prices ex-VAT instead, set Inputs!C22 and D22 to 0 and every figure above improves sharply.
B65: Voice minutes are the whole margin | C65: The MBA cost of EUR 11.28 per user implies 2.5 minutes a day, not the 5 minutes its own note describes. Doubling minutes roughly doubles cost of service and can take gross margin negative. Measure real call length in a pilot before committing to the price.
B66: Founders are unpaid in every year | C66: Per instruction. Paying a founding team properly would add roughly EUR 150-250k a year from year 2 and would push break-even out materially.
B67: Selling through the app stores would break this | C67: The model assumes web checkout at a 2.5% fee. Apple and Google take 15-30%, which is larger than the entire gross margin at the base price. Bill on the web.
B68: Preventive Care arrives late | C68: The deck puts it 24 months after launch. It carries a far better margin than Voice Care, so pulling it forward on Inputs!C15 is one of the cheapest ways to improve this plan.
B69: Working capital is approximated | C69: Receivables and payables use days ratios; VAT settlement timing is ignored. Fine for sizing, not for a cash-management calendar.
B71: The bars share one axis because both series are euros. Year 1 is short — it contains the build months.
B72: NET REVENUE AND EBITDA BY YEAR (EUR)
B92: Both series are euros on one axis. The blue line is money the founders have put in; the orange line is what the business has generated. Where orange crosses blue, the venture has repaid itself.
B93: CUMULATIVE FOUNDERS' EQUITY IN vs CUMULATIVE FREE CASH FLOW (EUR, by month)

Sheet Scenarios
B2: SCENARIO LEVERS
B3: The ten assumptions that actually move this business. Edit any cell below; the model uses the column chosen on Inputs!C6.
B5: Lever | C5: Unit | D5: 1 Conservative | E5: 2 Base | F5: 3 Optimistic | H5: Why it matters / where the base case comes from
B6: New paying customers in Portugal launch month | C6: cust | D6: 6 | E6: 10 | F6: 16 | H6: MBA model starts Portugal at 10 in month 1. Conservative assumes a slower cold start.
B7: New paying customers in Spain launch month | C7: cust | D7: 8 | E7: 15 | F7: 25 | H7: Spain starts warm: brand, content and playbook already exist from Portugal.
B8: Growth ramp multiplier on monthly new-customer growth | C8: x | D8: 0.7 | E8: 1 | F8: 1.35 | H8: Scales the whole acquisition ramp set on Inputs rows 30-34. 1.00x reproduces the base ramp.
B9: Annual churn rate | C9: % / yr | D9: 0.25 | E9: 0.18 | F9: 0.12 | H9: MBA model assumes 15%/yr. For a EUR 19 consumer subscription that is optimistic, so base is 18%.
B10: Voice Care price (EUR/month, incl. VAT) | C10: EUR | D10: 18.99 | E10: 18.99 | F10: 24.99 | H10: Deck price is 18.99. Survey median willingness to pay for a basic tier was EUR 26 (mean 31), so the optimistic case tests 24.99.
B11: Minutes per AI call | C11: min | D11: 3 | E11: 2.5 | F11: 2 | H11: The MBA COGS of EUR 11.28 implies 2.5 min/day at 1 call/day, despite its note saying '~5 min/day'. This is the assumption to challenge hardest.
B12: Cost per AI voice minute, Year 1 | C12: EUR | D12: 0.18 | E12: 0.15 | F12: 0.08 | H12: MBA model cites Retell at EUR 0.15/min. Optimistic reflects volume pricing and cheaper models.
B13: COCA multiplier on the acquisition cost curve | C13: x | D13: 1.3 | E13: 1 | F13: 0.8 | H13: Scales the cost-per-acquired-customer curve on Inputs rows 62-63.
B14: Preventive Care attach-rate multiplier | C14: x | D14: 0.6 | E14: 1 | F14: 1.4 | H14: Scales the attach curve on Inputs rows 44-45. Preventive is the margin repair, so attach matters more than it looks.
B15: Brand marketing spend multiplier | C15: x | D15: 1 | E15: 1 | F15: 1.2 | H15: Scales the brand/content line in OPEX. Higher spend in the optimistic case funds the faster ramp.
B17: Active scenario | C17: =Inputs!C7 | D17: =INDEX($D$5:$F$5,1,Inputs!C7)
B19: Everything not listed here is on the Inputs sheet and applies to all three scenarios.

Sheet Inputs
B2: VOICE CARE — INPUTS & ASSUMPTIONS
B3: Blue = edit here. Green = pulled from the Scenarios tab. Black = calculated. Yellow fill = the assumptions worth arguing about.
B6: 1 · SCENARIO SELECTOR | I6: Source / rationale
B7: Active scenario (1 = Conservative, 2 = Base, 3 = Optimistic) | C7: 2 | I7: Change this one cell to reprice the whole business.
B8: Scenario in force | C8: =INDEX(Scenarios!$D$5:$F$5,1,$C$7)
B10: 2 · TIMING | I10: Source / rationale
B11: Model horizon (months) | C11: 60 | I11: Five years. Month 1 is the first month of the venture, not the first month of trading.
B12: Product build period before launch (months) | C12: 4 | I12: No revenue during the build. BP tech section sizes the Voice Care build at 3-4 months.
B13: Portugal launch month | C13: =C12+1
B14: Spain launch month | C14: =C13+12 | I14: Twelve months after Portugal, per instruction and the deck (Voice Care Spain: +12 months).
B15: Preventive Care launch month | C15: =C13+24 | I15: Deck slide 25: Preventive Care is a post-launch upgrade at +24 months. Pull this forward to test the margin effect.
B16: Average days per month | C16: 30.44 | I16: 365.25 / 12. Drives voice minutes per month.
B18: 3 · PRICING, VAT & REVENUE LEAKAGE | I18: Source / rationale
C19: Portugal | D19: Spain
B20: Voice Care price (EUR/month, as paid by customer) | C20: =INDEX(Scenarios!$D$10:$F$10,1,$C$7) | D20: =C20 | I20: From the Scenarios tab. Spain is priced identically to Portugal by default.
B21: Preventive Care add-on (EUR/month, as paid) | C21: 8.99 | D21: 8.99 | I21: BP Revenue Architecture: Preventive Care add-on at EUR 8.99, available across all tiers.
B22: Prices include VAT? (1 = yes, 0 = no) | C22: 1 | D22: 1 | I22: Neither the BP nor the deck mentions VAT. Per instruction the listed price is what the end user pays, so it is treated as VAT-inclusive.
B23: VAT rate | C23: 0.23 | D23: 0.21 | I23: Standard rate: Portugal 23%, Spain 21%.
B24: Annual price increase | C24: 0.01 | D24: 0.01 | I24: MBA model escalates Voice Care ~1%/yr (18.99 to 19.76 over five years).
B25: Payment leakage (failed cards, refunds, chargebacks) | C25: 0.04 | D25: 0.04 | I25: 'Details V2' sheet: 3-5% revenue leakage, recommends modelling a 4% haircut.
B26: Billing / payment channel fee | C26: 0.025 | D26: 0.025 | I26: Assumes web checkout (Stripe ~2.5%). Selling through the app stores instead would cost 15-30% and break the model — see Dashboard note.
B27: Net revenue retained per EUR 1 billed | C27: =IF(C22=1,1/(1+C23),1)*(1-C25)*(1-C26) | D27: =IF(D22=1,1/(1+D23),1)*(1-D25)*(1-D26) | I27: The gap between headline price and money actually earned.
B28: Net revenue per customer, Year 1 (EUR/month) | C28: =C20*C27 | D28: =D20*D27
B30: 4 · CUSTOMER GROWTH & RETENTION | I30: Source / rationale
C31: Portugal | D31: Spain
B32: New paying customers in the launch month | C32: =INDEX(Scenarios!$D$6:$F$6,1,$C$7) | D32: =INDEX(Scenarios!$D$7:$F$7,1,$C$7) | I32: MBA growth sheet opens Portugal at 10 customers in month 1.
B33: Monthly growth in new customer additions, by year in that market:
B34: Market year 1 | C34: 0.2 | D34: 0.2 | I34: The acquisition ramp. MBA model uses a decaying-rate curve; this is the same shape expressed as a growth rate you can type over.
B35: Market year 2 | C35: 0.07 | D35: 0.07
B36: Market year 3 | C36: 0.04 | D36: 0.04
B37: Market year 4 | C37: 0.025 | D37: 0.025
B38: Market year 5 | C38: 0.015 | D38: 0.015
B39: Growth ramp multiplier (scenario) | C39: =INDEX(Scenarios!$D$8:$F$8,1,$C$7) | I39: Scales all five growth rates above at once.
B40: Cap on new customers per month | C40: 500 | D40: 1000 | I40: A sanity ceiling so an aggressive ramp cannot compound to absurdity.
B41: Annual churn rate | C41: =INDEX(Scenarios!$D$9:$F$9,1,$C$7) | D41: =C41 | I41: MBA model assumes 15%/yr for Voice Care. Base case here is 18%.
B42: Monthly churn (calculated) | C42: =1-(1-C41)^(1/12) | D42: =1-(1-D41)^(1/12)
B43: Implied average customer life (months) | C43: =1/C42 | D43: =1/D42
B44: Free trial length (days) | C44: 14 | D44: 14 | I44: BP Layer 1 go-to-market relies on a time-limited free trial. The BP never costs it; this model does.
B45: Trial to paid conversion | C45: 0.35 | D45: 0.35 | I45: Drives how many un-monetised trial minutes are burned per paying customer won.
B47: 5 · PREVENTIVE CARE ATTACH | I47: Source / rationale
B48: Years since that market launched | C48: Year 1 | D48: Year 2 | E48: Year 3 | F48: Year 4 | G48: Year 5
B49: Portugal — % of active customers taking Preventive | C49: 0 | D49: 0 | E49: 0.1 | F49: 0.2 | G49: 0.3 | I49: No published attach data exists. These are placeholders and deserve a hard look — Preventive is what repairs the Voice Care margin.
B50: Spain — % of active customers taking Preventive | C50: 0 | D50: 0 | E50: 0.1 | F50: 0.2 | G50: 0.3
B51: Attach-rate multiplier (scenario) | C51: =INDEX(Scenarios!$D$14:$F$14,1,$C$7)
B52: Preventive Care variable cost (EUR/user/month) | C52: 3.6 | I52: BP Financial Plan: EUR 3.60 variable cost, ~60% operating margin on the add-on.
B54: 6 · VOICE AI COST ENGINE — the core economics | I54: Source / rationale
B55: AI calls per customer per day | C55: 1 | I55: 'Details V2': 1 interaction per day.
B56: Minutes per call | C56: =INDEX(Scenarios!$D$11:$F$11,1,$C$7) | I56: The MBA sheet says '~5 minutes/day' but its EUR 11.25 cost is 75 min/month = 2.5 min/day. At a true 5 min/day the gross margin goes negative. This is the number to verify in a pilot.
B57: Voice minutes per customer per month | C57: =C55*C56*C16
B58: Cost per voice minute, Year 1 (EUR) | C58: =INDEX(Scenarios!$D$12:$F$12,1,$C$7) | I58: MBA model cites Retell AI at EUR 0.15/min.
B59: Annual change in cost per minute | C59: -0.15 | I59: Inference costs have fallen steadily. A -15%/yr glide is deliberate but assumed, not sourced.
B60: Model year | C60: Year 1 | D60: Year 2 | E60: Year 3 | F60: Year 4 | G60: Year 5
B61: Cost per minute by model year (EUR) | C61: =$C$58 | D61: =C61*(1+$C$59) | E61: =D61*(1+$C$59) | F61: =E61*(1+$C$59) | G61: =F61*(1+$C$59)
B62: Data & storage (EUR/user/month) | C62: 0.03 | I62: 'Details V2': 72 MB/month of call data at Google Cloud Storage rates.
B63: AI cost per paying customer, Year 1 (EUR/month) | C63: =C57*C58+C62 | I63: Compare against net revenue per customer above. That difference is the whole business.
B64: Gross margin per Portugal customer, Year 1 | C64: =IFERROR(1-C63/C28,0)
B66: 7 · CUSTOMER ACQUISITION COST | I66: Source / rationale
B67: Years since that market launched | C67: Year 1 | D67: Year 2 | E67: Year 3 | F67: Year 4 | G67: Year 5
B68: Portugal — cost per acquired customer (EUR) | C68: 38 | D68: 32 | E68: 26 | F68: 22 | G68: 20 | I68: MBA growth sheet: COCA decays from EUR 37.98 to EUR 21.36 as organic and referral channels mature.
B69: Spain — cost per acquired customer (EUR) | C69: 38 | D69: 32 | E69: 26 | F69: 22 | G69: 20
B70: COCA multiplier (scenario) | C70: =INDEX(Scenarios!$D$13:$F$13,1,$C$7)
B72: 8 · OPERATING EXPENSES (EUR per month, by model year) | I72: Source / rationale
B73: Model year | C73: Year 1 | D73: Year 2 | E73: Year 3 | F73: Year 4 | G73: Year 5
B74: Founders' salaries (all founders) | C74: 0 | D74: 0 | E74: 0 | F74: 0 | G74: 0 | I74: Zero, per instruction. A normally-paid founding team would add roughly EUR 150-250k a year from Year 2 and would materially change the equity requirement.
B75: Developer / platform maintenance | C75: 1500 | D75: 4000 | E75: 8000 | F75: 12000 | G75: 16000 | I75: 'Details V2' lean case: EUR 1,500-4,500/month part-time maintenance. Scaled up as the base grows.
B76: Customer support | C76: 0 | D76: 1200 | E76: 3000 | F76: 5000 | G76: 7000 | I76: 'Details V2': EUR 800-1,200/month part-time to start. BP has support part-time from Year 2.
B77: Brand marketing & content (excludes COCA) | C77: 1000 | D77: 2500 | E77: 5000 | F77: 7000 | G77: 9000 | I77: Deliberately a fraction of the BP's EUR 500k Year 1 brand budget, which assumed a funded launch. Multiplied by the scenario marketing lever.
B78: Cloud & tools (non-usage infrastructure) | C78: 250 | D78: 400 | E78: 700 | F78: 1000 | G78: 1400 | I78: 'Details V2': GCP base, monitoring and logging. Usage-driven AI cost sits in COGS, not here.
B79: Accounting, admin & legal | C79: 400 | D79: 500 | E79: 700 | F79: 900 | G79: 1100
B80: Insurance (professional liability + cyber) | C80: 0 | D80: 625 | E80: 625 | F80: 750 | G80: 900 | I80: 'Details V2': EUR 4,000 liability + EUR 3,500 cyber per year, from the first year of trading.
B81: Office / co-working | C81: 0 | D81: 300 | E81: 600 | F81: 900 | G81: 1200 | I81: Remote to start; BP assumes EUR 3,000/month office, which a founder-led launch does not need.
B82: Spain local lead & market management | C82: 0 | D82: 1500 | E82: 3000 | F82: 4000 | G82: 5000 | I82: BP Place section: marketing must be run locally in each market. Charged only from the Spain launch month.
B83: Other / contingency | C83: 200 | D83: 400 | E83: 800 | F83: 1200 | G83: 1600
B85: 9 · CAPITAL EXPENDITURE & DEPRECIATION | I85: Source / rationale
B86: Voice Care platform build (EUR) | C86: 46000 | I86: MBA model, Voice Care R&D line. An AI-native build was costed at EUR 38,000 in 'Details V2'. Spread evenly across the build months.
B87: Preventive Care module build (EUR) | C87: 24250 | I87: MBA model, Preventive Care CAPEX. Incurred in its launch month.
B88: Spain localisation & compliance (EUR) | C88: 10000 | I88: Not in the MBA model. Added here: Spanish-language voice models, legal, local payment setup.
B89: Ongoing development capex, % of cumulative build per year | C89: 0.2 | I89: MBA model applies 20% of initial R&D per year as maintenance capex.
B90: Depreciation period (years, straight line) | C90: 5 | I90: MBA model depreciates R&D over 5 years.
B92: 10 · WORKING CAPITAL & CASH | I92: Source / rationale
B93: Receivable days | C93: 5 | I93: Card-on-file subscriptions settle in days, not months.
B94: Payable days | C94: 30 | I94: Applied to cost of service and cash operating costs.
B95: % of new customers taking an annual prepaid plan | C95: 0 | I95: A real self-funding lever: annual prepay pulls twelve months of cash forward and cuts the equity needed. Base case is 0% so the result is not flattered.
B96: Discount offered on the annual prepaid plan | C96: 0.15
B97: Minimum cash buffer to hold (EUR) | C97: 15000 | I97: Founders top up to this level each month. Sets the floor for the equity requirement.
B99: 11 · TAX, FUNDING & RETURN | I99: Source / rationale
B100: Corporate tax rate | C100: 0.19 | I100: MBA model assumes 19%. Losses are carried forward without limit.
B101: Discount rate for NPV | C101: 0.12 | I101: MBA sheets use 12% (older) and 11.5% WACC (DCF). For an unfunded pre-revenue venture this is generous.
B102: Exit basis (1 = multiple of Year 5 revenue, 2 = multiple of Year 5 EBITDA) | C102: 1
B103: Exit multiple — times Year 5 net revenue | C103: 3 | I103: A convention for a subscription business, not a valuation. Change it and the IRR changes with it.
B104: Exit multiple — times Year 5 EBITDA | C104: 8
B105: Cap on the LTV horizon (months) | C105: 36 | I105: At 18% annual churn the implied average customer life is 61 months. Valuing five years of an unproven subscription is not credible, so lifetime value is capped at this horizon.
B106: Funding structure: 100% founders' equity — no debt, no grant, no external round.
B107: Equity is injected month by month, only as much as is needed to hold the minimum cash buffer. The total injected is the investment figure on the Dashboard.

Sheet Model PT
B2: PORTUGAL — VOICE CARE MONTHLY MODEL
B3: Monthly engine. Every driver comes from the Inputs sheet — nothing is hardcoded here.
B4: Month | C4: Unit | D4: 1 | E4: 2 | F4: 3 | G4: 4 | H4: 5 | I4: 6 | J4: 7 | K4: 8 | L4: 9 | M4: 10 | N4: 11 | O4: 12 | P4: 13 | Q4: 14 | R4: 15 | S4: 16 | T4: 17 | U4: 18 | V4: 19 | W4: 20 | X4: 21 | Y4: 22 | Z4: 23 | AA4: 24 | AB4: 25 | AC4: 26 | AD4: 27 | AE4: 28 | AF4: 29 | AG4: 30 | AH4: 31 | AI4: 32 | AJ4: 33 | AK4: 34 | AL4: 35 | AM4: 36 | AN4: 37 | AO4: 38 | AP4: 39 | AQ4: 40 | AR4: 41 | AS4: 42 | AT4: 43 | AU4: 44 | AV4: 45 | AW4: 46 | AX4: 47 | AY4: 48 | AZ4: 49 | BA4: 50 | BB4: 51 | BC4: 52 | BD4: 53 | BE4: 54 | BF4: 55 | BG4: 56 | BH4: 57 | BI4: 58 | BJ4: 59 | BK4: 60
B5: Model year | C5: yr | D5: =MIN(5,INT((D4-1)/12)+1) | E5: =MIN(5,INT((E4-1)/12)+1) | F5: =MIN(5,INT((F4-1)/12)+1) | G5: =MIN(5,INT((G4-1)/12)+1) | H5: =MIN(5,INT((H4-1)/12)+1) | I5: =MIN(5,INT((I4-1)/12)+1) | J5: =MIN(5,INT((J4-1)/12)+1) | K5: =MIN(5,INT((K4-1)/12)+1) | ... BK5: =MIN(5,INT((BK4-1)/12)+1)
B6: Months since this market launched | C6: mo | D6: =IF(D4<Inputs!$C$13,0,D4-Inputs!$C$13+1) | E6: =IF(E4<Inputs!$C$13,0,E4-Inputs!$C$13+1) | F6: =IF(F4<Inputs!$C$13,0,F4-Inputs!$C$13+1) | G6: =IF(G4<Inputs!$C$13,0,G4-Inputs!$C$13+1) | H6: =IF(H4<Inputs!$C$13,0,H4-Inputs!$C$13+1) | I6: =IF(I4<Inputs!$C$13,0,I4-Inputs!$C$13+1) | J6: =IF(J4<Inputs!$C$13,0,J4-Inputs!$C$13+1) | K6: =IF(K4<Inputs!$C$13,0,K4-Inputs!$C$13+1) | ... BK6: =IF(BK4<Inputs!$C$13,0,BK4-Inputs!$C$13+1)
B7: Market year | C7: yr | D7: =IF(D6=0,0,MIN(5,INT((D6-1)/12)+1)) | E7: =IF(E6=0,0,MIN(5,INT((E6-1)/12)+1)) | F7: =IF(F6=0,0,MIN(5,INT((F6-1)/12)+1)) | G7: =IF(G6=0,0,MIN(5,INT((G6-1)/12)+1)) | H7: =IF(H6=0,0,MIN(5,INT((H6-1)/12)+1)) | I7: =IF(I6=0,0,MIN(5,INT((I6-1)/12)+1)) | J7: =IF(J6=0,0,MIN(5,INT((J6-1)/12)+1)) | K7: =IF(K6=0,0,MIN(5,INT((K6-1)/12)+1)) | ... BK7: =IF(BK6=0,0,MIN(5,INT((BK6-1)/12)+1))
B9: CUSTOMERS
B10: Opening active customers | C10: cust | D10: =0 | E10: =D13 | F10: =E13 | G10: =F13 | H10: =G13 | I10: =H13 | J10: =I13 | K10: =J13 | L10: =K13 | ... BK10: =BJ13
B11: New paying customers | C11: cust | D11: =IF(D6=1,Inputs!$C$32,0) | E11: =IF(E6<1,0,IF(E6=1,Inputs!$C$32,MIN(Inputs!$C$40,D11*(1+INDEX(Inputs!$C$34:$C$38,E7)*Inputs!$C$39)))) | F11: =IF(F6<1,0,IF(F6=1,Inputs!$C$32,MIN(Inputs!$C$40,E11*(1+INDEX(Inputs!$C$34:$C$38,F7)*Inputs!$C$39)))) | G11: =IF(G6<1,0,IF(G6=1,Inputs!$C$32,MIN(Inputs!$C$40,F11*(1+INDEX(Inputs!$C$34:$C$38,G7)*Inputs!$C$39)))) | H11: =IF(H6<1,0,IF(H6=1,Inputs!$C$32,MIN(Inputs!$C$40,G11*(1+INDEX(Inputs!$C$34:$C$38,H7)*Inputs!$C$39)))) | I11: =IF(I6<1,0,IF(I6=1,Inputs!$C$32,MIN(Inputs!$C$40,H11*(1+INDEX(Inputs!$C$34:$C$38,I7)*Inputs!$C$39)))) | J11: =IF(J6<1,0,IF(J6=1,Inputs!$C$32,MIN(Inputs!$C$40,I11*(1+INDEX(Inputs!$C$34:$C$38,J7)*Inputs!$C$39)))) | K11: =IF(K6<1,0,IF(K6=1,Inputs!$C$32,MIN(Inputs!$C$40,J11*(1+INDEX(Inputs!$C$34:$C$38,K7)*Inputs!$C$39)))) | L11: =IF(L6<1,0,IF(L6=1,Inputs!$C$32,MIN(Inputs!$C$40,K11*(1+INDEX(Inputs!$C$34:$C$38,L7)*Inputs!$C$39)))) | ... BK11: =IF(BK6<1,0,IF(BK6=1,Inputs!$C$32,MIN(Inputs!$C$40,BJ11*(1+INDEX(Inputs!$C$34:$C$38,BK7)*Inputs!$C$39))))
B12: Customers lost to churn | C12: cust | D12: =-D10*Inputs!$C$42 | E12: =-E10*Inputs!$C$42 | F12: =-F10*Inputs!$C$42 | G12: =-G10*Inputs!$C$42 | H12: =-H10*Inputs!$C$42 | I12: =-I10*Inputs!$C$42 | J12: =-J10*Inputs!$C$42 | K12: =-K10*Inputs!$C$42 | ... BK12: =-BK10*Inputs!$C$42
B13: Closing active customers | C13: cust | D13: =D10+D11+D12 | E13: =E10+E11+E12 | F13: =F10+F11+F12 | G13: =G10+G11+G12 | H13: =H10+H11+H12 | I13: =I10+I11+I12 | J13: =J10+J11+J12 | K13: =K10+K11+K12 | ... BK13: =BK10+BK11+BK12
B14: Average active customers | C14: cust | D14: =(D10+D13)/2 | E14: =(E10+E13)/2 | F14: =(F10+F13)/2 | G14: =(G10+G13)/2 | H14: =(H10+H13)/2 | I14: =(I10+I13)/2 | J14: =(J10+J13)/2 | K14: =(K10+K13)/2 | ... BK14: =(BK10+BK13)/2
B15: Free trials started | C15: trials | D15: =IFERROR(D11/Inputs!$C$45,0) | E15: =IFERROR(E11/Inputs!$C$45,0) | F15: =IFERROR(F11/Inputs!$C$45,0) | G15: =IFERROR(G11/Inputs!$C$45,0) | H15: =IFERROR(H11/Inputs!$C$45,0) | I15: =IFERROR(I11/Inputs!$C$45,0) | J15: =IFERROR(J11/Inputs!$C$45,0) | K15: =IFERROR(K11/Inputs!$C$45,0) | ... BK15: =IFERROR(BK11/Inputs!$C$45,0)
B17: REVENUE (EUR)
B18: Voice Care price (indexed) | C18: EUR | D18: =Inputs!$C$20*(1+Inputs!$C$24)^(D5-1) | E18: =Inputs!$C$20*(1+Inputs!$C$24)^(E5-1) | F18: =Inputs!$C$20*(1+Inputs!$C$24)^(F5-1) | G18: =Inputs!$C$20*(1+Inputs!$C$24)^(G5-1) | H18: =Inputs!$C$20*(1+Inputs!$C$24)^(H5-1) | I18: =Inputs!$C$20*(1+Inputs!$C$24)^(I5-1) | J18: =Inputs!$C$20*(1+Inputs!$C$24)^(J5-1) | K18: =Inputs!$C$20*(1+Inputs!$C$24)^(K5-1) | ... BK18: =Inputs!$C$20*(1+Inputs!$C$24)^(BK5-1)
B19: Preventive Care price (indexed) | C19: EUR | D19: =Inputs!$C$21*(1+Inputs!$C$24)^(D5-1) | E19: =Inputs!$C$21*(1+Inputs!$C$24)^(E5-1) | F19: =Inputs!$C$21*(1+Inputs!$C$24)^(F5-1) | G19: =Inputs!$C$21*(1+Inputs!$C$24)^(G5-1) | H19: =Inputs!$C$21*(1+Inputs!$C$24)^(H5-1) | I19: =Inputs!$C$21*(1+Inputs!$C$24)^(I5-1) | J19: =Inputs!$C$21*(1+Inputs!$C$24)^(J5-1) | K19: =Inputs!$C$21*(1+Inputs!$C$24)^(K5-1) | ... BK19: =Inputs!$C$21*(1+Inputs!$C$24)^(BK5-1)
B20: Preventive Care attach rate | C20: % | D20: =IF(OR(D7=0,D4<Inputs!$C$15),0,INDEX(Inputs!$C$49:$G$49,1,D7)*Inputs!$C$51) | E20: =IF(OR(E7=0,E4<Inputs!$C$15),0,INDEX(Inputs!$C$49:$G$49,1,E7)*Inputs!$C$51) | F20: =IF(OR(F7=0,F4<Inputs!$C$15),0,INDEX(Inputs!$C$49:$G$49,1,F7)*Inputs!$C$51) | G20: =IF(OR(G7=0,G4<Inputs!$C$15),0,INDEX(Inputs!$C$49:$G$49,1,G7)*Inputs!$C$51) | H20: =IF(OR(H7=0,H4<Inputs!$C$15),0,INDEX(Inputs!$C$49:$G$49,1,H7)*Inputs!$C$51) | I20: =IF(OR(I7=0,I4<Inputs!$C$15),0,INDEX(Inputs!$C$49:$G$49,1,I7)*Inputs!$C$51) | J20: =IF(OR(J7=0,J4<Inputs!$C$15),0,INDEX(Inputs!$C$49:$G$49,1,J7)*Inputs!$C$51) | K20: =IF(OR(K7=0,K4<Inputs!$C$15),0,INDEX(Inputs!$C$49:$G$49,1,K7)*Inputs!$C$51) | ... BK20: =IF(OR(BK7=0,BK4<Inputs!$C$15),0,INDEX(Inputs!$C$49:$G$49,1,BK7)*Inputs!$C$51)
B21: Gross billings — Voice Care | C21: EUR | D21: =D14*D18 | E21: =E14*E18 | F21: =F14*F18 | G21: =G14*G18 | H21: =H14*H18 | I21: =I14*I18 | J21: =J14*J18 | K21: =K14*K18 | ... BK21: =BK14*BK18
B22: Gross billings — Preventive Care | C22: EUR | D22: =D14*D20*D19 | E22: =E14*E20*E19 | F22: =F14*F20*F19 | G22: =G14*G20*G19 | H22: =H14*H20*H19 | I22: =I14*I20*I19 | J22: =J14*J20*J19 | K22: =K14*K20*K19 | ... BK22: =BK14*BK20*BK19
B23: Total gross billings (what customers pay) | C23: EUR | D23: =D21+D22 | E23: =E21+E22 | F23: =F21+F22 | G23: =G21+G22 | H23: =H21+H22 | I23: =I21+I22 | J23: =J21+J22 | K23: =K21+K22 | ... BK23: =BK21+BK22
B24: Net revenue — Voice Care | C24: EUR | D24: =D21*Inputs!$C$27 | E24: =E21*Inputs!$C$27 | F24: =F21*Inputs!$C$27 | G24: =G21*Inputs!$C$27 | H24: =H21*Inputs!$C$27 | I24: =I21*Inputs!$C$27 | J24: =J21*Inputs!$C$27 | K24: =K21*Inputs!$C$27 | ... BK24: =BK21*Inputs!$C$27
B25: Net revenue — Preventive Care | C25: EUR | D25: =D22*Inputs!$C$27 | E25: =E22*Inputs!$C$27 | F25: =F22*Inputs!$C$27 | G25: =G22*Inputs!$C$27 | H25: =H22*Inputs!$C$27 | I25: =I22*Inputs!$C$27 | J25: =J22*Inputs!$C$27 | K25: =K22*Inputs!$C$27 | ... BK25: =BK22*Inputs!$C$27
B26: Total net revenue | C26: EUR | D26: =D24+D25 | E26: =E24+E25 | F26: =F24+F25 | G26: =G24+G25 | H26: =H24+H25 | I26: =I24+I25 | J26: =J24+J25 | K26: =K24+K25 | ... BK26: =BK24+BK25
B28: COST OF SERVICE (EUR)
B29: Cost per voice minute | C29: EUR | D29: =INDEX(Inputs!$C$61:$G$61,1,D5) | E29: =INDEX(Inputs!$C$61:$G$61,1,E5) | F29: =INDEX(Inputs!$C$61:$G$61,1,F5) | G29: =INDEX(Inputs!$C$61:$G$61,1,G5) | H29: =INDEX(Inputs!$C$61:$G$61,1,H5) | I29: =INDEX(Inputs!$C$61:$G$61,1,I5) | J29: =INDEX(Inputs!$C$61:$G$61,1,J5) | K29: =INDEX(Inputs!$C$61:$G$61,1,K5) | ... BK29: =INDEX(Inputs!$C$61:$G$61,1,BK5)
B30: AI voice — paying customers | C30: EUR | D30: =D14*Inputs!$C$57*D29 | E30: =E14*Inputs!$C$57*E29 | F30: =F14*Inputs!$C$57*F29 | G30: =G14*Inputs!$C$57*G29 | H30: =H14*Inputs!$C$57*H29 | I30: =I14*Inputs!$C$57*I29 | J30: =J14*Inputs!$C$57*J29 | K30: =K14*Inputs!$C$57*K29 | ... BK30: =BK14*Inputs!$C$57*BK29
B31: AI voice — free trials | C31: EUR | D31: =D15*Inputs!$C$44*Inputs!$C$55*Inputs!$C$56*D29 | E31: =E15*Inputs!$C$44*Inputs!$C$55*Inputs!$C$56*E29 | F31: =F15*Inputs!$C$44*Inputs!$C$55*Inputs!$C$56*F29 | G31: =G15*Inputs!$C$44*Inputs!$C$55*Inputs!$C$56*G29 | H31: =H15*Inputs!$C$44*Inputs!$C$55*Inputs!$C$56*H29 | I31: =I15*Inputs!$C$44*Inputs!$C$55*Inputs!$C$56*I29 | J31: =J15*Inputs!$C$44*Inputs!$C$55*Inputs!$C$56*J29 | K31: =K15*Inputs!$C$44*Inputs!$C$55*Inputs!$C$56*K29 | ... BK31: =BK15*Inputs!$C$44*Inputs!$C$55*Inputs!$C$56*BK29
B32: Data & storage | C32: EUR | D32: =D14*Inputs!$C$62 | E32: =E14*Inputs!$C$62 | F32: =F14*Inputs!$C$62 | G32: =G14*Inputs!$C$62 | H32: =H14*Inputs!$C$62 | I32: =I14*Inputs!$C$62 | J32: =J14*Inputs!$C$62 | K32: =K14*Inputs!$C$62 | ... BK32: =BK14*Inputs!$C$62
B33: Preventive Care variable cost | C33: EUR | D33: =D14*D20*Inputs!$C$52 | E33: =E14*E20*Inputs!$C$52 | F33: =F14*F20*Inputs!$C$52 | G33: =G14*G20*Inputs!$C$52 | H33: =H14*H20*Inputs!$C$52 | I33: =I14*I20*Inputs!$C$52 | J33: =J14*J20*Inputs!$C$52 | K33: =K14*K20*Inputs!$C$52 | ... BK33: =BK14*BK20*Inputs!$C$52
B34: Total cost of service | C34: EUR | D34: =SUM(D30:D33) | E34: =SUM(E30:E33) | F34: =SUM(F30:F33) | G34: =SUM(G30:G33) | H34: =SUM(H30:H33) | I34: =SUM(I30:I33) | J34: =SUM(J30:J33) | K34: =SUM(K30:K33) | ... BK34: =SUM(BK30:BK33)
B35: Gross profit | C35: EUR | D35: =D26-D34 | E35: =E26-E34 | F35: =F26-F34 | G35: =G26-G34 | H35: =H26-H34 | I35: =I26-I34 | J35: =J26-J34 | K35: =K26-K34 | ... BK35: =BK26-BK34
B36: Gross margin | C36: % | D36: =IFERROR(D35/D26,0) | E36: =IFERROR(E35/E26,0) | F36: =IFERROR(F35/F26,0) | G36: =IFERROR(G35/G26,0) | H36: =IFERROR(H35/H26,0) | I36: =IFERROR(I35/I26,0) | J36: =IFERROR(J35/J26,0) | K36: =IFERROR(K35/K26,0) | ... BK36: =IFERROR(BK35/BK26,0)
B38: CUSTOMER ACQUISITION (EUR)
B39: Cost per acquired customer | C39: EUR | D39: =IF(D7=0,0,INDEX(Inputs!$C$68:$G$68,1,D7)*Inputs!$C$70) | E39: =IF(E7=0,0,INDEX(Inputs!$C$68:$G$68,1,E7)*Inputs!$C$70) | F39: =IF(F7=0,0,INDEX(Inputs!$C$68:$G$68,1,F7)*Inputs!$C$70) | G39: =IF(G7=0,0,INDEX(Inputs!$C$68:$G$68,1,G7)*Inputs!$C$70) | H39: =IF(H7=0,0,INDEX(Inputs!$C$68:$G$68,1,H7)*Inputs!$C$70) | I39: =IF(I7=0,0,INDEX(Inputs!$C$68:$G$68,1,I7)*Inputs!$C$70) | J39: =IF(J7=0,0,INDEX(Inputs!$C$68:$G$68,1,J7)*Inputs!$C$70) | K39: =IF(K7=0,0,INDEX(Inputs!$C$68:$G$68,1,K7)*Inputs!$C$70) | ... BK39: =IF(BK7=0,0,INDEX(Inputs!$C$68:$G$68,1,BK7)*Inputs!$C$70)
B40: Acquisition spend | C40: EUR | D40: =D11*D39 | E40: =E11*E39 | F40: =F11*F39 | G40: =G11*G39 | H40: =H11*H39 | I40: =I11*I39 | J40: =J11*J39 | K40: =K11*K39 | ... BK40: =BK11*BK39
B41: Contribution after acquisition | C41: EUR | D41: =D35-D40 | E41: =E35-E40 | F41: =F35-F40 | G41: =G35-G40 | H41: =H35-H40 | I41: =I35-I40 | J41: =J35-J40 | K41: =K35-K40 | ... BK41: =BK35-BK40

Sheet Model ES
B2: SPAIN — VOICE CARE MONTHLY MODEL
B3: Monthly engine. Every driver comes from the Inputs sheet — nothing is hardcoded here.
B4: Month | C4: Unit | D4: 1 | E4: 2 | F4: 3 | G4: 4 | H4: 5 | I4: 6 | J4: 7 | K4: 8 | L4: 9 | M4: 10 | N4: 11 | O4: 12 | P4: 13 | Q4: 14 | R4: 15 | S4: 16 | T4: 17 | U4: 18 | V4: 19 | W4: 20 | X4: 21 | Y4: 22 | Z4: 23 | AA4: 24 | AB4: 25 | AC4: 26 | AD4: 27 | AE4: 28 | AF4: 29 | AG4: 30 | AH4: 31 | AI4: 32 | AJ4: 33 | AK4: 34 | AL4: 35 | AM4: 36 | AN4: 37 | AO4: 38 | AP4: 39 | AQ4: 40 | AR4: 41 | AS4: 42 | AT4: 43 | AU4: 44 | AV4: 45 | AW4: 46 | AX4: 47 | AY4: 48 | AZ4: 49 | BA4: 50 | BB4: 51 | BC4: 52 | BD4: 53 | BE4: 54 | BF4: 55 | BG4: 56 | BH4: 57 | BI4: 58 | BJ4: 59 | BK4: 60
B5: Model year | C5: yr | D5: =MIN(5,INT((D4-1)/12)+1) | E5: =MIN(5,INT((E4-1)/12)+1) | F5: =MIN(5,INT((F4-1)/12)+1) | G5: =MIN(5,INT((G4-1)/12)+1) | H5: =MIN(5,INT((H4-1)/12)+1) | I5: =MIN(5,INT((I4-1)/12)+1) | J5: =MIN(5,INT((J4-1)/12)+1) | K5: =MIN(5,INT((K4-1)/12)+1) | ... BK5: =MIN(5,INT((BK4-1)/12)+1)
B6: Months since this market launched | C6: mo | D6: =IF(D4<Inputs!$C$14,0,D4-Inputs!$C$14+1) | E6: =IF(E4<Inputs!$C$14,0,E4-Inputs!$C$14+1) | F6: =IF(F4<Inputs!$C$14,0,F4-Inputs!$C$14+1) | G6: =IF(G4<Inputs!$C$14,0,G4-Inputs!$C$14+1) | H6: =IF(H4<Inputs!$C$14,0,H4-Inputs!$C$14+1) | I6: =IF(I4<Inputs!$C$14,0,I4-Inputs!$C$14+1) | J6: =IF(J4<Inputs!$C$14,0,J4-Inputs!$C$14+1) | K6: =IF(K4<Inputs!$C$14,0,K4-Inputs!$C$14+1) | ... BK6: =IF(BK4<Inputs!$C$14,0,BK4-Inputs!$C$14+1)
B7: Market year | C7: yr | D7: =IF(D6=0,0,MIN(5,INT((D6-1)/12)+1)) | E7: =IF(E6=0,0,MIN(5,INT((E6-1)/12)+1)) | F7: =IF(F6=0,0,MIN(5,INT((F6-1)/12)+1)) | G7: =IF(G6=0,0,MIN(5,INT((G6-1)/12)+1)) | H7: =IF(H6=0,0,MIN(5,INT((H6-1)/12)+1)) | I7: =IF(I6=0,0,MIN(5,INT((I6-1)/12)+1)) | J7: =IF(J6=0,0,MIN(5,INT((J6-1)/12)+1)) | K7: =IF(K6=0,0,MIN(5,INT((K6-1)/12)+1)) | ... BK7: =IF(BK6=0,0,MIN(5,INT((BK6-1)/12)+1))
B9: CUSTOMERS
B10: Opening active customers | C10: cust | D10: =0 | E10: =D13 | F10: =E13 | G10: =F13 | H10: =G13 | I10: =H13 | J10: =I13 | K10: =J13 | L10: =K13 | ... BK10: =BJ13
B11: New paying customers | C11: cust | D11: =IF(D6=1,Inputs!$D$32,0) | E11: =IF(E6<1,0,IF(E6=1,Inputs!$D$32,MIN(Inputs!$D$40,D11*(1+INDEX(Inputs!$D$34:$D$38,E7)*Inputs!$C$39)))) | F11: =IF(F6<1,0,IF(F6=1,Inputs!$D$32,MIN(Inputs!$D$40,E11*(1+INDEX(Inputs!$D$34:$D$38,F7)*Inputs!$C$39)))) | G11: =IF(G6<1,0,IF(G6=1,Inputs!$D$32,MIN(Inputs!$D$40,F11*(1+INDEX(Inputs!$D$34:$D$38,G7)*Inputs!$C$39)))) | H11: =IF(H6<1,0,IF(H6=1,Inputs!$D$32,MIN(Inputs!$D$40,G11*(1+INDEX(Inputs!$D$34:$D$38,H7)*Inputs!$C$39)))) | I11: =IF(I6<1,0,IF(I6=1,Inputs!$D$32,MIN(Inputs!$D$40,H11*(1+INDEX(Inputs!$D$34:$D$38,I7)*Inputs!$C$39)))) | J11: =IF(J6<1,0,IF(J6=1,Inputs!$D$32,MIN(Inputs!$D$40,I11*(1+INDEX(Inputs!$D$34:$D$38,J7)*Inputs!$C$39)))) | K11: =IF(K6<1,0,IF(K6=1,Inputs!$D$32,MIN(Inputs!$D$40,J11*(1+INDEX(Inputs!$D$34:$D$38,K7)*Inputs!$C$39)))) | L11: =IF(L6<1,0,IF(L6=1,Inputs!$D$32,MIN(Inputs!$D$40,K11*(1+INDEX(Inputs!$D$34:$D$38,L7)*Inputs!$C$39)))) | ... BK11: =IF(BK6<1,0,IF(BK6=1,Inputs!$D$32,MIN(Inputs!$D$40,BJ11*(1+INDEX(Inputs!$D$34:$D$38,BK7)*Inputs!$C$39))))
B12: Customers lost to churn | C12: cust | D12: =-D10*Inputs!$D$42 | E12: =-E10*Inputs!$D$42 | F12: =-F10*Inputs!$D$42 | G12: =-G10*Inputs!$D$42 | H12: =-H10*Inputs!$D$42 | I12: =-I10*Inputs!$D$42 | J12: =-J10*Inputs!$D$42 | K12: =-K10*Inputs!$D$42 | ... BK12: =-BK10*Inputs!$D$42
B13: Closing active customers | C13: cust | D13: =D10+D11+D12 | E13: =E10+E11+E12 | F13: =F10+F11+F12 | G13: =G10+G11+G12 | H13: =H10+H11+H12 | I13: =I10+I11+I12 | J13: =J10+J11+J12 | K13: =K10+K11+K12 | ... BK13: =BK10+BK11+BK12
B14: Average active customers | C14: cust | D14: =(D10+D13)/2 | E14: =(E10+E13)/2 | F14: =(F10+F13)/2 | G14: =(G10+G13)/2 | H14: =(H10+H13)/2 | I14: =(I10+I13)/2 | J14: =(J10+J13)/2 | K14: =(K10+K13)/2 | ... BK14: =(BK10+BK13)/2
B15: Free trials started | C15: trials | D15: =IFERROR(D11/Inputs!$D$45,0) | E15: =IFERROR(E11/Inputs!$D$45,0) | F15: =IFERROR(F11/Inputs!$D$45,0) | G15: =IFERROR(G11/Inputs!$D$45,0) | H15: =IFERROR(H11/Inputs!$D$45,0) | I15: =IFERROR(I11/Inputs!$D$45,0) | J15: =IFERROR(J11/Inputs!$D$45,0) | K15: =IFERROR(K11/Inputs!$D$45,0) | ... BK15: =IFERROR(BK11/Inputs!$D$45,0)
B17: REVENUE (EUR)
B18: Voice Care price (indexed) | C18: EUR | D18: =Inputs!$D$20*(1+Inputs!$D$24)^(D5-1) | E18: =Inputs!$D$20*(1+Inputs!$D$24)^(E5-1) | F18: =Inputs!$D$20*(1+Inputs!$D$24)^(F5-1) | G18: =Inputs!$D$20*(1+Inputs!$D$24)^(G5-1) | H18: =Inputs!$D$20*(1+Inputs!$D$24)^(H5-1) | I18: =Inputs!$D$20*(1+Inputs!$D$24)^(I5-1) | J18: =Inputs!$D$20*(1+Inputs!$D$24)^(J5-1) | K18: =Inputs!$D$20*(1+Inputs!$D$24)^(K5-1) | ... BK18: =Inputs!$D$20*(1+Inputs!$D$24)^(BK5-1)
B19: Preventive Care price (indexed) | C19: EUR | D19: =Inputs!$D$21*(1+Inputs!$D$24)^(D5-1) | E19: =Inputs!$D$21*(1+Inputs!$D$24)^(E5-1) | F19: =Inputs!$D$21*(1+Inputs!$D$24)^(F5-1) | G19: =Inputs!$D$21*(1+Inputs!$D$24)^(G5-1) | H19: =Inputs!$D$21*(1+Inputs!$D$24)^(H5-1) | I19: =Inputs!$D$21*(1+Inputs!$D$24)^(I5-1) | J19: =Inputs!$D$21*(1+Inputs!$D$24)^(J5-1) | K19: =Inputs!$D$21*(1+Inputs!$D$24)^(K5-1) | ... BK19: =Inputs!$D$21*(1+Inputs!$D$24)^(BK5-1)
B20: Preventive Care attach rate | C20: % | D20: =IF(OR(D7=0,D4<Inputs!$C$15),0,INDEX(Inputs!$C$50:$G$50,1,D7)*Inputs!$C$51) | E20: =IF(OR(E7=0,E4<Inputs!$C$15),0,INDEX(Inputs!$C$50:$G$50,1,E7)*Inputs!$C$51) | F20: =IF(OR(F7=0,F4<Inputs!$C$15),0,INDEX(Inputs!$C$50:$G$50,1,F7)*Inputs!$C$51) | G20: =IF(OR(G7=0,G4<Inputs!$C$15),0,INDEX(Inputs!$C$50:$G$50,1,G7)*Inputs!$C$51) | H20: =IF(OR(H7=0,H4<Inputs!$C$15),0,INDEX(Inputs!$C$50:$G$50,1,H7)*Inputs!$C$51) | I20: =IF(OR(I7=0,I4<Inputs!$C$15),0,INDEX(Inputs!$C$50:$G$50,1,I7)*Inputs!$C$51) | J20: =IF(OR(J7=0,J4<Inputs!$C$15),0,INDEX(Inputs!$C$50:$G$50,1,J7)*Inputs!$C$51) | K20: =IF(OR(K7=0,K4<Inputs!$C$15),0,INDEX(Inputs!$C$50:$G$50,1,K7)*Inputs!$C$51) | ... BK20: =IF(OR(BK7=0,BK4<Inputs!$C$15),0,INDEX(Inputs!$C$50:$G$50,1,BK7)*Inputs!$C$51)
B21: Gross billings — Voice Care | C21: EUR | D21: =D14*D18 | E21: =E14*E18 | F21: =F14*F18 | G21: =G14*G18 | H21: =H14*H18 | I21: =I14*I18 | J21: =J14*J18 | K21: =K14*K18 | ... BK21: =BK14*BK18
B22: Gross billings — Preventive Care | C22: EUR | D22: =D14*D20*D19 | E22: =E14*E20*E19 | F22: =F14*F20*F19 | G22: =G14*G20*G19 | H22: =H14*H20*H19 | I22: =I14*I20*I19 | J22: =J14*J20*J19 | K22: =K14*K20*K19 | ... BK22: =BK14*BK20*BK19
B23: Total gross billings (what customers pay) | C23: EUR | D23: =D21+D22 | E23: =E21+E22 | F23: =F21+F22 | G23: =G21+G22 | H23: =H21+H22 | I23: =I21+I22 | J23: =J21+J22 | K23: =K21+K22 | ... BK23: =BK21+BK22
B24: Net revenue — Voice Care | C24: EUR | D24: =D21*Inputs!$D$27 | E24: =E21*Inputs!$D$27 | F24: =F21*Inputs!$D$27 | G24: =G21*Inputs!$D$27 | H24: =H21*Inputs!$D$27 | I24: =I21*Inputs!$D$27 | J24: =J21*Inputs!$D$27 | K24: =K21*Inputs!$D$27 | ... BK24: =BK21*Inputs!$D$27
B25: Net revenue — Preventive Care | C25: EUR | D25: =D22*Inputs!$D$27 | E25: =E22*Inputs!$D$27 | F25: =F22*Inputs!$D$27 | G25: =G22*Inputs!$D$27 | H25: =H22*Inputs!$D$27 | I25: =I22*Inputs!$D$27 | J25: =J22*Inputs!$D$27 | K25: =K22*Inputs!$D$27 | ... BK25: =BK22*Inputs!$D$27
B26: Total net revenue | C26: EUR | D26: =D24+D25 | E26: =E24+E25 | F26: =F24+F25 | G26: =G24+G25 | H26: =H24+H25 | I26: =I24+I25 | J26: =J24+J25 | K26: =K24+K25 | ... BK26: =BK24+BK25
B28: COST OF SERVICE (EUR)
B29: Cost per voice minute | C29: EUR | D29: =INDEX(Inputs!$C$61:$G$61,1,D5) | E29: =INDEX(Inputs!$C$61:$G$61,1,E5) | F29: =INDEX(Inputs!$C$61:$G$61,1,F5) | G29: =INDEX(Inputs!$C$61:$G$61,1,G5) | H29: =INDEX(Inputs!$C$61:$G$61,1,H5) | I29: =INDEX(Inputs!$C$61:$G$61,1,I5) | J29: =INDEX(Inputs!$C$61:$G$61,1,J5) | K29: =INDEX(Inputs!$C$61:$G$61,1,K5) | ... BK29: =INDEX(Inputs!$C$61:$G$61,1,BK5)
B30: AI voice — paying customers | C30: EUR | D30: =D14*Inputs!$C$57*D29 | E30: =E14*Inputs!$C$57*E29 | F30: =F14*Inputs!$C$57*F29 | G30: =G14*Inputs!$C$57*G29 | H30: =H14*Inputs!$C$57*H29 | I30: =I14*Inputs!$C$57*I29 | J30: =J14*Inputs!$C$57*J29 | K30: =K14*Inputs!$C$57*K29 | ... BK30: =BK14*Inputs!$C$57*BK29
B31: AI voice — free trials | C31: EUR | D31: =D15*Inputs!$D$44*Inputs!$C$55*Inputs!$C$56*D29 | E31: =E15*Inputs!$D$44*Inputs!$C$55*Inputs!$C$56*E29 | F31: =F15*Inputs!$D$44*Inputs!$C$55*Inputs!$C$56*F29 | G31: =G15*Inputs!$D$44*Inputs!$C$55*Inputs!$C$56*G29 | H31: =H15*Inputs!$D$44*Inputs!$C$55*Inputs!$C$56*H29 | I31: =I15*Inputs!$D$44*Inputs!$C$55*Inputs!$C$56*I29 | J31: =J15*Inputs!$D$44*Inputs!$C$55*Inputs!$C$56*J29 | K31: =K15*Inputs!$D$44*Inputs!$C$55*Inputs!$C$56*K29 | ... BK31: =BK15*Inputs!$D$44*Inputs!$C$55*Inputs!$C$56*BK29
B32: Data & storage | C32: EUR | D32: =D14*Inputs!$C$62 | E32: =E14*Inputs!$C$62 | F32: =F14*Inputs!$C$62 | G32: =G14*Inputs!$C$62 | H32: =H14*Inputs!$C$62 | I32: =I14*Inputs!$C$62 | J32: =J14*Inputs!$C$62 | K32: =K14*Inputs!$C$62 | ... BK32: =BK14*Inputs!$C$62
B33: Preventive Care variable cost | C33: EUR | D33: =D14*D20*Inputs!$C$52 | E33: =E14*E20*Inputs!$C$52 | F33: =F14*F20*Inputs!$C$52 | G33: =G14*G20*Inputs!$C$52 | H33: =H14*H20*Inputs!$C$52 | I33: =I14*I20*Inputs!$C$52 | J33: =J14*J20*Inputs!$C$52 | K33: =K14*K20*Inputs!$C$52 | ... BK33: =BK14*BK20*Inputs!$C$52
B34: Total cost of service | C34: EUR | D34: =SUM(D30:D33) | E34: =SUM(E30:E33) | F34: =SUM(F30:F33) | G34: =SUM(G30:G33) | H34: =SUM(H30:H33) | I34: =SUM(I30:I33) | J34: =SUM(J30:J33) | K34: =SUM(K30:K33) | ... BK34: =SUM(BK30:BK33)
B35: Gross profit | C35: EUR | D35: =D26-D34 | E35: =E26-E34 | F35: =F26-F34 | G35: =G26-G34 | H35: =H26-H34 | I35: =I26-I34 | J35: =J26-J34 | K35: =K26-K34 | ... BK35: =BK26-BK34
B36: Gross margin | C36: % | D36: =IFERROR(D35/D26,0) | E36: =IFERROR(E35/E26,0) | F36: =IFERROR(F35/F26,0) | G36: =IFERROR(G35/G26,0) | H36: =IFERROR(H35/H26,0) | I36: =IFERROR(I35/I26,0) | J36: =IFERROR(J35/J26,0) | K36: =IFERROR(K35/K26,0) | ... BK36: =IFERROR(BK35/BK26,0)
B38: CUSTOMER ACQUISITION (EUR)
B39: Cost per acquired customer | C39: EUR | D39: =IF(D7=0,0,INDEX(Inputs!$C$69:$G$69,1,D7)*Inputs!$C$70) | E39: =IF(E7=0,0,INDEX(Inputs!$C$69:$G$69,1,E7)*Inputs!$C$70) | F39: =IF(F7=0,0,INDEX(Inputs!$C$69:$G$69,1,F7)*Inputs!$C$70) | G39: =IF(G7=0,0,INDEX(Inputs!$C$69:$G$69,1,G7)*Inputs!$C$70) | H39: =IF(H7=0,0,INDEX(Inputs!$C$69:$G$69,1,H7)*Inputs!$C$70) | I39: =IF(I7=0,0,INDEX(Inputs!$C$69:$G$69,1,I7)*Inputs!$C$70) | J39: =IF(J7=0,0,INDEX(Inputs!$C$69:$G$69,1,J7)*Inputs!$C$70) | K39: =IF(K7=0,0,INDEX(Inputs!$C$69:$G$69,1,K7)*Inputs!$C$70) | ... BK39: =IF(BK7=0,0,INDEX(Inputs!$C$69:$G$69,1,BK7)*Inputs!$C$70)
B40: Acquisition spend | C40: EUR | D40: =D11*D39 | E40: =E11*E39 | F40: =F11*F39 | G40: =G11*G39 | H40: =H11*H39 | I40: =I11*I39 | J40: =J11*J39 | K40: =K11*K39 | ... BK40: =BK11*BK39
B41: Contribution after acquisition | C41: EUR | D41: =D35-D40 | E41: =E35-E40 | F41: =F35-F40 | G41: =G35-G40 | H41: =H35-H40 | I41: =I35-I40 | J41: =J35-J40 | K41: =K35-K40 | ... BK41: =BK35-BK40

Sheet P&L Monthly
B2: CONSOLIDATED MONTHLY MODEL — PORTUGAL + SPAIN
B3: Profit and loss, capital expenditure, working capital, cash flow and the founders' equity injection.
B4: Month | C4: Unit | D4: 1 | E4: 2 | F4: 3 | G4: 4 | H4: 5 | I4: 6 | J4: 7 | K4: 8 | L4: 9 | M4: 10 | N4: 11 | O4: 12 | P4: 13 | Q4: 14 | R4: 15 | S4: 16 | T4: 17 | U4: 18 | V4: 19 | W4: 20 | X4: 21 | Y4: 22 | Z4: 23 | AA4: 24 | AB4: 25 | AC4: 26 | AD4: 27 | AE4: 28 | AF4: 29 | AG4: 30 | AH4: 31 | AI4: 32 | AJ4: 33 | AK4: 34 | AL4: 35 | AM4: 36 | AN4: 37 | AO4: 38 | AP4: 39 | AQ4: 40 | AR4: 41 | AS4: 42 | AT4: 43 | AU4: 44 | AV4: 45 | AW4: 46 | AX4: 47 | AY4: 48 | AZ4: 49 | BA4: 50 | BB4: 51 | BC4: 52 | BD4: 53 | BE4: 54 | BF4: 55 | BG4: 56 | BH4: 57 | BI4: 58 | BJ4: 59 | BK4: 60
B5: Model year | C5: yr | D5: =MIN(5,INT((D4-1)/12)+1) | E5: =MIN(5,INT((E4-1)/12)+1) | F5: =MIN(5,INT((F4-1)/12)+1) | G5: =MIN(5,INT((G4-1)/12)+1) | H5: =MIN(5,INT((H4-1)/12)+1) | I5: =MIN(5,INT((I4-1)/12)+1) | J5: =MIN(5,INT((J4-1)/12)+1) | K5: =MIN(5,INT((K4-1)/12)+1) | ... BK5: =MIN(5,INT((BK4-1)/12)+1)
B7: PROFIT & LOSS (EUR)
B8: Net revenue — Portugal | C8: EUR | D8: ='Model PT'!D26 | E8: ='Model PT'!E26 | F8: ='Model PT'!F26 | G8: ='Model PT'!G26 | H8: ='Model PT'!H26 | I8: ='Model PT'!I26 | J8: ='Model PT'!J26 | K8: ='Model PT'!K26 | ... BK8: ='Model PT'!BK26
B9: Net revenue — Spain | C9: EUR | D9: ='Model ES'!D26 | E9: ='Model ES'!E26 | F9: ='Model ES'!F26 | G9: ='Model ES'!G26 | H9: ='Model ES'!H26 | I9: ='Model ES'!I26 | J9: ='Model ES'!J26 | K9: ='Model ES'!K26 | ... BK9: ='Model ES'!BK26
B10: Total net revenue | C10: EUR | D10: =D8+D9 | E10: =E8+E9 | F10: =F8+F9 | G10: =G8+G9 | H10: =H8+H9 | I10: =I8+I9 | J10: =J8+J9 | K10: =K8+K9 | ... BK10: =BK8+BK9
B11: Cost of service — Portugal | C11: EUR | D11: =-'Model PT'!D34 | E11: =-'Model PT'!E34 | F11: =-'Model PT'!F34 | G11: =-'Model PT'!G34 | H11: =-'Model PT'!H34 | I11: =-'Model PT'!I34 | J11: =-'Model PT'!J34 | K11: =-'Model PT'!K34 | ... BK11: =-'Model PT'!BK34
B12: Cost of service — Spain | C12: EUR | D12: =-'Model ES'!D34 | E12: =-'Model ES'!E34 | F12: =-'Model ES'!F34 | G12: =-'Model ES'!G34 | H12: =-'Model ES'!H34 | I12: =-'Model ES'!I34 | J12: =-'Model ES'!J34 | K12: =-'Model ES'!K34 | ... BK12: =-'Model ES'!BK34
B13: Total cost of service | C13: EUR | D13: =D11+D12 | E13: =E11+E12 | F13: =F11+F12 | G13: =G11+G12 | H13: =H11+H12 | I13: =I11+I12 | J13: =J11+J12 | K13: =K11+K12 | ... BK13: =BK11+BK12
B14: Gross profit | C14: EUR | D14: =D10+D13 | E14: =E10+E13 | F14: =F10+F13 | G14: =G10+G13 | H14: =H10+H13 | I14: =I10+I13 | J14: =J10+J13 | K14: =K10+K13 | ... BK14: =BK10+BK13
B15: Gross margin | C15: % | D15: =IFERROR(D14/D10,0) | E15: =IFERROR(E14/E10,0) | F15: =IFERROR(F14/F10,0) | G15: =IFERROR(G14/G10,0) | H15: =IFERROR(H14/H10,0) | I15: =IFERROR(I14/I10,0) | J15: =IFERROR(J14/J10,0) | K15: =IFERROR(K14/K10,0) | ... BK15: =IFERROR(BK14/BK10,0)
B17: Customer acquisition (COCA) | C17: EUR | D17: =-('Model PT'!D40+'Model ES'!D40) | E17: =-('Model PT'!E40+'Model ES'!E40) | F17: =-('Model PT'!F40+'Model ES'!F40) | G17: =-('Model PT'!G40+'Model ES'!G40) | H17: =-('Model PT'!H40+'Model ES'!H40) | I17: =-('Model PT'!I40+'Model ES'!I40) | J17: =-('Model PT'!J40+'Model ES'!J40) | K17: =-('Model PT'!K40+'Model ES'!K40) | ... BK17: =-('Model PT'!BK40+'Model ES'!BK40)
B18: Brand marketing & content | C18: EUR | D18: =-INDEX(Inputs!$C$77:$G$77,1,D5)*INDEX(Scenarios!$D$15:$F$15,1,Inputs!$C$7) | E18: =-INDEX(Inputs!$C$77:$G$77,1,E5)*INDEX(Scenarios!$D$15:$F$15,1,Inputs!$C$7) | F18: =-INDEX(Inputs!$C$77:$G$77,1,F5)*INDEX(Scenarios!$D$15:$F$15,1,Inputs!$C$7) | G18: =-INDEX(Inputs!$C$77:$G$77,1,G5)*INDEX(Scenarios!$D$15:$F$15,1,Inputs!$C$7) | H18: =-INDEX(Inputs!$C$77:$G$77,1,H5)*INDEX(Scenarios!$D$15:$F$15,1,Inputs!$C$7) | I18: =-INDEX(Inputs!$C$77:$G$77,1,I5)*INDEX(Scenarios!$D$15:$F$15,1,Inputs!$C$7) | J18: =-INDEX(Inputs!$C$77:$G$77,1,J5)*INDEX(Scenarios!$D$15:$F$15,1,Inputs!$C$7) | K18: =-INDEX(Inputs!$C$77:$G$77,1,K5)*INDEX(Scenarios!$D$15:$F$15,1,Inputs!$C$7) | ... BK18: =-INDEX(Inputs!$C$77:$G$77,1,BK5)*INDEX(Scenarios!$D$15:$F$15,1,Inputs!$C$7)
B19: Personnel | C19: EUR | D19: =-(INDEX(Inputs!$C$74:$G$74,1,D5)+INDEX(Inputs!$C$75:$G$75,1,D5)+INDEX(Inputs!$C$76:$G$76,1,D5)+IF(D4>=Inputs!$C$14,INDEX(Inputs!$C$82:$G$82,1,D5),0)) | E19: =-(INDEX(Inputs!$C$74:$G$74,1,E5)+INDEX(Inputs!$C$75:$G$75,1,E5)+INDEX(Inputs!$C$76:$G$76,1,E5)+IF(E4>=Inputs!$C$14,INDEX(Inputs!$C$82:$G$82,1,E5),0)) | F19: =-(INDEX(Inputs!$C$74:$G$74,1,F5)+INDEX(Inputs!$C$75:$G$75,1,F5)+INDEX(Inputs!$C$76:$G$76,1,F5)+IF(F4>=Inputs!$C$14,INDEX(Inputs!$C$82:$G$82,1,F5),0)) | G19: =-(INDEX(Inputs!$C$74:$G$74,1,G5)+INDEX(Inputs!$C$75:$G$75,1,G5)+INDEX(Inputs!$C$76:$G$76,1,G5)+IF(G4>=Inputs!$C$14,INDEX(Inputs!$C$82:$G$82,1,G5),0)) | H19: =-(INDEX(Inputs!$C$74:$G$74,1,H5)+INDEX(Inputs!$C$75:$G$75,1,H5)+INDEX(Inputs!$C$76:$G$76,1,H5)+IF(H4>=Inputs!$C$14,INDEX(Inputs!$C$82:$G$82,1,H5),0)) | I19: =-(INDEX(Inputs!$C$74:$G$74,1,I5)+INDEX(Inputs!$C$75:$G$75,1,I5)+INDEX(Inputs!$C$76:$G$76,1,I5)+IF(I4>=Inputs!$C$14,INDEX(Inputs!$C$82:$G$82,1,I5),0)) | J19: =-(INDEX(Inputs!$C$74:$G$74,1,J5)+INDEX(Inputs!$C$75:$G$75,1,J5)+INDEX(Inputs!$C$76:$G$76,1,J5)+IF(J4>=Inputs!$C$14,INDEX(Inputs!$C$82:$G$82,1,J5),0)) | K19: =-(INDEX(Inputs!$C$74:$G$74,1,K5)+INDEX(Inputs!$C$75:$G$75,1,K5)+INDEX(Inputs!$C$76:$G$76,1,K5)+IF(K4>=Inputs!$C$14,INDEX(Inputs!$C$82:$G$82,1,K5),0)) | ... BK19: =-(INDEX(Inputs!$C$74:$G$74,1,BK5)+INDEX(Inputs!$C$75:$G$75,1,BK5)+INDEX(Inputs!$C$76:$G$76,1,BK5)+IF(BK4>=Inputs!$C$14,INDEX(Inputs!$C$82:$G$82,1,BK5),0))
B20: Cloud & tools | C20: EUR | D20: =-INDEX(Inputs!$C$78:$G$78,1,D5) | E20: =-INDEX(Inputs!$C$78:$G$78,1,E5) | F20: =-INDEX(Inputs!$C$78:$G$78,1,F5) | G20: =-INDEX(Inputs!$C$78:$G$78,1,G5) | H20: =-INDEX(Inputs!$C$78:$G$78,1,H5) | I20: =-INDEX(Inputs!$C$78:$G$78,1,I5) | J20: =-INDEX(Inputs!$C$78:$G$78,1,J5) | K20: =-INDEX(Inputs!$C$78:$G$78,1,K5) | ... BK20: =-INDEX(Inputs!$C$78:$G$78,1,BK5)
B21: General & administrative | C21: EUR | D21: =-(INDEX(Inputs!$C$79:$G$79,1,D5)+INDEX(Inputs!$C$80:$G$80,1,D5)+INDEX(Inputs!$C$81:$G$81,1,D5)+INDEX(Inputs!$C$83:$G$83,1,D5)) | E21: =-(INDEX(Inputs!$C$79:$G$79,1,E5)+INDEX(Inputs!$C$80:$G$80,1,E5)+INDEX(Inputs!$C$81:$G$81,1,E5)+INDEX(Inputs!$C$83:$G$83,1,E5)) | F21: =-(INDEX(Inputs!$C$79:$G$79,1,F5)+INDEX(Inputs!$C$80:$G$80,1,F5)+INDEX(Inputs!$C$81:$G$81,1,F5)+INDEX(Inputs!$C$83:$G$83,1,F5)) | G21: =-(INDEX(Inputs!$C$79:$G$79,1,G5)+INDEX(Inputs!$C$80:$G$80,1,G5)+INDEX(Inputs!$C$81:$G$81,1,G5)+INDEX(Inputs!$C$83:$G$83,1,G5)) | H21: =-(INDEX(Inputs!$C$79:$G$79,1,H5)+INDEX(Inputs!$C$80:$G$80,1,H5)+INDEX(Inputs!$C$81:$G$81,1,H5)+INDEX(Inputs!$C$83:$G$83,1,H5)) | I21: =-(INDEX(Inputs!$C$79:$G$79,1,I5)+INDEX(Inputs!$C$80:$G$80,1,I5)+INDEX(Inputs!$C$81:$G$81,1,I5)+INDEX(Inputs!$C$83:$G$83,1,I5)) | J21: =-(INDEX(Inputs!$C$79:$G$79,1,J5)+INDEX(Inputs!$C$80:$G$80,1,J5)+INDEX(Inputs!$C$81:$G$81,1,J5)+INDEX(Inputs!$C$83:$G$83,1,J5)) | K21: =-(INDEX(Inputs!$C$79:$G$79,1,K5)+INDEX(Inputs!$C$80:$G$80,1,K5)+INDEX(Inputs!$C$81:$G$81,1,K5)+INDEX(Inputs!$C$83:$G$83,1,K5)) | ... BK21: =-(INDEX(Inputs!$C$79:$G$79,1,BK5)+INDEX(Inputs!$C$80:$G$80,1,BK5)+INDEX(Inputs!$C$81:$G$81,1,BK5)+INDEX(Inputs!$C$83:$G$83,1,BK5))
B22: Total operating expenses | C22: EUR | D22: =SUM(D17:D21) | E22: =SUM(E17:E21) | F22: =SUM(F17:F21) | G22: =SUM(G17:G21) | H22: =SUM(H17:H21) | I22: =SUM(I17:I21) | J22: =SUM(J17:J21) | K22: =SUM(K17:K21) | ... BK22: =SUM(BK17:BK21)
B23: EBITDA | C23: EUR | D23: =D14+D22 | E23: =E14+E22 | F23: =F14+F22 | G23: =G14+G22 | H23: =H14+H22 | I23: =I14+I22 | J23: =J14+J22 | K23: =K14+K22 | ... BK23: =BK14+BK22
B24: EBITDA margin | C24: % | D24: =IFERROR(D23/D10,0) | E24: =IFERROR(E23/E10,0) | F24: =IFERROR(F23/F10,0) | G24: =IFERROR(G23/G10,0) | H24: =IFERROR(H23/H10,0) | I24: =IFERROR(I23/I10,0) | J24: =IFERROR(J23/J10,0) | K24: =IFERROR(K23/K10,0) | ... BK24: =IFERROR(BK23/BK10,0)
B25: Depreciation | C25: EUR | D25: =-D42 | E25: =-E42 | F25: =-F42 | G25: =-G42 | H25: =-H42 | I25: =-I42 | J25: =-J42 | K25: =-K42 | ... BK25: =-BK42
B26: EBIT | C26: EUR | D26: =D23+D25 | E26: =E23+E25 | F26: =F23+F25 | G26: =G23+G25 | H26: =H23+H25 | I26: =I23+I25 | J26: =J23+J25 | K26: =K23+K25 | ... BK26: =BK23+BK25
B27: Tax loss pool — opening | C27: EUR | D27: =0 | E27: =D30 | F27: =E30 | G27: =F30 | H27: =G30 | I27: =H30 | J27: =I30 | K27: =J30 | L27: =K30 | ... BK27: =BJ30
B28: Corporation tax | C28: EUR | D28: =-MAX(0,D26-D27)*Inputs!$C$100 | E28: =-MAX(0,E26-E27)*Inputs!$C$100 | F28: =-MAX(0,F26-F27)*Inputs!$C$100 | G28: =-MAX(0,G26-G27)*Inputs!$C$100 | H28: =-MAX(0,H26-H27)*Inputs!$C$100 | I28: =-MAX(0,I26-I27)*Inputs!$C$100 | J28: =-MAX(0,J26-J27)*Inputs!$C$100 | K28: =-MAX(0,K26-K27)*Inputs!$C$100 | ... BK28: =-MAX(0,BK26-BK27)*Inputs!$C$100
B29: Net income | C29: EUR | D29: =D26+D28 | E29: =E26+E28 | F29: =F26+F28 | G29: =G26+G28 | H29: =H26+H28 | I29: =I26+I28 | J29: =J26+J28 | K29: =K26+K28 | ... BK29: =BK26+BK28
B30: Tax loss pool — closing | C30: EUR | D30: =MAX(0,D27-D26) | E30: =MAX(0,E27-E26) | F30: =MAX(0,F27-F26) | G30: =MAX(0,G27-G26) | H30: =MAX(0,H27-H26) | I30: =MAX(0,I27-I26) | J30: =MAX(0,J27-J26) | K30: =MAX(0,K27-K26) | ... BK30: =MAX(0,BK27-BK26)
B32: CAPITAL EXPENDITURE (EUR)
B33: Voice Care platform build | C33: EUR | D33: =IF(D4<=Inputs!$C$12,Inputs!$C$86/Inputs!$C$12,0) | E33: =IF(E4<=Inputs!$C$12,Inputs!$C$86/Inputs!$C$12,0) | F33: =IF(F4<=Inputs!$C$12,Inputs!$C$86/Inputs!$C$12,0) | G33: =IF(G4<=Inputs!$C$12,Inputs!$C$86/Inputs!$C$12,0) | H33: =IF(H4<=Inputs!$C$12,Inputs!$C$86/Inputs!$C$12,0) | I33: =IF(I4<=Inputs!$C$12,Inputs!$C$86/Inputs!$C$12,0) | J33: =IF(J4<=Inputs!$C$12,Inputs!$C$86/Inputs!$C$12,0) | K33: =IF(K4<=Inputs!$C$12,Inputs!$C$86/Inputs!$C$12,0) | ... BK33: =IF(BK4<=Inputs!$C$12,Inputs!$C$86/Inputs!$C$12,0)
B34: Preventive Care module | C34: EUR | D34: =IF(D4=Inputs!$C$15,Inputs!$C$87,0) | E34: =IF(E4=Inputs!$C$15,Inputs!$C$87,0) | F34: =IF(F4=Inputs!$C$15,Inputs!$C$87,0) | G34: =IF(G4=Inputs!$C$15,Inputs!$C$87,0) | H34: =IF(H4=Inputs!$C$15,Inputs!$C$87,0) | I34: =IF(I4=Inputs!$C$15,Inputs!$C$87,0) | J34: =IF(J4=Inputs!$C$15,Inputs!$C$87,0) | K34: =IF(K4=Inputs!$C$15,Inputs!$C$87,0) | ... BK34: =IF(BK4=Inputs!$C$15,Inputs!$C$87,0)
B35: Spain localisation & compliance | C35: EUR | D35: =IF(D4=Inputs!$C$14,Inputs!$C$88,0) | E35: =IF(E4=Inputs!$C$14,Inputs!$C$88,0) | F35: =IF(F4=Inputs!$C$14,Inputs!$C$88,0) | G35: =IF(G4=Inputs!$C$14,Inputs!$C$88,0) | H35: =IF(H4=Inputs!$C$14,Inputs!$C$88,0) | I35: =IF(I4=Inputs!$C$14,Inputs!$C$88,0) | J35: =IF(J4=Inputs!$C$14,Inputs!$C$88,0) | K35: =IF(K4=Inputs!$C$14,Inputs!$C$88,0) | ... BK35: =IF(BK4=Inputs!$C$14,Inputs!$C$88,0)
B36: Ongoing development capex | C36: EUR | D36: =IF(D5=1,0,(Inputs!$C$86+IF(D4>Inputs!$C$15,Inputs!$C$87,0)+IF(D4>Inputs!$C$14,Inputs!$C$88,0))*Inputs!$C$89/12) | E36: =IF(E5=1,0,(Inputs!$C$86+IF(E4>Inputs!$C$15,Inputs!$C$87,0)+IF(E4>Inputs!$C$14,Inputs!$C$88,0))*Inputs!$C$89/12) | F36: =IF(F5=1,0,(Inputs!$C$86+IF(F4>Inputs!$C$15,Inputs!$C$87,0)+IF(F4>Inputs!$C$14,Inputs!$C$88,0))*Inputs!$C$89/12) | G36: =IF(G5=1,0,(Inputs!$C$86+IF(G4>Inputs!$C$15,Inputs!$C$87,0)+IF(G4>Inputs!$C$14,Inputs!$C$88,0))*Inputs!$C$89/12) | H36: =IF(H5=1,0,(Inputs!$C$86+IF(H4>Inputs!$C$15,Inputs!$C$87,0)+IF(H4>Inputs!$C$14,Inputs!$C$88,0))*Inputs!$C$89/12) | I36: =IF(I5=1,0,(Inputs!$C$86+IF(I4>Inputs!$C$15,Inputs!$C$87,0)+IF(I4>Inputs!$C$14,Inputs!$C$88,0))*Inputs!$C$89/12) | J36: =IF(J5=1,0,(Inputs!$C$86+IF(J4>Inputs!$C$15,Inputs!$C$87,0)+IF(J4>Inputs!$C$14,Inputs!$C$88,0))*Inputs!$C$89/12) | K36: =IF(K5=1,0,(Inputs!$C$86+IF(K4>Inputs!$C$15,Inputs!$C$87,0)+IF(K4>Inputs!$C$14,Inputs!$C$88,0))*Inputs!$C$89/12) | ... BK36: =IF(BK5=1,0,(Inputs!$C$86+IF(BK4>Inputs!$C$15,Inputs!$C$87,0)+IF(BK4>Inputs!$C$14,Inputs!$C$88,0))*Inputs!$C$89/12)
B37: Total capital expenditure | C37: EUR | D37: =SUM(D33:D36) | E37: =SUM(E33:E36) | F37: =SUM(F33:F36) | G37: =SUM(G33:G36) | H37: =SUM(H33:H36) | I37: =SUM(I33:I36) | J37: =SUM(J33:J36) | K37: =SUM(K33:K36) | ... BK37: =SUM(BK33:BK36)
B38: Cumulative capital expenditure | C38: EUR | D38: =D37 | E38: =D38+E37 | F38: =E38+F37 | G38: =F38+G37 | H38: =G38+H37 | I38: =H38+I37 | J38: =I38+J37 | K38: =J38+K37 | L38: =K38+L37 | ... BK38: =BJ38+BK37
B40: Gross fixed assets | C40: EUR | D40: =D38 | E40: =E38 | F40: =F38 | G40: =G38 | H40: =H38 | I40: =I38 | J40: =J38 | K40: =K38 | ... BK40: =BK38
B41: Accumulated depreciation | C41: EUR | D41: =D42 | E41: =D41+E42 | F41: =E41+F42 | G41: =F41+G42 | H41: =G41+H42 | I41: =H41+I42 | J41: =I41+J42 | K41: =J41+K42 | L41: =K41+L42 | ... BK41: =BJ41+BK42
B42: Depreciation charge for the month | C42: EUR | D42: =0 | E42: =D38/(Inputs!$C$90*12) | F42: =E38/(Inputs!$C$90*12) | G42: =F38/(Inputs!$C$90*12) | H42: =G38/(Inputs!$C$90*12) | I42: =H38/(Inputs!$C$90*12) | J42: =I38/(Inputs!$C$90*12) | K42: =J38/(Inputs!$C$90*12) | L42: =K38/(Inputs!$C$90*12) | ... BK42: =BJ38/(Inputs!$C$90*12)
B43: Net fixed assets | C43: EUR | D43: =D40-D41 | E43: =E40-E41 | F43: =F40-F41 | G43: =G40-G41 | H43: =H40-H41 | I43: =I40-I41 | J43: =J40-J41 | K43: =K40-K41 | ... BK43: =BK40-BK41
B45: WORKING CAPITAL (EUR)
B46: Net revenue per active customer | C46: EUR | D46: =IFERROR(D10/('Model PT'!D14+'Model ES'!D14),0) | E46: =IFERROR(E10/('Model PT'!E14+'Model ES'!E14),0) | F46: =IFERROR(F10/('Model PT'!F14+'Model ES'!F14),0) | G46: =IFERROR(G10/('Model PT'!G14+'Model ES'!G14),0) | H46: =IFERROR(H10/('Model PT'!H14+'Model ES'!H14),0) | I46: =IFERROR(I10/('Model PT'!I14+'Model ES'!I14),0) | J46: =IFERROR(J10/('Model PT'!J14+'Model ES'!J14),0) | K46: =IFERROR(K10/('Model PT'!K14+'Model ES'!K14),0) | ... BK46: =IFERROR(BK10/('Model PT'!BK14+'Model ES'!BK14),0)
B47: Annual-prepay cash collected up front | C47: EUR | D47: =('Model PT'!D11+'Model ES'!D11)*Inputs!$C$95*D46*12*(1-Inputs!$C$96) | E47: =('Model PT'!E11+'Model ES'!E11)*Inputs!$C$95*E46*12*(1-Inputs!$C$96) | F47: =('Model PT'!F11+'Model ES'!F11)*Inputs!$C$95*F46*12*(1-Inputs!$C$96) | G47: =('Model PT'!G11+'Model ES'!G11)*Inputs!$C$95*G46*12*(1-Inputs!$C$96) | H47: =('Model PT'!H11+'Model ES'!H11)*Inputs!$C$95*H46*12*(1-Inputs!$C$96) | I47: =('Model PT'!I11+'Model ES'!I11)*Inputs!$C$95*I46*12*(1-Inputs!$C$96) | J47: =('Model PT'!J11+'Model ES'!J11)*Inputs!$C$95*J46*12*(1-Inputs!$C$96) | K47: =('Model PT'!K11+'Model ES'!K11)*Inputs!$C$95*K46*12*(1-Inputs!$C$96) | ... BK47: =('Model PT'!BK11+'Model ES'!BK11)*Inputs!$C$95*BK46*12*(1-Inputs!$C$96)
B48: Receivables | C48: EUR | D48: =D10*(1-Inputs!$C$95)*Inputs!$C$93/Inputs!$C$16 | E48: =E10*(1-Inputs!$C$95)*Inputs!$C$93/Inputs!$C$16 | F48: =F10*(1-Inputs!$C$95)*Inputs!$C$93/Inputs!$C$16 | G48: =G10*(1-Inputs!$C$95)*Inputs!$C$93/Inputs!$C$16 | H48: =H10*(1-Inputs!$C$95)*Inputs!$C$93/Inputs!$C$16 | I48: =I10*(1-Inputs!$C$95)*Inputs!$C$93/Inputs!$C$16 | J48: =J10*(1-Inputs!$C$95)*Inputs!$C$93/Inputs!$C$16 | K48: =K10*(1-Inputs!$C$95)*Inputs!$C$93/Inputs!$C$16 | ... BK48: =BK10*(1-Inputs!$C$95)*Inputs!$C$93/Inputs!$C$16
B49: Payables | C49: EUR | D49: =(-D13-D22)*Inputs!$C$94/Inputs!$C$16 | E49: =(-E13-E22)*Inputs!$C$94/Inputs!$C$16 | F49: =(-F13-F22)*Inputs!$C$94/Inputs!$C$16 | G49: =(-G13-G22)*Inputs!$C$94/Inputs!$C$16 | H49: =(-H13-H22)*Inputs!$C$94/Inputs!$C$16 | I49: =(-I13-I22)*Inputs!$C$94/Inputs!$C$16 | J49: =(-J13-J22)*Inputs!$C$94/Inputs!$C$16 | K49: =(-K13-K22)*Inputs!$C$94/Inputs!$C$16 | ... BK49: =(-BK13-BK22)*Inputs!$C$94/Inputs!$C$16
B50: Deferred revenue (annual prepay) | C50: EUR | D50: =D47 | E50: =MAX(0,D50+E47-D50/12) | F50: =MAX(0,E50+F47-E50/12) | G50: =MAX(0,F50+G47-F50/12) | H50: =MAX(0,G50+H47-G50/12) | I50: =MAX(0,H50+I47-H50/12) | J50: =MAX(0,I50+J47-I50/12) | K50: =MAX(0,J50+K47-J50/12) | L50: =MAX(0,K50+L47-K50/12) | ... BK50: =MAX(0,BJ50+BK47-BJ50/12)
B51: Net working capital | C51: EUR | D51: =D48-D49-D50 | E51: =E48-E49-E50 | F51: =F48-F49-F50 | G51: =G48-G49-G50 | H51: =H48-H49-H50 | I51: =I48-I49-I50 | J51: =J48-J49-J50 | K51: =K48-K49-K50 | ... BK51: =BK48-BK49-BK50
B52: Change in net working capital | C52: EUR | D52: =D51 | E52: =E51-D51 | F52: =F51-E51 | G52: =G51-F51 | H52: =H51-G51 | I52: =I51-H51 | J52: =J51-I51 | K52: =K51-J51 | L52: =L51-K51 | ... BK52: =BK51-BJ51
B54: CASH FLOW (EUR)
B55: EBITDA | C55: EUR | D55: =D23 | E55: =E23 | F55: =F23 | G55: =G23 | H55: =H23 | I55: =I23 | J55: =J23 | K55: =K23 | ... BK55: =BK23
B56: Corporation tax paid | C56: EUR | D56: =D28 | E56: =E28 | F56: =F28 | G56: =G28 | H56: =H28 | I56: =I28 | J56: =J28 | K56: =K28 | ... BK56: =BK28
B57: Capital expenditure | C57: EUR | D57: =-D37 | E57: =-E37 | F57: =-F37 | G57: =-G37 | H57: =-H37 | I57: =-I37 | J57: =-J37 | K57: =-K37 | ... BK57: =-BK37
B58: Change in working capital | C58: EUR | D58: =-D52 | E58: =-E52 | F58: =-F52 | G58: =-G52 | H58: =-H52 | I58: =-I52 | J58: =-J52 | K58: =-K52 | ... BK58: =-BK52
B59: Free cash flow | C59: EUR | D59: =SUM(D55:D58) | E59: =SUM(E55:E58) | F59: =SUM(F55:F58) | G59: =SUM(G55:G58) | H59: =SUM(H55:H58) | I59: =SUM(I55:I58) | J59: =SUM(J55:J58) | K59: =SUM(K55:K58) | ... BK59: =SUM(BK55:BK58)
B60: Cumulative free cash flow | C60: EUR | D60: =D59 | E60: =D60+E59 | F60: =E60+F59 | G60: =F60+G59 | H60: =G60+H59 | I60: =H60+I59 | J60: =I60+J59 | K60: =J60+K59 | L60: =K60+L59 | ... BK60: =BJ60+BK59
B61: Cash before founders' injection | C61: EUR | D61: =D59 | E61: =D64+E59 | F61: =E64+F59 | G61: =F64+G59 | H61: =G64+H59 | I61: =H64+I59 | J61: =I64+J59 | K61: =J64+K59 | L61: =K64+L59 | ... BK61: =BJ64+BK59
B62: Founders' equity injected | C62: EUR | D62: =MAX(0,Inputs!$C$97-D61) | E62: =MAX(0,Inputs!$C$97-E61) | F62: =MAX(0,Inputs!$C$97-F61) | G62: =MAX(0,Inputs!$C$97-G61) | H62: =MAX(0,Inputs!$C$97-H61) | I62: =MAX(0,Inputs!$C$97-I61) | J62: =MAX(0,Inputs!$C$97-J61) | K62: =MAX(0,Inputs!$C$97-K61) | ... BK62: =MAX(0,Inputs!$C$97-BK61)
B63: Cumulative equity invested | C63: EUR | D63: =D62 | E63: =D63+E62 | F63: =E63+F62 | G63: =F63+G62 | H63: =G63+H62 | I63: =H63+I62 | J63: =I63+J62 | K63: =J63+K62 | L63: =K63+L62 | ... BK63: =BJ63+BK62
B64: Cash — closing balance | C64: EUR | D64: =D61+D62 | E64: =E61+E62 | F64: =F61+F62 | G64: =G61+G62 | H64: =H61+H62 | I64: =I61+I62 | J64: =J61+J62 | K64: =K61+K62 | ... BK64: =BK61+BK62
B66: BALANCE SHEET (month end, EUR)
B67: Cash | C67: EUR | D67: =D64 | E67: =E64 | F67: =F64 | G67: =G64 | H67: =H64 | I67: =I64 | J67: =J64 | K67: =K64 | ... BK67: =BK64
B68: Receivables | C68: EUR | D68: =D48 | E68: =E48 | F68: =F48 | G68: =G48 | H68: =H48 | I68: =I48 | J68: =J48 | K68: =K48 | ... BK68: =BK48
B69: Net fixed assets | C69: EUR | D69: =D43 | E69: =E43 | F69: =F43 | G69: =G43 | H69: =H43 | I69: =I43 | J69: =J43 | K69: =K43 | ... BK69: =BK43
B70: Total assets | C70: EUR | D70: =SUM(D67:D69) | E70: =SUM(E67:E69) | F70: =SUM(F67:F69) | G70: =SUM(G67:G69) | H70: =SUM(H67:H69) | I70: =SUM(I67:I69) | J70: =SUM(J67:J69) | K70: =SUM(K67:K69) | ... BK70: =SUM(BK67:BK69)
B71: Payables | C71: EUR | D71: =D49 | E71: =E49 | F71: =F49 | G71: =G49 | H71: =H49 | I71: =I49 | J71: =J49 | K71: =K49 | ... BK71: =BK49
B72: Deferred revenue | C72: EUR | D72: =D50 | E72: =E50 | F72: =F50 | G72: =G50 | H72: =H50 | I72: =I50 | J72: =J50 | K72: =K50 | ... BK72: =BK50
B73: Paid-in equity | C73: EUR | D73: =D63 | E73: =E63 | F73: =F63 | G73: =G63 | H73: =H63 | I73: =I63 | J73: =J63 | K73: =K63 | ... BK73: =BK63
B74: Retained earnings | C74: EUR | D74: =D29 | E74: =D74+E29 | F74: =E74+F29 | G74: =F74+G29 | H74: =G74+H29 | I74: =H74+I29 | J74: =I74+J29 | K74: =J74+K29 | L74: =K74+L29 | ... BK74: =BJ74+BK29
B75: Total liabilities & equity | C75: EUR | D75: =SUM(D71:D74) | E75: =SUM(E71:E74) | F75: =SUM(F71:F74) | G75: =SUM(G71:G74) | H75: =SUM(H71:H74) | I75: =SUM(I71:I74) | J75: =SUM(J71:J74) | K75: =SUM(K71:K74) | ... BK75: =SUM(BK71:BK74)
B76: Balance check (must be nil) | C76: EUR | D76: =D70-D75 | E76: =E70-E75 | F76: =F70-F75 | G76: =G70-G75 | H76: =H70-H75 | I76: =I70-I75 | J76: =J70-J75 | K76: =K70-K75 | ... BK76: =BK70-BK75
B78: BREAK-EVEN HELPERS (first month from which the measure stays positive)
B79: EBITDA turns and stays positive | C79: mo | D79: =IF(AND(D23>0,MIN(D23:$BK$23)>0),D4,9999) | E79: =IF(AND(E23>0,MIN(E23:$BK$23)>0),E4,9999) | F79: =IF(AND(F23>0,MIN(F23:$BK$23)>0),F4,9999) | G79: =IF(AND(G23>0,MIN(G23:$BK$23)>0),G4,9999) | H79: =IF(AND(H23>0,MIN(H23:$BK$23)>0),H4,9999) | I79: =IF(AND(I23>0,MIN(I23:$BK$23)>0),I4,9999) | J79: =IF(AND(J23>0,MIN(J23:$BK$23)>0),J4,9999) | K79: =IF(AND(K23>0,MIN(K23:$BK$23)>0),K4,9999) | ... BK79: =IF(AND(BK23>0,MIN(BK23:$BK$23)>0),BK4,9999)
B80: Free cash flow turns and stays positive | C80: mo | D80: =IF(AND(D59>0,MIN(D59:$BK$59)>0),D4,9999) | E80: =IF(AND(E59>0,MIN(E59:$BK$59)>0),E4,9999) | F80: =IF(AND(F59>0,MIN(F59:$BK$59)>0),F4,9999) | G80: =IF(AND(G59>0,MIN(G59:$BK$59)>0),G4,9999) | H80: =IF(AND(H59>0,MIN(H59:$BK$59)>0),H4,9999) | I80: =IF(AND(I59>0,MIN(I59:$BK$59)>0),I4,9999) | J80: =IF(AND(J59>0,MIN(J59:$BK$59)>0),J4,9999) | K80: =IF(AND(K59>0,MIN(K59:$BK$59)>0),K4,9999) | ... BK80: =IF(AND(BK59>0,MIN(BK59:$BK$59)>0),BK4,9999)
B81: Net income turns and stays positive | C81: mo | D81: =IF(AND(D29>0,MIN(D29:$BK$29)>0),D4,9999) | E81: =IF(AND(E29>0,MIN(E29:$BK$29)>0),E4,9999) | F81: =IF(AND(F29>0,MIN(F29:$BK$29)>0),F4,9999) | G81: =IF(AND(G29>0,MIN(G29:$BK$29)>0),G4,9999) | H81: =IF(AND(H29>0,MIN(H29:$BK$29)>0),H4,9999) | I81: =IF(AND(I29>0,MIN(I29:$BK$29)>0),I4,9999) | J81: =IF(AND(J29>0,MIN(J29:$BK$29)>0),J4,9999) | K81: =IF(AND(K29>0,MIN(K29:$BK$29)>0),K4,9999) | ... BK81: =IF(AND(BK29>0,MIN(BK29:$BK$29)>0),BK4,9999)
B82: Cumulative free cash flow turns positive | C82: mo | D82: =IF(D60>0,D4,9999) | E82: =IF(E60>0,E4,9999) | F82: =IF(F60>0,F4,9999) | G82: =IF(G60>0,G4,9999) | H82: =IF(H60>0,H4,9999) | I82: =IF(I60>0,I4,9999) | J82: =IF(J60>0,J4,9999) | K82: =IF(K60>0,K4,9999) | ... BK82: =IF(BK60>0,BK4,9999)

Sheet Annual
B2: ANNUAL FINANCIAL STATEMENTS — YEARS 1 TO 5
B3: All figures in euros. Year 1 includes the product build months, so it carries only part of a year of trading.
C5: Unit | D5: Year 1 | E5: Year 2 | F5: Year 3 | G5: Year 4 | H5: Year 5 | I5: 5-year total
B7: PROFIT & LOSS
B8: Net revenue — Portugal | C8: EUR | D8: =SUM('P&L Monthly'!D8:O8) | E8: =SUM('P&L Monthly'!P8:AA8) | F8: =SUM('P&L Monthly'!AB8:AM8) | G8: =SUM('P&L Monthly'!AN8:AY8) | H8: =SUM('P&L Monthly'!AZ8:BK8) | I8: =SUM(D8:H8)
B9: Net revenue — Spain | C9: EUR | D9: =SUM('P&L Monthly'!D9:O9) | E9: =SUM('P&L Monthly'!P9:AA9) | F9: =SUM('P&L Monthly'!AB9:AM9) | G9: =SUM('P&L Monthly'!AN9:AY9) | H9: =SUM('P&L Monthly'!AZ9:BK9) | I9: =SUM(D9:H9)
B10: Total net revenue | C10: EUR | D10: =SUM('P&L Monthly'!D10:O10) | E10: =SUM('P&L Monthly'!P10:AA10) | F10: =SUM('P&L Monthly'!AB10:AM10) | G10: =SUM('P&L Monthly'!AN10:AY10) | H10: =SUM('P&L Monthly'!AZ10:BK10) | I10: =SUM(D10:H10)
B11: Cost of service | C11: EUR | D11: =SUM('P&L Monthly'!D13:O13) | E11: =SUM('P&L Monthly'!P13:AA13) | F11: =SUM('P&L Monthly'!AB13:AM13) | G11: =SUM('P&L Monthly'!AN13:AY13) | H11: =SUM('P&L Monthly'!AZ13:BK13) | I11: =SUM(D11:H11)
B12: Gross profit | C12: EUR | D12: =SUM('P&L Monthly'!D14:O14) | E12: =SUM('P&L Monthly'!P14:AA14) | F12: =SUM('P&L Monthly'!AB14:AM14) | G12: =SUM('P&L Monthly'!AN14:AY14) | H12: =SUM('P&L Monthly'!AZ14:BK14) | I12: =SUM(D12:H12)
B13: Gross margin | C13: % | D13: =IFERROR(D12/D10,0) | E13: =IFERROR(E12/E10,0) | F13: =IFERROR(F12/F10,0) | G13: =IFERROR(G12/G10,0) | H13: =IFERROR(H12/H10,0) | I13: =IFERROR(I12/I10,0)
B14: Customer acquisition (COCA) | C14: EUR | D14: =SUM('P&L Monthly'!D17:O17) | E14: =SUM('P&L Monthly'!P17:AA17) | F14: =SUM('P&L Monthly'!AB17:AM17) | G14: =SUM('P&L Monthly'!AN17:AY17) | H14: =SUM('P&L Monthly'!AZ17:BK17) | I14: =SUM(D14:H14)
B15: Brand marketing & content | C15: EUR | D15: =SUM('P&L Monthly'!D18:O18) | E15: =SUM('P&L Monthly'!P18:AA18) | F15: =SUM('P&L Monthly'!AB18:AM18) | G15: =SUM('P&L Monthly'!AN18:AY18) | H15: =SUM('P&L Monthly'!AZ18:BK18) | I15: =SUM(D15:H15)
B16: Personnel | C16: EUR | D16: =SUM('P&L Monthly'!D19:O19) | E16: =SUM('P&L Monthly'!P19:AA19) | F16: =SUM('P&L Monthly'!AB19:AM19) | G16: =SUM('P&L Monthly'!AN19:AY19) | H16: =SUM('P&L Monthly'!AZ19:BK19) | I16: =SUM(D16:H16)
B17: Cloud & tools | C17: EUR | D17: =SUM('P&L Monthly'!D20:O20) | E17: =SUM('P&L Monthly'!P20:AA20) | F17: =SUM('P&L Monthly'!AB20:AM20) | G17: =SUM('P&L Monthly'!AN20:AY20) | H17: =SUM('P&L Monthly'!AZ20:BK20) | I17: =SUM(D17:H17)
B18: General & administrative | C18: EUR | D18: =SUM('P&L Monthly'!D21:O21) | E18: =SUM('P&L Monthly'!P21:AA21) | F18: =SUM('P&L Monthly'!AB21:AM21) | G18: =SUM('P&L Monthly'!AN21:AY21) | H18: =SUM('P&L Monthly'!AZ21:BK21) | I18: =SUM(D18:H18)
B19: Total operating expenses | C19: EUR | D19: =SUM('P&L Monthly'!D22:O22) | E19: =SUM('P&L Monthly'!P22:AA22) | F19: =SUM('P&L Monthly'!AB22:AM22) | G19: =SUM('P&L Monthly'!AN22:AY22) | H19: =SUM('P&L Monthly'!AZ22:BK22) | I19: =SUM(D19:H19)
B20: EBITDA | C20: EUR | D20: =SUM('P&L Monthly'!D23:O23) | E20: =SUM('P&L Monthly'!P23:AA23) | F20: =SUM('P&L Monthly'!AB23:AM23) | G20: =SUM('P&L Monthly'!AN23:AY23) | H20: =SUM('P&L Monthly'!AZ23:BK23) | I20: =SUM(D20:H20)
B21: EBITDA margin | C21: % | D21: =IFERROR(D20/D10,0) | E21: =IFERROR(E20/E10,0) | F21: =IFERROR(F20/F10,0) | G21: =IFERROR(G20/G10,0) | H21: =IFERROR(H20/H10,0) | I21: =IFERROR(I20/I10,0)
B22: Depreciation | C22: EUR | D22: =SUM('P&L Monthly'!D25:O25) | E22: =SUM('P&L Monthly'!P25:AA25) | F22: =SUM('P&L Monthly'!AB25:AM25) | G22: =SUM('P&L Monthly'!AN25:AY25) | H22: =SUM('P&L Monthly'!AZ25:BK25) | I22: =SUM(D22:H22)
B23: EBIT | C23: EUR | D23: =SUM('P&L Monthly'!D26:O26) | E23: =SUM('P&L Monthly'!P26:AA26) | F23: =SUM('P&L Monthly'!AB26:AM26) | G23: =SUM('P&L Monthly'!AN26:AY26) | H23: =SUM('P&L Monthly'!AZ26:BK26) | I23: =SUM(D23:H23)
B24: Corporation tax | C24: EUR | D24: =SUM('P&L Monthly'!D28:O28) | E24: =SUM('P&L Monthly'!P28:AA28) | F24: =SUM('P&L Monthly'!AB28:AM28) | G24: =SUM('P&L Monthly'!AN28:AY28) | H24: =SUM('P&L Monthly'!AZ28:BK28) | I24: =SUM(D24:H24)
B25: Net income | C25: EUR | D25: =SUM('P&L Monthly'!D29:O29) | E25: =SUM('P&L Monthly'!P29:AA29) | F25: =SUM('P&L Monthly'!AB29:AM29) | G25: =SUM('P&L Monthly'!AN29:AY29) | H25: =SUM('P&L Monthly'!AZ29:BK29) | I25: =SUM(D25:H25)
B26: Net margin | C26: % | D26: =IFERROR(D25/D10,0) | E26: =IFERROR(E25/E10,0) | F26: =IFERROR(F25/F10,0) | G26: =IFERROR(G25/G10,0) | H26: =IFERROR(H25/H10,0) | I26: =IFERROR(I25/I10,0)
B28: CUSTOMERS
B29: Active customers — Portugal (year end) | C29: EUR | D29: ='Model PT'!O13 | E29: ='Model PT'!AA13 | F29: ='Model PT'!AM13 | G29: ='Model PT'!AY13 | H29: ='Model PT'!BK13 | I29: =H29
B30: Active customers — Spain (year end) | C30: EUR | D30: ='Model ES'!O13 | E30: ='Model ES'!AA13 | F30: ='Model ES'!AM13 | G30: ='Model ES'!AY13 | H30: ='Model ES'!BK13 | I30: =H30
B31: Total active customers (year end) | D31: =D29+D30 | E31: =E29+E30 | F31: =F29+F30 | G31: =G29+G30 | H31: =H29+H30 | I31: =H31
B32: New customers acquired during the year | D32: =SUM('Model PT'!D11:O11)+SUM('Model ES'!D11:O11) | E32: =SUM('Model PT'!P11:AA11)+SUM('Model ES'!P11:AA11) | F32: =SUM('Model PT'!AB11:AM11)+SUM('Model ES'!AB11:AM11) | G32: =SUM('Model PT'!AN11:AY11)+SUM('Model ES'!AN11:AY11) | H32: =SUM('Model PT'!AZ11:BK11)+SUM('Model ES'!AZ11:BK11) | I32: =SUM(D32:H32)
B33: Net revenue per customer per month (blended) | D33: =IFERROR(D10/(SUM('Model PT'!D14:O14)+SUM('Model ES'!D14:O14)),0) | E33: =IFERROR(E10/(SUM('Model PT'!P14:AA14)+SUM('Model ES'!P14:AA14)),0) | F33: =IFERROR(F10/(SUM('Model PT'!AB14:AM14)+SUM('Model ES'!AB14:AM14)),0) | G33: =IFERROR(G10/(SUM('Model PT'!AN14:AY14)+SUM('Model ES'!AN14:AY14)),0) | H33: =IFERROR(H10/(SUM('Model PT'!AZ14:BK14)+SUM('Model ES'!AZ14:BK14)),0)
B35: CASH FLOW
B36: EBITDA | C36: EUR | D36: =SUM('P&L Monthly'!D55:O55) | E36: =SUM('P&L Monthly'!P55:AA55) | F36: =SUM('P&L Monthly'!AB55:AM55) | G36: =SUM('P&L Monthly'!AN55:AY55) | H36: =SUM('P&L Monthly'!AZ55:BK55) | I36: =SUM(D36:H36)
B37: Corporation tax paid | C37: EUR | D37: =SUM('P&L Monthly'!D56:O56) | E37: =SUM('P&L Monthly'!P56:AA56) | F37: =SUM('P&L Monthly'!AB56:AM56) | G37: =SUM('P&L Monthly'!AN56:AY56) | H37: =SUM('P&L Monthly'!AZ56:BK56) | I37: =SUM(D37:H37)
B38: Capital expenditure | C38: EUR | D38: =SUM('P&L Monthly'!D57:O57) | E38: =SUM('P&L Monthly'!P57:AA57) | F38: =SUM('P&L Monthly'!AB57:AM57) | G38: =SUM('P&L Monthly'!AN57:AY57) | H38: =SUM('P&L Monthly'!AZ57:BK57) | I38: =SUM(D38:H38)
B39: Change in working capital | C39: EUR | D39: =SUM('P&L Monthly'!D58:O58) | E39: =SUM('P&L Monthly'!P58:AA58) | F39: =SUM('P&L Monthly'!AB58:AM58) | G39: =SUM('P&L Monthly'!AN58:AY58) | H39: =SUM('P&L Monthly'!AZ58:BK58) | I39: =SUM(D39:H39)
B40: Free cash flow | C40: EUR | D40: =SUM('P&L Monthly'!D59:O59) | E40: =SUM('P&L Monthly'!P59:AA59) | F40: =SUM('P&L Monthly'!AB59:AM59) | G40: =SUM('P&L Monthly'!AN59:AY59) | H40: =SUM('P&L Monthly'!AZ59:BK59) | I40: =SUM(D40:H40)
B41: Cumulative free cash flow (year end) | C41: EUR | D41: ='P&L Monthly'!O60 | E41: ='P&L Monthly'!AA60 | F41: ='P&L Monthly'!AM60 | G41: ='P&L Monthly'!AY60 | H41: ='P&L Monthly'!BK60 | I41: =H41
B42: Founders' equity injected | C42: EUR | D42: =SUM('P&L Monthly'!D62:O62) | E42: =SUM('P&L Monthly'!P62:AA62) | F42: =SUM('P&L Monthly'!AB62:AM62) | G42: =SUM('P&L Monthly'!AN62:AY62) | H42: =SUM('P&L Monthly'!AZ62:BK62) | I42: =SUM(D42:H42)
B43: Cumulative equity invested (year end) | C43: EUR | D43: ='P&L Monthly'!O63 | E43: ='P&L Monthly'!AA63 | F43: ='P&L Monthly'!AM63 | G43: ='P&L Monthly'!AY63 | H43: ='P&L Monthly'!BK63 | I43: =H43
B44: Cash — closing balance | C44: EUR | D44: ='P&L Monthly'!O64 | E44: ='P&L Monthly'!AA64 | F44: ='P&L Monthly'!AM64 | G44: ='P&L Monthly'!AY64 | H44: ='P&L Monthly'!BK64 | I44: =H44
B46: BALANCE SHEET (year end)
B47: Cash | C47: EUR | D47: ='P&L Monthly'!O67 | E47: ='P&L Monthly'!AA67 | F47: ='P&L Monthly'!AM67 | G47: ='P&L Monthly'!AY67 | H47: ='P&L Monthly'!BK67 | I47: =H47
B48: Receivables | C48: EUR | D48: ='P&L Monthly'!O68 | E48: ='P&L Monthly'!AA68 | F48: ='P&L Monthly'!AM68 | G48: ='P&L Monthly'!AY68 | H48: ='P&L Monthly'!BK68 | I48: =H48
B49: Net fixed assets | C49: EUR | D49: ='P&L Monthly'!O69 | E49: ='P&L Monthly'!AA69 | F49: ='P&L Monthly'!AM69 | G49: ='P&L Monthly'!AY69 | H49: ='P&L Monthly'!BK69 | I49: =H49
B50: Total assets | C50: EUR | D50: ='P&L Monthly'!O70 | E50: ='P&L Monthly'!AA70 | F50: ='P&L Monthly'!AM70 | G50: ='P&L Monthly'!AY70 | H50: ='P&L Monthly'!BK70 | I50: =H50
B51: Payables | C51: EUR | D51: ='P&L Monthly'!O71 | E51: ='P&L Monthly'!AA71 | F51: ='P&L Monthly'!AM71 | G51: ='P&L Monthly'!AY71 | H51: ='P&L Monthly'!BK71 | I51: =H51
B52: Deferred revenue | C52: EUR | D52: ='P&L Monthly'!O72 | E52: ='P&L Monthly'!AA72 | F52: ='P&L Monthly'!AM72 | G52: ='P&L Monthly'!AY72 | H52: ='P&L Monthly'!BK72 | I52: =H52
B53: Paid-in equity | C53: EUR | D53: ='P&L Monthly'!O73 | E53: ='P&L Monthly'!AA73 | F53: ='P&L Monthly'!AM73 | G53: ='P&L Monthly'!AY73 | H53: ='P&L Monthly'!BK73 | I53: =H53
B54: Retained earnings | C54: EUR | D54: ='P&L Monthly'!O74 | E54: ='P&L Monthly'!AA74 | F54: ='P&L Monthly'!AM74 | G54: ='P&L Monthly'!AY74 | H54: ='P&L Monthly'!BK74 | I54: =H54
B55: Total liabilities & equity | C55: EUR | D55: ='P&L Monthly'!O75 | E55: ='P&L Monthly'!AA75 | F55: ='P&L Monthly'!AM75 | G55: ='P&L Monthly'!AY75 | H55: ='P&L Monthly'!BK75 | I55: =H55
B56: Balance check (must be nil) | C56: EUR | D56: ='P&L Monthly'!O76 | E56: ='P&L Monthly'!AA76 | F56: ='P&L Monthly'!AM76 | G56: ='P&L Monthly'!AY76 | H56: ='P&L Monthly'!BK76 | I56: =H56
