Workbook

Sheet 01 Dashboard
B1: REVII · WRIST-WEARABLE BENCHMARK — EXECUTIVE DASHBOARD
B2: Research as of 27 Oct 2026 · Wonlex wrist wearables vs Revii's customer research · every figure below recalculates from the input sheets
B4: =IF(COUNTIF('10 Scoring & Weights'!$S$87:$S$99,"Eligible")=0,"No wearable is confirmed eligible yet — none has supplier-verified data access. "&IF('11 Ranking & Shortlist'!C41="","No model is conditionally eligible either — see the pending-verification list.","Provisional leader: "&'11 Ranking & Shortlist'!C41&" ("&TEXT('11 Ranking & Shortlist'!D41,"0.0")&"/100)"&IF('11 Ranking & Shortlist'!C42="","",", then "&'11 Ranking & Shortlist'!C42&IF('11 Ranking & Shortlist'!C43="",""," and "&'11 Ranking & Shortlist'!C43)&", all within "&TEXT('11 Ranking & Shortlist'!D41-MIN('11 Ranking & Shortlist'!D41:D43),"0.0")&" points — a tie on current evidence")&". Treat these as the models to verify, not a purchase decision."),COUNTIF('10 Scoring & Weights'!$S$87:$S$99,"Eligible")&" model(s) eligible. Confirmed leader: "&'11 Ranking & Shortlist'!C24&".") -> No wearable is confirmed eligible yet — none has supplier-verified data access. Provisional leader: HW19 (55.8/100), then CT34 and VB10, all within 2.6 points — a tie on current evidence. Treat these as the models to verify, not a purchase decision.
B6: Manufacturers authorised | C6: Models catalogued | D6: Wrist models scored | E6: Eligible (all gates passed) | F6: Conditionally eligible | G6: Pending verification | H6: Open P1 supplier questions | I6: Fleet used for TCO
B7: =SUMPRODUCT(1/COUNTIF('02 Model Master List'!$B$6:$B$53,'02 Model Master List'!$B$6:$B$53)) -> 5 | C7: =COUNTA('02 Model Master List'!$C$6:$C$53) -> 48 | D7: =COUNTA('03 Feature Comparison'!$C$6:$C$18) -> 13 | E7: =COUNTIF('10 Scoring & Weights'!$S$87:$S$99,"Eligible") -> 0 | F7: =COUNTIF('10 Scoring & Weights'!$S$87:$S$99,"Conditionally eligible") -> 3 | G7: =COUNTIF('10 Scoring & Weights'!$S$87:$S$99,"Pending verification") -> 10 | H7: =COUNTIFS('15 Data Gaps & Questions'!$F$5:$F$60,"P1",'15 Data Gaps & Questions'!$H$5:$H$60,"<>Verified") -> 13 | I7: ='08 TCO Model'!$C$22 -> 1000
B9: Provisional ranking — conditionally eligible models (shortlist for supplier verification; none is eligible yet)
B10: # | C10: Model | D10: Overall | E10: Market fit (confirmed – potential) | F10: Integration | G10: Commercial | H10: TCO 36m / device (EUR) | I10: Integration status | J10: Eligibility | K10: Confidence | L10: Strongest need
B11: 1 | C11: ='11 Ranking & Shortlist'!C41 -> HW19 | D11: ='11 Ranking & Shortlist'!D41 -> 55.767454 | E11: =IF(C11="","",ROUND(INDEX('10 Scoring & Weights'!$J$87:$J$99,MATCH(C11,'10 Scoring & Weights'!$C$87:$C$99,0)),0)&" – "&ROUND(INDEX('10 Scoring & Weights'!$K$87:$K$99,MATCH(C11,'10 Scoring & Weights'!$C$87:$C$99,0)),0)) -> 57 – 94 | F11: ='11 Ranking & Shortlist'!F41 -> 53.75 | G11: ='11 Ranking & Shortlist'!G41 -> 30.562055 | H11: ='11 Ranking & Shortlist'!H41 -> 189.7286 | I11: ='11 Ranking & Shortlist'!K41 -> Conditional | J11: ='11 Ranking & Shortlist'!I41 -> Conditionally eligible | K11: ='11 Ranking & Shortlist'!J41 -> Medium | L11: =IF(C11="","",INDEX('06 Needs-Feature Map'!$Q$113:$Q$125,MATCH(C11,'06 Needs-Feature Map'!$C$113:$C$125,0))) -> N1
B12: 2 | C12: ='11 Ranking & Shortlist'!C42 -> CT34 | D12: ='11 Ranking & Shortlist'!D42 -> 55.034149 | E12: =IF(C12="","",ROUND(INDEX('10 Scoring & Weights'!$J$87:$J$99,MATCH(C12,'10 Scoring & Weights'!$C$87:$C$99,0)),0)&" – "&ROUND(INDEX('10 Scoring & Weights'!$K$87:$K$99,MATCH(C12,'10 Scoring & Weights'!$C$87:$C$99,0)),0)) -> 50 – 96 | F12: ='11 Ranking & Shortlist'!F42 -> 50 | G12: ='11 Ranking & Shortlist'!G42 -> 43.538109 | H12: ='11 Ranking & Shortlist'!H42 -> 140.1386 | I12: ='11 Ranking & Shortlist'!K42 -> Conditional | J12: ='11 Ranking & Shortlist'!I42 -> Conditionally eligible | K12: ='11 Ranking & Shortlist'!J42 -> Low | L12: =IF(C12="","",INDEX('06 Needs-Feature Map'!$Q$113:$Q$125,MATCH(C12,'06 Needs-Feature Map'!$C$113:$C$125,0))) -> N1
B13: 3 | C13: ='11 Ranking & Shortlist'!C43 -> VB10 | D13: ='11 Ranking & Shortlist'!D43 -> 53.207128 | E13: =IF(C13="","",ROUND(INDEX('10 Scoring & Weights'!$J$87:$J$99,MATCH(C13,'10 Scoring & Weights'!$C$87:$C$99,0)),0)&" – "&ROUND(INDEX('10 Scoring & Weights'!$K$87:$K$99,MATCH(C13,'10 Scoring & Weights'!$C$87:$C$99,0)),0)) -> 53 – 91 | F13: ='11 Ranking & Shortlist'!F43 -> 40 | G13: ='11 Ranking & Shortlist'!G43 -> 61.117119 | H13: ='11 Ranking & Shortlist'!H43 -> 93.23 | I13: ='11 Ranking & Shortlist'!K43 -> Conditional | J13: ='11 Ranking & Shortlist'!I43 -> Conditionally eligible | K13: ='11 Ranking & Shortlist'!J43 -> Medium | L13: =IF(C13="","",INDEX('06 Needs-Feature Map'!$Q$113:$Q$125,MATCH(C13,'06 Needs-Feature Map'!$C$113:$C$125,0))) -> N3
B14: 4 | C14: ='11 Ranking & Shortlist'!C44 | D14: ='11 Ranking & Shortlist'!D44 | E14: =IF(C14="","",ROUND(INDEX('10 Scoring & Weights'!$J$87:$J$99,MATCH(C14,'10 Scoring & Weights'!$C$87:$C$99,0)),0)&" – "&ROUND(INDEX('10 Scoring & Weights'!$K$87:$K$99,MATCH(C14,'10 Scoring & Weights'!$C$87:$C$99,0)),0)) | F14: ='11 Ranking & Shortlist'!F44 | G14: ='11 Ranking & Shortlist'!G44 | H14: ='11 Ranking & Shortlist'!H44 | I14: ='11 Ranking & Shortlist'!K44 | J14: ='11 Ranking & Shortlist'!I44 | K14: ='11 Ranking & Shortlist'!J44 | L14: =IF(C14="","",INDEX('06 Needs-Feature Map'!$Q$113:$Q$125,MATCH(C14,'06 Needs-Feature Map'!$C$113:$C$125,0)))
B15: 5 | C15: ='11 Ranking & Shortlist'!C45 | D15: ='11 Ranking & Shortlist'!D45 | E15: =IF(C15="","",ROUND(INDEX('10 Scoring & Weights'!$J$87:$J$99,MATCH(C15,'10 Scoring & Weights'!$C$87:$C$99,0)),0)&" – "&ROUND(INDEX('10 Scoring & Weights'!$K$87:$K$99,MATCH(C15,'10 Scoring & Weights'!$C$87:$C$99,0)),0)) | F15: ='11 Ranking & Shortlist'!F45 | G15: ='11 Ranking & Shortlist'!G45 | H15: ='11 Ranking & Shortlist'!H45 | I15: ='11 Ranking & Shortlist'!K45 | J15: ='11 Ranking & Shortlist'!I45 | K15: ='11 Ranking & Shortlist'!J45 | L15: =IF(C15="","",INDEX('06 Needs-Feature Map'!$Q$113:$Q$125,MATCH(C15,'06 Needs-Feature Map'!$C$113:$C$125,0)))
B17: Strong candidates still PENDING verification (no model-specific integration evidence yet) — top 3
B18: # | C18: Model | D18: Overall | E18: Market fit | F18: Integration | G18: Commercial | H18: TCO 36m / device (EUR) | I18: Integration status | J18: Eligibility | K18: Confidence
B19: 1 | C19: ='11 Ranking & Shortlist'!C58 -> HW20 | D19: ='11 Ranking & Shortlist'!D58 -> 55.888039 | E19: ='11 Ranking & Shortlist'!E58 -> 76.832089 | F19: ='11 Ranking & Shortlist'!F58 -> 32.5 | G19: ='11 Ranking & Shortlist'!G58 -> 34.562055 | H19: ='11 Ranking & Shortlist'!H58 -> 189.7286 | I19: ='11 Ranking & Shortlist'!K58 -> Not verified | J19: ='11 Ranking & Shortlist'!I58 -> Pending verification | K19: ='11 Ranking & Shortlist'!J58 -> Low
B20: 2 | C20: ='11 Ranking & Shortlist'!C59 -> MF90 | D20: ='11 Ranking & Shortlist'!D59 -> 50.896513 | E20: ='11 Ranking & Shortlist'!E59 -> 70.370989 | F20: ='11 Ranking & Shortlist'!F59 -> 22.5 | G20: ='11 Ranking & Shortlist'!G59 -> 56.5 | H20: ='11 Ranking & Shortlist'!H59 -> 66.69935 | I20: ='11 Ranking & Shortlist'!K59 -> Not verified | J20: ='11 Ranking & Shortlist'!I59 -> Pending verification | K20: ='11 Ranking & Shortlist'!J59 -> Medium
B21: 3 | C21: ='11 Ranking & Shortlist'!C60 -> CT31 | D21: ='11 Ranking & Shortlist'!D60 -> 50.075791 | E21: ='11 Ranking & Shortlist'!E60 -> 58.34465 | F21: ='11 Ranking & Shortlist'!F60 -> 32.5 | G21: ='11 Ranking & Shortlist'!G60 -> 55.201092 | H21: ='11 Ranking & Shortlist'!H60 -> 137.1632 | I21: ='11 Ranking & Shortlist'!K60 -> Not verified | J21: ='11 Ranking & Shortlist'!I60 -> Pending verification | K21: ='11 Ranking & Shortlist'!J60 -> Low
B22: ="Confirmed ranking: "&'11 Ranking & Shortlist'!B22 -> Confirmed ranking: No model currently passes all three mandatory gates — no confirmed ranking can be issued. See the provisional ranking.
B24: Best model by use case — within the ranking pool (live, from 13 and 11)
B25: Use case | C25: Top model | D25: Score | E25: Eligibility | F25: Runner-up
B26: ='13 Sensitivity & Scenarios'!C75 -> Market-research baseline | C26: ='13 Sensitivity & Scenarios'!D75 -> HW19 | D26: ='13 Sensitivity & Scenarios'!E75 -> 55.767454 | E26: ='13 Sensitivity & Scenarios'!F75 -> Conditionally eligible | F26: ='13 Sensitivity & Scenarios'!G75 -> CT34
B27: ='13 Sensitivity & Scenarios'!C76 -> Safety-first | C27: ='13 Sensitivity & Scenarios'!D76 -> HW19 | D27: ='13 Sensitivity & Scenarios'!E76 -> 58.412243 | E27: ='13 Sensitivity & Scenarios'!F76 -> Conditionally eligible | F27: ='13 Sensitivity & Scenarios'!G76 -> CT34
B28: ='13 Sensitivity & Scenarios'!C77 -> Wellbeing monitoring | C28: ='13 Sensitivity & Scenarios'!D77 -> VB10 | D28: ='13 Sensitivity & Scenarios'!E77 -> 56.053326 | E28: ='13 Sensitivity & Scenarios'!F77 -> Conditionally eligible | F28: ='13 Sensitivity & Scenarios'!G77 -> HW19
B29: ='13 Sensitivity & Scenarios'!C78 -> Ease-of-use | C29: ='13 Sensitivity & Scenarios'!D78 -> CT34 | D29: ='13 Sensitivity & Scenarios'!E78 -> 55.949167 | E29: ='13 Sensitivity & Scenarios'!F78 -> Conditionally eligible | F29: ='13 Sensitivity & Scenarios'!G78 -> HW19
B30: ='13 Sensitivity & Scenarios'!C79 -> Cost-efficiency | C30: ='13 Sensitivity & Scenarios'!D79 -> VB10 | D30: ='13 Sensitivity & Scenarios'!E79 -> 54.761902 | E30: ='13 Sensitivity & Scenarios'!F79 -> Conditionally eligible | F30: ='13 Sensitivity & Scenarios'!G79 -> CT34
B31: ='13 Sensitivity & Scenarios'!C80 -> Segment: independent / stable seniors | C31: ='13 Sensitivity & Scenarios'!D80 -> VB10 | D31: ='13 Sensitivity & Scenarios'!E80 -> 55.566467 | E31: ='13 Sensitivity & Scenarios'!F80 -> Conditionally eligible | F31: ='13 Sensitivity & Scenarios'!G80 -> CT34
B32: ='13 Sensitivity & Scenarios'!C81 -> Segment: vulnerable / higher dependency | C32: ='13 Sensitivity & Scenarios'!D81 -> HW19 | D32: ='13 Sensitivity & Scenarios'!E81 -> 56.707616 | E32: ='13 Sensitivity & Scenarios'!F81 -> Conditionally eligible | F32: ='13 Sensitivity & Scenarios'!G81 -> CT34
B33: Best cost-to-value (score per EUR 100 of 36-month TCO) | C33: =IFERROR(INDEX('11 Ranking & Shortlist'!$C$7:$C$19,MATCH(MAX('11 Ranking & Shortlist'!$T$7:$T$19),'11 Ranking & Shortlist'!$T$7:$T$19,0)),"") -> VB10 | D33: =MAX('11 Ranking & Shortlist'!$T$7:$T$19) -> 57.070823
B35: Critical uncertainties — open P1 supplier questions (15)
B36: ='15 Data Gaps & Questions'!B5 -> CT29 | C36: ='15 Data Gaps & Questions'!C5 -> Product identity and specification sheet | G36: ='15 Data Gaps & Questions'!D5 -> Supplied URL shows the S10 kids watch; no CT29 spec page exists | L36: ='15 Data Gaps & Questions'!H5 -> Open
B37: ='15 Data Gaps & Questions'!B6 -> CT34 | C37: ='15 Data Gaps & Questions'!C6 -> Health sensors on CT34 | G37: ='15 Data Gaps & Questions'!D6 -> Determines whether CT34 can serve early-decline needs (N2) or safety only | L37: ='15 Data Gaps & Questions'!H6 -> Open
B38: ='15 Data Gaps & Questions'!B7 -> CT34 | C38: ='15 Data Gaps & Questions'!C7 -> TCP protocol document and event list | G38: ='15 Data Gaps & Questions'!D7 -> Mandatory data-access gate | L38: ='15 Data Gaps & Questions'!H7 -> Open
B39: ='15 Data Gaps & Questions'!B8 -> CT34 | C39: ='15 Data Gaps & Questions'!C8 -> Two-way calling hardware; SIM size; EU operator testing | G39: ='15 Data Gaps & Questions'!D8 -> SOS without voice is weaker; SIM logistics | L39: ='15 Data Gaps & Questions'!H8 -> Open
B40: ='15 Data Gaps & Questions'!B9 -> VB10 | C40: ='15 Data Gaps & Questions'!C9 -> SDK support and licence | G40: ='15 Data Gaps & Questions'!D9 -> Mandatory data-access gate for VB10 | L40: ='15 Data Gaps & Questions'!H9 -> Open
B41: ='15 Data Gaps & Questions'!B10 -> VB10 | C41: ='15 Data Gaps & Questions'!C10 -> Fall detection / button | G41: ='15 Data Gaps & Questions'!D10 -> Top research need (N1); currently Unknown | L41: ='15 Data Gaps & Questions'!H10 -> Open
B42: ='15 Data Gaps & Questions'!B11 -> VB10 | C42: ='15 Data Gaps & Questions'!C11 -> Medical claims and estimation features | G42: ='15 Data Gaps & Questions'!D11 -> Regulatory exposure (MDR / AI Act) | L42: ='15 Data Gaps & Questions'!H11 -> Open
B43: ='15 Data Gaps & Questions'!B12 -> HW19 | C43: ='15 Data Gaps & Questions'!C12 -> KSCtracker API and hosting | G43: ='15 Data Gaps & Questions'!D12 -> Integration and GDPR transfer assessment | L43: ='15 Data Gaps & Questions'!H12 -> Open
B45: Charts
H62: Colours: categorical pair validated for colour-vision deficiency. Bars share one axis per chart; the market-fit chart's gap between the two bars is the share of each score that still rests on Unknown evidence.

Sheet 02 Model Master List
A1: MODEL MASTER LIST
A2: Every product considered: user-mandated, historical, discovered alternatives and screened-out items (with reasons). Scope: wrist-worn devices only.
A3: Authorised manufacturers: Wonlex (mandatory list + historical), 2M Engineering, Shelly, Aeotec, OWON (historical workbook). No other manufacturer was introduced. Excluded by scope: smart glasses (incl. Dinowear AI Glasses), rings and every other non-wrist category. No separate manufacturer/model list file was provided; the six images in the historical workbook are captures of Wonlex product pages (S39).
A5: ID | B5: Manufacturer | C5: Model | D5: Product category | E5: Form factor | F5: Official product URL | G5: Original source / input | H5: Classification | I5: Mandatory vs discovered | J5: Market availability | K5: Inclusion / exclusion rationale | L5: Integration status | M5: Eligibility | N5: Research completeness | O5: Notes
A6: M01 | B6: Wonlex | C6: VB10 | D6: Screenless BLE health band | E6: Wrist — band | F6: https://www.iwonlex.net/products/vb10-medical-grade-screenless-health-band-with-ecg-and-hrv-monitoring/ | G6: Brief — mandatory model | H6: User-mandated | I6: Mandatory | J6: Listed on manufacturer site (May 2026 spec) | K6: Mandatory. Richest physiological sensing (ECG 500 Hz, HRV, SpO2, sleep stages) with a public-but-licensed SDK pointer. | L6: ='04 API & Integration'!K6 -> Conditional | M6: ='10 Scoring & Weights'!S87 -> Conditionally eligible | N6: ='10 Scoring & Weights'!L87 -> 0.72222222
A7: M02 | B7: Wonlex | C7: CT29 | D7: 4G health bracelet with fall detection | E7: Wrist — band | F7: https://www.iwonlex.net/products/wonlex-4g-cheap-gps-wifi-calling-cat1-kids-smart-watch-s10/ | G7: Brief — mandatory model | H7: User-mandated | I7: Mandatory | J7: Name listed on manufacturer category page; no spec page found | K7: Mandatory. Supplied URL resolves to the S10 KIDS watch; CT29 specifications could not be established and S10 specs are not transferred. | L7: ='04 API & Integration'!K7 -> Not verified | M7: ='10 Scoring & Weights'!S88 -> Pending verification | N7: ='10 Scoring & Weights'!L88 -> 0.13513514
A8: M03 | B8: Wonlex | C8: CT34 | D8: 4G GPS screenless SOS band for seniors | E8: Wrist — band | F8: https://www.iwonlex.net/products/wonlex-ct34-4g-gps-screenless-sos-smart-band-for-seniors/ | G8: Brief — mandatory model | H8: User-mandated | I8: Mandatory | J8: Listed on manufacturer site; Alibaba storefront | K8: Mandatory. Simplest safety device: screenless, fall detection, SOS call, 4G, TCP integration stated on the model page. | L8: ='04 API & Integration'!K8 -> Conditional | M8: ='10 Scoring & Weights'!S89 -> Conditionally eligible | N8: ='10 Scoring & Weights'!L89 -> 0.51351351
A9: M04 | B9: Wonlex | C9: MF90 | D9: BLE screenless ECG & health band | E9: Wrist — band | F9: https://www.iwonlex.net/products/mf90-bluetooth-screenless-ecg---health-monitoring-band/ | G9: Historical workbook | H9: Historical comparison model | I9: Historical | J9: Listed on manufacturer site | K9: In historical benchmark; screenless ECG band, 7-15 day battery. | L9: ='04 API & Integration'!K9 -> Not verified | M9: ='10 Scoring & Weights'!S90 -> Pending verification | N9: ='10 Scoring & Weights'!L90 -> 0.61111111
A10: M05 | B10: Wonlex | C10: MF91 | D10: BLE screenless fitness/health bracelet | E10: Wrist — band | F10: https://www.iwonlex.net/products/mf91-screenless-health-fitness-bracelet-for-gym-and-sports-monitoring-band/ | G10: Historical workbook | H10: Historical comparison model | I10: Historical | J10: Listed on manufacturer site ('offline sale only, not for USA') | K10: In historical benchmark (only model with a cost); 28 g, lightest device. | L10: ='04 API & Integration'!K10 -> Not verified | M10: ='10 Scoring & Weights'!S91 -> Pending verification | N10: ='10 Scoring & Weights'!L91 -> 0.55555556
A11: M06 | B11: Wonlex | C11: MF40 | D11: BLE AMOLED watch with air-pump BP and ECG | E11: Wrist — watch | F11: https://www.iwonlex.net/top-5-smart-health-watches-for-seniors-aging-in-place/ | G11: Historical workbook | H11: Historical comparison model | I11: Historical | J11: Described on manufacturer articles; product page not captured | K11: In historical benchmark; only BLE device with cuff-type (air-pump) blood pressure. | L11: ='04 API & Integration'!K11 -> Not verified | M11: ='10 Scoring & Weights'!S92 -> Pending verification | N11: ='10 Scoring & Weights'!L92 -> 0.52777778
A12: M07 | B12: Wonlex | C12: HW20 | D12: 4G senior watch with air-pump BP | E12: Wrist — watch | F12: https://www.iwonlex.net/products/wonlex-hw20-4g-gps-senior-health-smartwatch-with-air-pump-blood-pressure-monitor/ | G12: Historical workbook | H12: Historical comparison model | I12: Historical | J12: Listed on manufacturer site | K12: In historical benchmark (cost 77); combines 4G safety with cuff-type BP. | L12: ='04 API & Integration'!K12 -> Not verified | M12: ='10 Scoring & Weights'!S93 -> Pending verification | N12: ='10 Scoring & Weights'!L93 -> 0.51351351
A13: M08 | B13: Wonlex | C13: MF91Pro | D13: BLE screenless medical-marketed ECG band | E13: Wrist — band | F13: https://www.iwonlex.net/products/mf91pro-medical-grade-screenless-health-band-with-ecg-and-hrv-monitoring/ | G13: Discovered — Wonlex catalogue | H13: Additional shortlisted alternative | I13: Discovered | J13: Listed on manufacturer site | K13: Same documented platform as VB10 (nRF54L15, TI4950, 265 mAh); included to test whether VB10 has an interchangeable second source. | L13: ='04 API & Integration'!K13 -> Not verified | M13: ='10 Scoring & Weights'!S94 -> Pending verification | N13: ='10 Scoring & Weights'!L94 -> 0.33333333
A14: M09 | B14: Wonlex | C14: HW20Pro | D14: 4G + BLE watch with air-pump BP | E14: Wrist — watch | F14: https://www.iwonlex.net/products/wonlex-4g-ble-medical-air-pump-smartwatch-hw20pro--precision-bp---senior-health-monitoring/ | G14: Discovered — Wonlex catalogue | H14: Additional shortlisted alternative | I14: Discovered | J14: Listed on manufacturer site; Alibaba listing | K14: Successor to historical HW20 with documented fall detection and power-saving BLE co-processor. | L14: ='04 API & Integration'!K14 -> Not verified | M14: ='10 Scoring & Weights'!S95 -> Pending verification | N14: ='10 Scoring & Weights'!L95 -> 0.40540541
A15: M10 | B15: Wonlex | C15: HW19 | D15: 4G AMOLED senior health watch | E15: Wrist — watch | F15: https://www.iwonlex.net/products/hw19-4g-senior-health-smartwatch-with-sos-and-gps/ | G15: Discovered — Wonlex catalogue | H15: Additional shortlisted alternative | I15: Discovered | J15: Listed on manufacturer site | K15: Only model documenting multi-sensor (barometric) fall detection; KSCtracker platform named on the model page. | L15: ='04 API & Integration'!K15 -> Conditional | M15: ='10 Scoring & Weights'!S96 -> Conditionally eligible | N15: ='10 Scoring & Weights'!L96 -> 0.64864865
A16: M11 | B16: Wonlex | C16: CT20S | D16: 4G senior watch with fall detection | E16: Wrist — watch | F16: https://www.iwonlex.net/products/wonlex-ct20s-4g-smart-watch-for-elderly-with-large-screen-and-fall-detection/ | G16: Discovered — Wonlex catalogue | H16: Additional shortlisted alternative | I16: Discovered | J16: Listed on manufacturer site | K16: Large-screen 4G watch with automatic fall-triggered SOS and IP67; screen-based alternative to CT34. | L16: ='04 API & Integration'!K16 -> Not verified | M16: ='10 Scoring & Weights'!S97 -> Pending verification | N16: ='10 Scoring & Weights'!L97 -> 0.43243243
A17: M12 | B17: Wonlex | C17: CT30 (band) | D17: 4G GPS senior band with HR/BP | E17: Wrist — band | F17: https://www.iwonlex.net/products/wonlex-4g-cat1-hr-br-monitoring-gps-kids-watch-s8-with-wifi-sos/ | G17: Discovered — Wonlex catalogue | H17: Additional shortlisted alternative | I17: Discovered | J17: Listed on manufacturer site | K17: 4G band adding HR/BP and activity to SOS + GPS; candidate middle ground between CT34 and VB10. | L17: ='04 API & Integration'!K17 -> Not verified | M17: ='10 Scoring & Weights'!S98 -> Pending verification | N17: ='10 Scoring & Weights'!L98 -> 0.32432432
A18: M13 | B18: Wonlex | C18: CT31 | D18: 4G screenless two-button senior band | E18: Wrist — band | F18: https://www.iwonlex.net/products/4g-ct31-screenless-senior-band-with-dual-big-button-and-big-battery/ | G18: Discovered — Wonlex catalogue | H18: Additional shortlisted alternative | I18: Discovered | J18: Listed on manufacturer site; Alibaba MOQ 2 | K18: Screenless, largest battery (950 mAh), dedicated health-check and SOS buttons; positioned for telecare integrators. | L18: ='04 API & Integration'!K18 -> Not verified | M18: ='10 Scoring & Weights'!S99 -> Pending verification | N18: ='10 Scoring & Weights'!L99 -> 0.43243243
A19: X01 | B19: Wonlex | C19: S10 | D19: 4G kids smartwatch | E19: Wrist | G19: URL supplied for CT29 | H19: Screened out | I19: Discovered | K19: Children's product with touch screen; it is what the supplied CT29 URL shows. Recorded to prevent its specifications being attributed to CT29. | L19: — | M19: Screened out | N19: —
A20: X02 | B20: Wonlex | C20: CT10T | D20: 4G senior smartwatch | E20: Wrist | G20: Discovered — Wonlex catalogue | H20: Screened out | I20: Discovered | K20: SOS/HR/BP watch without documented fall detection; functionally dominated by CT20S (same chipset class, adds fall detection). | L20: — | M20: Screened out | N20: —
A21: X03 | B21: Wonlex | C21: KT17S | D21: 4G SOS senior smartwatch | E21: Wrist | G21: Discovered — Wonlex catalogue | H21: Screened out | I21: Discovered | K21: Marginal variant of the CT20S/HW19 class; fall detection only in a third-party search summary. | L21: — | M21: Screened out | N21: —
A22: X04 | B22: Wonlex | C22: KT43 | D22: 4G Android senior smartwatch | E22: Wrist | G22: Discovered — Wonlex catalogue | H22: Screened out | I22: Discovered | K22: Full Android OS raises power draw and interface complexity — contrary to the research priority on ease of use. | L22: — | M22: Screened out | N22: —
A23: X05 | B23: Wonlex | C23: MF19 / MF30 | D23: BLE AMOLED ECG / BP watches | E23: Wrist | G23: Discovered — Wonlex catalogue | H23: Screened out | I23: Discovered | K23: Near-duplicates of MF40 (BLE, AMOLED, ECG/air-pump BP); MF40 retained as the representative. | L23: — | M23: Screened out | N23: —
A24: X06 | B24: Wonlex | C24: CT30 Pro | D24: 4G senior smartwatch | E24: Wrist | G24: Discovered — marketplace | H24: Screened out | I24: Discovered | K24: Watch-format variant of CT30; CT30 band retained. | L24: — | M24: Screened out | N24: —
A25: X07 | B25: Wonlex | C25: Marsfit Apex ring | D25: Smart ring | E25: Ring | G25: Discovered — Wonlex catalogue | H25: Screened out | I25: Discovered | K25: Not wrist-worn (ring) — outside product scope. | L25: — | M25: Screened out | N25: —
A26: X08 | B26: Wonlex | C26: KT34 / KT10 / CT10 kids watches | D26: Kids smartwatches | E26: Wrist | G26: Discovered — Wonlex catalogue | H26: Screened out | I26: Discovered | K26: Children's products. | L26: — | M26: Screened out | N26: —
A27: H01 | B27: 2M Engineering | C27: Health Patch Platform | D27: Chest/body patch | E27: Non-wrist | G27: Historical workbook | H27: Screened out | I27: Historical | K27: Not wrist-worn (adhesive patch). | L27: — | M27: Screened out | N27: —
A28: H02 | B28: 2M Engineering | C28: P-CARDIO HP201 | D28: 1-lead ECG patch | E28: Non-wrist | G28: Historical workbook | H28: Screened out | I28: Historical | K28: Not wrist-worn (patch). | L28: — | M28: Screened out | N28: —
A29: H03 | B29: 2M Engineering | C29: T-Sense Smart Shirt | D29: Smart textile | E29: Non-wrist | G29: Historical workbook | H29: Screened out | I29: Historical | K29: Not wrist-worn (garment). | L29: — | M29: Screened out | N29: —
A30: H04 | B30: 2M Engineering | C30: Activ8 Platform | D30: Activity monitor | E30: Non-wrist | G30: Historical workbook | H30: Screened out | I30: Historical | K30: Prescribed wear location is trouser pocket / thigh (S36). | L30: — | M30: Screened out | N30: —
... A53: I22 | B53: OWON | C53: WPS311-Z | D53: Ambient IoT sensor / switch / button | E53: Non-wrist (home) | G53: Historical workbook | H53: Screened out | I53: Historical | K53: Not wrist-worn — outside this benchmark; retained for the IoT Monitor roadmap. | L53: — | M53: Screened out | N53: —

Sheet 03 Feature Comparison
A1: DETAILED FEATURE COMPARISON — HARDWARE CAPABILITY
A2: Rows = shortlisted wrist wearables. Status = what the HARDWARE offers per captured evidence (Revii's data access is separate: 04). Hover any status cell for grade, source and note.
A3: Legend: | B3: Yes | C3: Conditional | D3: Unknown | E3: No | F3: N/A | G3: Unknown ≠ No: Unknown means no captured evidence either way. Blue status cells are editable — update them as suppliers answer and every score recalculates.
F4: Physiological | G4: Physiological | H4: Physiological | I4: Physiological | J4: Physiological | K4: Physiological | L4: Physiological | M4: Physiological | N4: Physiological | O4: Safety | P4: Safety | Q4: Safety | R4: Safety | S4: Safety | T4: Connectivity | U4: Connectivity | V4: Usability | W4: Wellbeing | X4: Risk flag | Y4: Privacy | Z4: Connectivity | AA4: Usability | AC4: Specifications (numbers are numeric; blank = not captured)
A5: ID | B5: Manufacturer | C5: Model | D5: Form | E5: Link | F5: F01 Heart rate | G5: F02 Heart-rate variability (HRV) | H5: F03 ECG | I5: F04 SpO2 | J5: F05 Blood pressure | K5: F06 Body / skin temperature | L5: F07 Sleep monitoring | M5: F08 Steps & activity | N5: F09 Stress indicator | O5: F10 Automatic fall detection | P5: F11 SOS button | Q5: F12 Two-way voice calling | R5: F13 GNSS positioning | S5: F14 Geofencing | T5: F15 Standalone 4G/LTE | U5: F16 Works without a smartphone | V5: F17 Screenless / minimal interface | W5: F18 Medication reminder | X5: F19 Non-invasive glucose / lipid estimation | Y5: F20 No camera | Z5: F21 Offline on-device data storage | AA5: F22 Water resistance IP67 or better | AC5: Chipset / sensor platform | AD5: Connectivity | AE5: LTE bands | AF5: Battery (mAh) | AG5: Battery life — typical use, lower bound (days) | AH5: Battery evidence | AI5: Battery note | AJ5: Weight (g) | AK5: Dimensions | AL5: Display | AM5: Water rating | AN5: Charging | AO5: SIM | AP5: App / platform | AQ5: Sampling mode
A6: M01 | B6: Wonlex | C6: VB10 | D6: Band | E6: BLE | F6: Yes | G6: Yes | H6: Yes | I6: Yes | J6: Unknown | K6: Yes | L6: Yes | M6: Yes | N6: Yes | O6: Unknown | P6: Unknown | Q6: Unknown | R6: No | S6: No | T6: No | U6: No | V6: Yes | W6: Unknown | X6: Yes | Y6: Yes | Z6: Unknown | AA6: Yes | AC6: Nordic nRF54L15 + TI4950 AFE | AD6: BLE 6.0 | AE6: — | AF6: 265 | AG6: 10 | AH6: X | AI6: Spec table 'active up to 10 d'; intro says '10 d standby' | AK6: Not captured | AL6: Screenless | AM6: IP68 | AN6: Magnetic pin dock | AO6: — | AP6: Gband Companion App; SDK pointer github.com/HBandSDK | AQ6: Real-time optical; ECG 500 Hz / PPG 50 Hz
A7: M02 | B7: Wonlex | C7: CT29 | D7: Band | E7: 4G | F7: Unknown | G7: Unknown | H7: Unknown | I7: Unknown | J7: Unknown | K7: Unknown | L7: Unknown | M7: Unknown | N7: Unknown | O7: Yes | P7: Unknown | Q7: Unknown | R7: Unknown | S7: Unknown | T7: Yes | U7: Conditional | V7: Unknown | W7: Unknown | X7: Unknown | Y7: Unknown | Z7: Unknown | AA7: Unknown | AD7: 4G (per name) | AE7: Unknown | AK7: Unknown | AL7: Unknown | AM7: Unknown | AN7: Unknown | AO7: Unknown | AP7: Unknown | AQ7: Unknown
A8: M03 | B8: Wonlex | C8: CT34 | D8: Band | E8: 4G | F8: Unknown | G8: Unknown | H8: Unknown | I8: Unknown | J8: Unknown | K8: Unknown | L8: Unknown | M8: Unknown | N8: Unknown | O8: Yes | P8: Yes | Q8: Conditional | R8: Yes | S8: Unknown | T8: Yes | U8: Yes | V8: Yes | W8: Unknown | X8: Unknown | Y8: Yes | Z8: Unknown | AA8: Yes | AC8: ASR3603S (RTOS) | AD8: 4G Cat1 + GSM | AE8: B1/B2/B3/B5/B7/B8/B20 | AF8: 530 | AG8: 3 | AH8: B | AI8: 3-5 days continuous use claimed | AK8: Not captured | AL8: Screenless | AM8: IP67 | AN8: Not captured | AO8: Not captured | AP8: TCP protocol to care platform | AQ8: Not documented
A9: M04 | B9: Wonlex | C9: MF90 | D9: Band | E9: BLE | F9: Yes | G9: Yes | H9: Yes | I9: Yes | J9: Conditional | K9: Yes | L9: Yes | M9: Yes | N9: Yes | O9: Unknown | P9: Unknown | Q9: Unknown | R9: No | S9: No | T9: No | U9: No | V9: Yes | W9: Yes | X9: Yes | Y9: Yes | Z9: Unknown | AA9: Yes | AC9: PPG GH3228T | AD9: BLE 5.3 | AE9: — | AF9: 180 | AG9: 7 | AH9: B | AI9: 7-15 days typical; 30+ days standby | AK9: 42.3 x 27.4 x 8.0 mm | AL9: Screenless | AM9: IP68 | AN9: Magnetic | AO9: — | AP9: Companion app; remote family view | AQ9: 24 h HR; ECG 500 Hz
A10: M05 | B10: Wonlex | C10: MF91 | D10: Band | E10: BLE | F10: Yes | G10: Yes | H10: Unknown | I10: Yes | J10: Conditional | K10: Yes | L10: Yes | M10: Yes | N10: Yes | O10: Unknown | P10: Unknown | Q10: Unknown | R10: No | S10: No | T10: No | U10: No | V10: Yes | W10: Yes | X10: Yes | Y10: Yes | Z10: Unknown | AA10: Yes | AC10: JL7013A | AD10: BLE 5.3 + NFC | AE10: — | AF10: 125 | AG10: 7 | AH10: B | AI10: 7-15 days typical; 30+ days standby | AJ10: 28 | AK10: 39 x 29 x 10 mm | AL10: Screenless | AM10: IP68 | AN10: Magnetic | AO10: — | AP10: Companion app | AQ10: 24 h HR
A11: M06 | B11: Wonlex | C11: MF40 | D11: Watch | E11: BLE | F11: Yes | G11: Unknown | H11: Yes | I11: Yes | J11: Yes | K11: Unknown | L11: Yes | M11: Yes | N11: Yes | O11: Unknown | P11: Unknown | Q11: Unknown | R11: No | S11: No | T11: No | U11: No | V11: No | W11: Unknown | X11: Unknown | Y11: Yes | Z11: Unknown | AA11: No | AC11: TI4950 ECG; Murata air pump | AD11: BLE 5.3 | AE11: — | AI11: Not found (MF30 sibling: 300 mAh — not transferred) | AK11: Not captured | AL11: AMOLED touchscreen (size conflicting) | AM11: IP66 | AN11: Not captured | AO11: — | AP11: Companion app | AQ11: 24/7 HR & SpO2
A12: M07 | B12: Wonlex | C12: HW20 | D12: Watch | E12: 4G | F12: Yes | G12: Unknown | H12: Unknown | I12: Yes | J12: Yes | K12: Unknown | L12: Yes | M12: Yes | N12: Unknown | O12: Yes | P12: Yes | Q12: Yes | R12: Yes | S12: Unknown | T12: Yes | U12: Yes | V12: No | W12: Unknown | X12: Yes | Y12: Yes | Z12: Unknown | AA12: Unknown | AC12: Not captured | AD12: 4G LTE + BT 5.0 | AE12: B1/B3/B7/B8/B20/B28A | AI12: Not stated on manufacturer page | AK12: Not captured | AL12: 1.78" 368x448 touchscreen | AM12: Not captured | AN12: Magnetic | AO12: Not captured | AP12: Not captured | AQ12: Continuous HR & SpO2
A13: M08 | B13: Wonlex | C13: MF91Pro | D13: Band | E13: BLE | F13: Yes | G13: Yes | H13: Yes | I13: Unknown | J13: Unknown | K13: Unknown | L13: Unknown | M13: Unknown | N13: Unknown | O13: Unknown | P13: Unknown | Q13: Unknown | R13: No | S13: No | T13: No | U13: No | V13: Yes | W13: Unknown | X13: Yes | Y13: Yes | Z13: Unknown | AA13: Unknown | AC13: Nordic nRF54L15 + TI4950 AFE | AD13: BLE 6.0 | AE13: — | AF13: 265 | AI13: Only '10 days standby' stated | AK13: Not captured | AL13: Screenless | AM13: Not captured | AN13: Not captured | AO13: — | AP13: Not captured | AQ13: ECG 500 Hz
A14: M09 | B14: Wonlex | C14: HW20Pro | D14: Watch | E14: 4G | F14: Unknown | G14: Unknown | H14: Unknown | I14: Unknown | J14: Yes | K14: Unknown | L14: Unknown | M14: Unknown | N14: Unknown | O14: Yes | P14: Yes | Q14: Yes | R14: Yes | S14: Unknown | T14: Yes | U14: Yes | V14: No | W14: Unknown | X14: Yes | Y14: Yes | Z14: Unknown | AA14: Yes | AC14: Not captured; BLE co-processor | AD14: 4G + BLE | AE14: Per HW20 family (unconfirmed) | AF14: 540 | AG14: 4 | AH14: C | AI14: Up to 4 days (marketplace) | AK14: Not captured | AL14: 1.96" AMOLED (marketplace) | AM14: IP67 (marketplace) | AN14: Not captured | AO14: Not captured | AP14: Not captured | AQ14: Not documented
A15: M10 | B15: Wonlex | C15: HW19 | D15: Watch | E15: 4G | F15: Yes | G15: Yes | H15: Unknown | I15: Yes | J15: Conditional | K15: Unknown | L15: Yes | M15: Unknown | N15: Unknown | O15: Yes | P15: Yes | Q15: Yes | R15: Yes | S15: Unknown | T15: Yes | U15: Yes | V15: No | W15: Unknown | X15: Yes | Y15: Yes | Z15: Unknown | AA15: Unknown | AC15: Not captured | AD15: 4G LTE + BT 5.3 | AE15: Not captured | AF15: 800 | AI15: Runtime not stated | AK15: Not captured | AL15: 1.96" AMOLED | AM15: Not captured | AN15: Magnetic | AO15: Nano SIM | AP15: KSCtracker platform | AQ15: Not documented
A16: M11 | B16: Wonlex | C16: CT20S | D16: Watch | E16: 4G | F16: Yes | G16: Unknown | H16: Unknown | I16: Unknown | J16: Unknown | K16: Yes | L16: Yes | M16: Unknown | N16: Unknown | O16: Yes | P16: Yes | Q16: Unknown | R16: Yes | S16: Yes | T16: Yes | U16: Yes | V16: No | W16: Unknown | X16: Unknown | Y16: Yes | Z16: Unknown | AA16: Yes | AC16: Not captured | AD16: 4G | AE16: Not captured | AF16: 680 | AH16: X | AI16: Product page 680 mAh; blog 650 mAh / 4 days standby | AK16: Not captured | AL16: 1.85" IPS 240x280 | AM16: IP67 | AN16: Magnetic | AO16: Not captured | AP16: Not captured | AQ16: Alerts outside preset ranges
A17: M12 | B17: Wonlex | C17: CT30 (band) | D17: Band | E17: 4G | F17: Yes | G17: Unknown | H17: Unknown | I17: Unknown | J17: Conditional | K17: Unknown | L17: Unknown | M17: Yes | N17: Unknown | O17: Unknown | P17: Yes | Q17: Yes | R17: Yes | S17: Unknown | T17: Yes | U17: Yes | V17: Unknown | W17: Unknown | X17: Unknown | Y17: Yes | Z17: Unknown | AA17: Unknown | AC17: ASR3603S | AD17: 4G Cat1 | AE17: Not captured | AF17: 700 | AI17: Runtime not stated | AK17: Not captured | AL17: Not captured | AM17: Not captured | AN17: Magnetic USB | AO17: Nano SIM | AP17: Not captured | AQ17: Not documented
A18: M13 | B18: Wonlex | C18: CT31 | D18: Band | E18: 4G | F18: Yes | G18: Unknown | H18: Unknown | I18: Yes | J18: Conditional | K18: Yes | L18: Unknown | M18: Unknown | N18: Unknown | O18: Unknown | P18: Yes | Q18: Yes | R18: Yes | S18: Unknown | T18: Yes | U18: Yes | V18: Yes | W18: Unknown | X18: Unknown | Y18: Yes | Z18: Unknown | AA18: Yes | AC18: ASR3603C (RTOS) | AD18: 4G FDD-LTE | AE18: Not captured | AF18: 950 | AI18: 'Multi-day' only | AJ18: 40 | AK18: 40.5 x 50 x 14.6 mm | AL18: Screenless, 2 large buttons | AM18: IP67 | AN18: Magnetic | AO18: Micro SIM | AP18: Positioned for telecare integrators | AQ18: One-touch (on-demand) health check
A21: Evidence grade per hardware status cell (A verified · B strong · C indicative · D unverified · X contradicted · blank = no claim). Feeds the evidence-quality confidence indicator.
A22: ID | B22: Manufacturer | C22: Model | F22: F01 | G22: F02 | H22: F03 | I22: F04 | J22: F05 | K22: F06 | L22: F07 | M22: F08 | N22: F09 | O22: F10 | P22: F11 | Q22: F12 | R22: F13 | S22: F14 | T22: F15 | U22: F16 | V22: F17 | W22: F18 | X22: F19 | Y22: F20 | Z22: F21 | AA22: F22
A23: M01 | C23: VB10 | F23: B | G23: B | H23: B | I23: B | K23: B | L23: B | M23: B | N23: B | R23: C | S23: C | T23: B | U23: B | V23: B | X23: B | Y23: C | AA23: B
A24: M02 | C24: CT29 | O24: C | T24: C | U24: C
A25: M03 | C25: CT34 | O25: B | P25: B | Q25: B | R25: B | T25: B | U25: B | V25: B | Y25: C | AA25: B
A26: M04 | C26: MF90 | F26: B | G26: B | H26: B | I26: B | J26: B | K26: B | L26: B | M26: C | N26: B | R26: C | S26: C | T26: B | U26: B | V26: B | W26: B | X26: B | Y26: C | AA26: B
A27: M05 | C27: MF91 | F27: B | G27: B | H27: X | I27: B | J27: B | K27: B | L27: B | M27: B | N27: B | R27: C | S27: C | T27: B | U27: B | V27: B | W27: B | X27: B | Y27: C | AA27: B
A28: M06 | C28: MF40 | F28: B | H28: B | I28: B | J28: B | L28: C | M28: C | N28: B | R28: C | S28: C | T28: B | U28: B | V28: B | Y28: C | AA28: B
A29: M07 | C29: HW20 | F29: B | I29: B | J29: B | L29: B | M29: C | O29: C | P29: B | Q29: B | R29: B | T29: B | U29: B | V29: B | X29: B | Y29: C
A30: M08 | C30: MF91Pro | F30: C | G30: B | H30: B | R30: C | S30: C | T30: B | U30: B | V30: B | X30: B | Y30: C
A31: M09 | C31: HW20Pro | J31: B | O31: B | P31: B | Q31: B | R31: C | T31: B | U31: B | V31: C | X31: C | Y31: C | AA31: C
A32: M10 | C32: HW19 | F32: B | G32: B | I32: B | J32: B | L32: B | O32: B | P32: B | Q32: B | R32: B | T32: B | U32: B | V32: B | X32: B | Y32: C
A33: M11 | C33: CT20S | F33: B | K33: B | L33: C | O33: B | P33: C | R33: B | S33: C | T33: B | U33: B | V33: B | Y33: C | AA33: B
A34: M12 | C34: CT30 (band) | F34: B | J34: B | M34: B | P34: B | Q34: B | R34: B | T34: B | U34: B | Y34: C
A35: M13 | C35: CT31 | F35: B | I35: B | J35: B | K35: B | P35: B | Q35: B | R35: B | T35: B | U35: B | V35: B | Y35: C | AA35: B
A38: Technical-depth criteria (Functional dimension B) — HOW WELL capabilities are implemented, distinct from market fit (WHETHER they exist). Weights live on 10.
A39: ID | B39: Manufacturer | C39: Model | F39: T1 Automatic / continuous physiological sampling | G39: T2 ECG waveform at >=250 Hz documented | H39: T3 Fall-detection method (Y = multi-sensor documented; C = method unspecified) | I39: T4 Multi-mode positioning (GNSS + Wi-Fi/LBS) | J39: T5 Offline storage / store-and-forward | K39: T6 Blood-pressure method (Y = oscillometric cuff; C = estimate) | L39: T7 LTE bands cover PT/ES operators (B3, B7, B20) | N39: Grade T1 | O39: T2 | P39: T3 | Q39: T4 | R39: T5 | S39: T6 | T39: T7
E40: Weight → | F40: ='10 Scoring & Weights'!$D$32 -> 25 | G40: ='10 Scoring & Weights'!$D$33 -> 10 | H40: ='10 Scoring & Weights'!$D$34 -> 25 | I40: ='10 Scoring & Weights'!$D$35 -> 15 | J40: ='10 Scoring & Weights'!$D$36 -> 5 | K40: ='10 Scoring & Weights'!$D$37 -> 10 | L40: ='10 Scoring & Weights'!$D$38 -> 10
A41: M01 | C41: VB10 | F41: Yes | G41: Yes | H41: Unknown | I41: No | J41: Unknown | K41: Unknown | L41: N/A | N41: B | O41: B | Q41: C
A42: M02 | C42: CT29 | F42: Unknown | G42: Unknown | H42: Conditional | I42: Unknown | J42: Unknown | K42: Unknown | L42: Unknown | P42: C
A43: M03 | C43: CT34 | F43: Unknown | G43: Unknown | H43: Conditional | I43: Yes | J43: Unknown | K43: Unknown | L43: Yes | P43: B | Q43: B | T43: B
A44: M04 | C44: MF90 | F44: Yes | G44: Yes | H44: Unknown | I44: No | J44: Unknown | K44: Conditional | L44: N/A | N44: B | O44: B | Q44: C | S44: B
A45: M05 | C45: MF91 | F45: Yes | G45: Unknown | H45: Unknown | I45: No | J45: Unknown | K45: Conditional | L45: N/A | N45: B | O45: X | Q45: C | S45: B
A46: M06 | C46: MF40 | F46: Yes | G46: Yes | H46: Unknown | I46: No | J46: Unknown | K46: Yes | L46: N/A | N46: B | O46: C | Q46: C | S46: B
A47: M07 | C47: HW20 | F47: Yes | G47: Unknown | H47: Conditional | I47: Yes | J47: Unknown | K47: Yes | L47: Yes | N47: B | P47: C | Q47: B | S47: B | T47: B
A48: M08 | C48: MF91Pro | F48: Unknown | G48: Yes | H48: Unknown | I48: No | J48: Unknown | K48: Unknown | L48: N/A | O48: B | Q48: C
A49: M09 | C49: HW20Pro | F49: Unknown | G49: Unknown | H49: Conditional | I49: Conditional | J49: Unknown | K49: Yes | L49: Conditional | P49: B | Q49: C | S49: B | T49: C
A50: M10 | C50: HW19 | F50: Unknown | G50: Unknown | H50: Yes | I50: Yes | J50: Unknown | K50: Conditional | L50: Unknown | P50: B | Q50: B | S50: B
A51: M11 | C51: CT20S | F51: Yes | G51: Unknown | H51: Conditional | I51: Conditional | J51: Unknown | K51: Unknown | L51: Unknown | N51: B | P51: B | Q51: B
A52: M12 | C52: CT30 (band) | F52: Unknown | G52: Unknown | H52: Unknown | I52: Yes | J52: Unknown | K52: Conditional | L52: Unknown | Q52: B | S52: B
A53: M13 | C53: CT31 | F53: Conditional | G53: Unknown | H53: Unknown | I53: Yes | J53: Unknown | K53: Conditional | L53: Unknown | N53: B | Q53: B | S53: B
A56: Feature evidence register (long format, filterable). Status and grade are live links to the grids above; source and note are the research record.
A58: Model ID | B58: Model | C58: Feature code | D58: Feature | E58: Hardware status | F58: Evidence grade | G58: Source ID(s) | H58: Note
A59: M01 | B59: VB10 | C59: F01 | D59: Heart rate | E59: =F6 -> Yes | F59: =IF(F23="","",F23) -> B | G59: S01 | H59: 4-channel optical PPG (50 Hz)
A60: M01 | B60: VB10 | C60: F02 | D60: Heart-rate variability (HRV) | E60: =G6 -> Yes | F60: =IF(G23="","",G23) -> B | G60: S01 | H60: HRV for fatigue/recovery/stress
A61: M01 | B61: VB10 | C61: F03 | D61: ECG | E61: =H6 -> Yes | F61: =IF(H23="","",H23) -> B | G61: S01 | H61: ECG 500 Hz, TI4950 AFE
A62: M01 | B62: VB10 | C62: F04 | D62: SpO2 | E62: =I6 -> Yes | F62: =IF(I23="","",I23) -> B | G62: S01 | H62: Via 4-channel optical
A63: M01 | B63: VB10 | C63: F05 | D63: Blood pressure | E63: =J6 -> Unknown | F63: =IF(J23="","",J23) | G63: — | H63: Not documented in captured sources
A64: M01 | B64: VB10 | C64: F06 | D64: Body / skin temperature | E64: =K6 -> Yes | F64: =IF(K23="","",K23) -> B | G64: S01 | H64: Skin temperature
A65: M01 | B65: VB10 | C65: F07 | D65: Sleep monitoring | E65: =L6 -> Yes | F65: =IF(L23="","",L23) -> B | G65: S01 | H65: Deep / light / REM
A66: M01 | B66: VB10 | C66: F08 | D66: Steps & activity | E66: =M6 -> Yes | F66: =IF(M23="","",M23) -> B | G66: S01 | H66: 6-axis motion: steps, calories, distance; 120+ sports modes
A67: M01 | B67: VB10 | C67: F09 | D67: Stress indicator | E67: =N6 -> Yes | F67: =IF(N23="","",N23) -> B | G67: S01 | H67: Optical + HRV
A68: M01 | B68: VB10 | C68: F10 | D68: Automatic fall detection | E68: =O6 -> Unknown | F68: =IF(O23="","",O23) | G68: — | H68: Not documented in captured sources
A69: M01 | B69: VB10 | C69: F11 | D69: SOS button | E69: =P6 -> Unknown | F69: =IF(P23="","",P23) | G69: — | H69: Not documented in captured sources
A70: M01 | B70: VB10 | C70: F12 | D70: Two-way voice calling | E70: =Q6 -> Unknown | F70: =IF(Q23="","",Q23) | G70: — | H70: Not documented in captured sources
A71: M01 | B71: VB10 | C71: F13 | D71: GNSS positioning | E71: =R6 -> No | F71: =IF(R23="","",R23) -> C | G71: S01 | H71: No GNSS receiver in documented spec (BLE-only) — inferred
A72: M01 | B72: VB10 | C72: F14 | D72: Geofencing | E72: =S6 -> No | F72: =IF(S23="","",S23) -> C | G72: S01 | H72: No on-device positioning — inferred
A73: M01 | B73: VB10 | C73: F15 | D73: Standalone 4G/LTE | E73: =T6 -> No | F73: =IF(T23="","",T23) -> B | G73: S01 | H73: BLE 6.0 only
A74: M01 | B74: VB10 | C74: F16 | D74: Works without a smartphone | E74: =U6 -> No | F74: =IF(U23="","",U23) -> B | G74: S01 | H74: Needs companion app (Android 8+/iOS 13+)
A75: M01 | B75: VB10 | C75: F17 | D75: Screenless / minimal interface | E75: =V6 -> Yes | F75: =IF(V23="","",V23) -> B | G75: S01 | H75: Screenless
A76: M01 | B76: VB10 | C76: F18 | D76: Medication reminder | E76: =W6 -> Unknown | F76: =IF(W23="","",W23) | G76: — | H76: Not documented in captured sources
A77: M01 | B77: VB10 | C77: F19 | D77: Non-invasive glucose / lipid estimation | E77: =X6 -> Yes | F77: =IF(X23="","",X23) -> B | G77: S01 | H77: Glucose / lipid / uric-acid estimation claimed
A78: M01 | B78: VB10 | C78: F20 | D78: No camera | E78: =Y6 -> Yes | F78: =IF(Y23="","",Y23) -> C | G78: S01 | H78: No camera in documented spec
A79: M01 | B79: VB10 | C79: F21 | D79: Offline on-device data storage | E79: =Z6 -> Unknown | F79: =IF(Z23="","",Z23) | G79: — | H79: Not documented in captured sources
A80: M01 | B80: VB10 | C80: F22 | D80: Water resistance IP67 or better | E80: =AA6 -> Yes | F80: =IF(AA23="","",AA23) -> B | G80: S01 | H80: IP68
A81: M02 | B81: CT29 | C81: F01 | D81: Heart rate | E81: =F7 -> Unknown | F81: =IF(F24="","",F24) | G81: — | H81: Not documented in captured sources
A82: M02 | B82: CT29 | C82: F02 | D82: Heart-rate variability (HRV) | E82: =G7 -> Unknown | F82: =IF(G24="","",G24) | G82: — | H82: Not documented in captured sources
A83: M02 | B83: CT29 | C83: F03 | D83: ECG | E83: =H7 -> Unknown | F83: =IF(H24="","",H24) | G83: — | H83: Not documented in captured sources
A84: M02 | B84: CT29 | C84: F04 | D84: SpO2 | E84: =I7 -> Unknown | F84: =IF(I24="","",I24) | G84: — | H84: Not documented in captured sources
A85: M02 | B85: CT29 | C85: F05 | D85: Blood pressure | E85: =J7 -> Unknown | F85: =IF(J24="","",J24) | G85: — | H85: Not documented in captured sources
A86: M02 | B86: CT29 | C86: F06 | D86: Body / skin temperature | E86: =K7 -> Unknown | F86: =IF(K24="","",K24) | G86: — | H86: Not documented in captured sources
A87: M02 | B87: CT29 | C87: F07 | D87: Sleep monitoring | E87: =L7 -> Unknown | F87: =IF(L24="","",L24) | G87: — | H87: Not documented in captured sources
A88: M02 | B88: CT29 | C88: F08 | D88: Steps & activity | E88: =M7 -> Unknown | F88: =IF(M24="","",M24) | G88: — | H88: Not documented in captured sources
A89: M02 | B89: CT29 | C89: F09 | D89: Stress indicator | E89: =N7 -> Unknown | F89: =IF(N24="","",N24) | G89: — | H89: Not documented in captured sources
A90: M02 | B90: CT29 | C90: F10 | D90: Automatic fall detection | E90: =O7 -> Yes | F90: =IF(O24="","",O24) -> C | G90: S04 | H90: Stated in product name only
A91: M02 | B91: CT29 | C91: F11 | D91: SOS button | E91: =P7 -> Unknown | F91: =IF(P24="","",P24) | G91: — | H91: Not documented in captured sources
A92: M02 | B92: CT29 | C92: F12 | D92: Two-way voice calling | E92: =Q7 -> Unknown | F92: =IF(Q24="","",Q24) | G92: — | H92: Not documented in captured sources
A93: M02 | B93: CT29 | C93: F13 | D93: GNSS positioning | E93: =R7 -> Unknown | F93: =IF(R24="","",R24) | G93: — | H93: Not documented in captured sources
A94: M02 | B94: CT29 | C94: F14 | D94: Geofencing | E94: =S7 -> Unknown | F94: =IF(S24="","",S24) | G94: — | H94: Not documented in captured sources
A95: M02 | B95: CT29 | C95: F15 | D95: Standalone 4G/LTE | E95: =T7 -> Yes | F95: =IF(T24="","",T24) -> C | G95: S04 | H95: Stated in product name only
A96: M02 | B96: CT29 | C96: F16 | D96: Works without a smartphone | E96: =U7 -> Conditional | F96: =IF(U24="","",U24) -> C | G96: S04 | H96: Implied by 4G; unverified
A97: M02 | B97: CT29 | C97: F17 | D97: Screenless / minimal interface | E97: =V7 -> Unknown | F97: =IF(V24="","",V24) | G97: — | H97: Not documented in captured sources
A98: M02 | B98: CT29 | C98: F18 | D98: Medication reminder | E98: =W7 -> Unknown | F98: =IF(W24="","",W24) | G98: — | H98: Not documented in captured sources
A99: M02 | B99: CT29 | C99: F19 | D99: Non-invasive glucose / lipid estimation | E99: =X7 -> Unknown | F99: =IF(X24="","",X24) | G99: — | H99: Not documented in captured sources
A100: M02 | B100: CT29 | C100: F20 | D100: No camera | E100: =Y7 -> Unknown | F100: =IF(Y24="","",Y24) | G100: — | H100: Not documented in captured sources
A101: M02 | B101: CT29 | C101: F21 | D101: Offline on-device data storage | E101: =Z7 -> Unknown | F101: =IF(Z24="","",Z24) | G101: — | H101: Not documented in captured sources
A102: M02 | B102: CT29 | C102: F22 | D102: Water resistance IP67 or better | E102: =AA7 -> Unknown | F102: =IF(AA24="","",AA24) | G102: — | H102: Not documented in captured sources
A103: M03 | B103: CT34 | C103: F01 | D103: Heart rate | E103: =F8 -> Unknown | F103: =IF(F25="","",F25) | G103: — | H103: Not documented in captured sources
A104: M03 | B104: CT34 | C104: F02 | D104: Heart-rate variability (HRV) | E104: =G8 -> Unknown | F104: =IF(G25="","",G25) | G104: — | H104: Not documented in captured sources
A105: M03 | B105: CT34 | C105: F03 | D105: ECG | E105: =H8 -> Unknown | F105: =IF(H25="","",H25) | G105: — | H105: Not documented in captured sources
A106: M03 | B106: CT34 | C106: F04 | D106: SpO2 | E106: =I8 -> Unknown | F106: =IF(I25="","",I25) | G106: — | H106: Not documented in captured sources
A107: M03 | B107: CT34 | C107: F05 | D107: Blood pressure | E107: =J8 -> Unknown | F107: =IF(J25="","",J25) | G107: — | H107: Not documented in captured sources
...

Sheet 04 API & Integration
A1: API & INTEGRATION — CAN REVII ACTUALLY GET THE DATA?
A2: Hardware capability is not integration capability. Only 'Verified feasible' can pass the integration gate; nothing is verified until a supplier confirms in writing.
A4: 1. Integration overview (Integration status is an editable input — it drives mandatory gate G1)
A5: ID | B5: Model | C5: Connectivity | D5: API / SDK type | E5: Documentation | F5: Synchronisation | G5: Smartphone dependence | H5: Backend requirements | I5: API restrictions | J5: Licensing | K5: Integration status | L5: Required verification actions
A6: M01 | B6: VB10 | C6: BLE | D6: Phone-side BLE SDK (Veepoo HBandSDK, Android AAR + iOS framework) | E6: Public GitHub repo; VB10 support list not published | F6: Phone-mediated; real-time when in range; periodic history pull (to confirm) | G6: High — needs senior's phone (63-64% of seniors use one) or a home BLE gateway | H6: Revii app running in background on Android/iOS; or gateway | I6: SDK for authorised cooperative customers; device list unknown | J6: Unknown — SDK licence required | K6: Conditional | L6: Obtain written confirmation VB10 is HBandSDK-supported; licence & fees; iOS SDK; field list incl. raw ECG/HRV; background-sync limits
A7: M02 | B7: CT29 | C7: 4G | D7: Unknown — presumably Wonlex 4G TCP protocol | E7: None found | F7: Unknown | G7: None if 4G as named | H7: Unknown | I7: Unknown | J7: Unknown | K7: Not verified | L7: Obtain CT29 datasheet and protocol document; confirm it is not the S10 kids watch
A8: M03 | B8: CT34 | C8: 4G | D8: Device-to-server TCP protocol (Wonlex 4G family); server address configurable; optional KSCtracker cloud | E8: Protocol on request; third-party decoders (flespi) for the protocol family | F8: Event push over 4G (TCP); positioning on schedule | G8: None — standalone 4G | H8: TCP listener/decoder on Revii backend (or flespi), SIM provisioning | I8: Some Wonlex firmware encrypted; one report of paid decryption key | J8: Unknown | K8: Conditional | L8: Request CT34 protocol spec (event codes for fall, SOS, battery, wear), encryption status, server re-pointing method, licence fees
A9: M04 | B9: MF90 | C9: BLE | D9: BLE SDK on request (H Band line) | E9: Not model-specific | F9: Phone-mediated | G9: High | H9: Revii app / gateway | I9: Unknown | J9: Unknown | K9: Not verified | L9: Confirm MF90 SDK support and field list
A10: M05 | B10: MF91 | C10: BLE | D10: BLE SDK on request (H Band line) | E10: Not model-specific | F10: Phone-mediated | G10: High | H10: Revii app / gateway | I10: 'Offline sale only — not for USA' | J10: Unknown | K10: Not verified | L10: Confirm MF91 SDK support; resolve ECG conflict
A11: M06 | B11: MF40 | C11: BLE | D11: BLE SDK on request (H Band line) | E11: Not model-specific | F11: Phone-mediated | G11: High | H11: Revii app / gateway | I11: Unknown | J11: Unknown | K11: Not verified | L11: Confirm MF40 SDK support incl. air-pump BP readings
A12: M07 | B12: HW20 | C12: 4G | D12: Wonlex 4G TCP protocol (company-level) | E12: Company-level only | F12: Event push over 4G | G12: None | H12: TCP decoder | I12: Unknown | J12: Unknown | K12: Not verified | L12: Confirm HW20 protocol, BP data fields
A13: M08 | B13: MF91Pro | C13: BLE | D13: BLE SDK (platform identical to VB10; no SDK pointer captured) | E13: Not model-specific | F13: Phone-mediated | G13: High | H13: Revii app / gateway | I13: Unknown | J13: Unknown | K13: Not verified | L13: Confirm MF91Pro vs VB10 relationship and SDK support
A14: M09 | B14: HW20Pro | C14: 4G | D14: Wonlex 4G TCP protocol (company-level) | E14: Company-level only | F14: Event push over 4G | G14: None | H14: TCP decoder | I14: Unknown | J14: Unknown | K14: Not verified | L14: Confirm HW20Pro protocol, fall/BP events
A15: M10 | B15: HW19 | C15: 4G | D15: KSCtracker platform (hosted on AWS) or device TCP to own server | E15: Platform API not public; protocol on request | F15: Platform push / device TCP | G15: None — standalone 4G | H15: Own TCP server or KSCtracker API | I15: Encryption risk; terms unknown | J15: Unknown — platform fee unknown | K15: Conditional | L15: Request KSCtracker API reference, own-server option, AWS region, DPA, per-device fee
A16: M11 | B16: CT20S | C16: 4G | D16: Wonlex 4G TCP protocol (company-level) | E16: Company-level only | F16: Event push over 4G | G16: None | H16: TCP decoder | I16: Unknown | J16: Unknown | K16: Not verified | L16: Confirm CT20S protocol and fall event
... A18: M13 | B18: CT31 | C18: 4G | D18: Not documented — page positions CT31 for telecare & healthcare integrators | E18: Not found | F18: Unknown | G18: None — standalone 4G | H18: Unknown | I18: Unknown | J18: Unknown | K18: Not verified | L18: Strong lead: request CT31 integration interface, health-check data fields, fall-detection status
A20: 2. Integration criteria (dimension C). Status per model — hover for grade and source. Weights are set on 10.
A22: ID | B22: Model | C22: Conn. | D22: I1 Model-specific integration mechanism documented | E22: I2 Interface documentation obtainable (public or on request) | F22: I3 Safety events (fall / SOS) exposed via integration | G22: I4 Physiological data exposed via integration | H22: I5 Raw data available (not only processed values) | I22: I6 Data path independent of the senior's smartphone | J22: I7 Commercial / licensing terms for Revii's use clear | K22: I8 Revii can host the data (no mandatory vendor cloud) | L22: I9 Near-real-time event delivery | M22: Integration score (0-100)
C23: Weight → | D23: ='10 Scoring & Weights'!$D$43 -> 20 | E23: ='10 Scoring & Weights'!$D$44 -> 10 | F23: ='10 Scoring & Weights'!$D$45 -> 20 | G23: ='10 Scoring & Weights'!$D$46 -> 15 | H23: ='10 Scoring & Weights'!$D$47 -> 5 | I23: ='10 Scoring & Weights'!$D$48 -> 10 | J23: ='10 Scoring & Weights'!$D$49 -> 10 | K23: ='10 Scoring & Weights'!$D$50 -> 5 | L23: ='10 Scoring & Weights'!$D$51 -> 5
A24: M01 | B24: VB10 | C24: BLE | D24: Conditional | E24: Conditional | F24: Unknown | G24: Conditional | H24: Conditional | I24: No | J24: Conditional | K24: Conditional | L24: Conditional | M24: ='10 Scoring & Weights'!F87 -> 40
A25: M02 | B25: CT29 | C25: 4G | D25: Unknown | E25: Unknown | F25: Unknown | G25: Unknown | H25: Unknown | I25: Conditional | J25: Unknown | K25: Unknown | L25: Unknown | M25: ='10 Scoring & Weights'!F88 -> 27.5
A26: M03 | B26: CT34 | C26: 4G | D26: Conditional | E26: Conditional | F26: Conditional | G26: Unknown | H26: Unknown | I26: Yes | J26: Conditional | K26: Conditional | L26: Conditional | M26: ='10 Scoring & Weights'!F89 -> 50
A27: M04 | B27: MF90 | C27: BLE | D27: Unknown | E27: Unknown | F27: Unknown | G27: Unknown | H27: Unknown | I27: No | J27: Unknown | K27: Unknown | L27: Unknown | M27: ='10 Scoring & Weights'!F90 -> 22.5
A28: M05 | B28: MF91 | C28: BLE | D28: Unknown | E28: Unknown | F28: Unknown | G28: Unknown | H28: Unknown | I28: No | J28: Unknown | K28: Unknown | L28: Unknown | M28: ='10 Scoring & Weights'!F91 -> 22.5
A29: M06 | B29: MF40 | C29: BLE | D29: Unknown | E29: Unknown | F29: Unknown | G29: Unknown | H29: Unknown | I29: No | J29: Unknown | K29: Unknown | L29: Unknown | M29: ='10 Scoring & Weights'!F92 -> 22.5
A30: M07 | B30: HW20 | C30: 4G | D30: Unknown | E30: Unknown | F30: Unknown | G30: Unknown | H30: Unknown | I30: Yes | J30: Unknown | K30: Unknown | L30: Unknown | M30: ='10 Scoring & Weights'!F93 -> 32.5
A31: M08 | B31: MF91Pro | C31: BLE | D31: Unknown | E31: Unknown | F31: Unknown | G31: Unknown | H31: Unknown | I31: No | J31: Unknown | K31: Unknown | L31: Unknown | M31: ='10 Scoring & Weights'!F94 -> 22.5
A32: M09 | B32: HW20Pro | C32: 4G | D32: Unknown | E32: Unknown | F32: Unknown | G32: Unknown | H32: Unknown | I32: Yes | J32: Unknown | K32: Unknown | L32: Unknown | M32: ='10 Scoring & Weights'!F95 -> 32.5
A33: M10 | B33: HW19 | C33: 4G | D33: Conditional | E33: Conditional | F33: Conditional | G33: Conditional | H33: Unknown | I33: Yes | J33: Conditional | K33: Conditional | L33: Conditional | M33: ='10 Scoring & Weights'!F96 -> 53.75
A34: M11 | B34: CT20S | C34: 4G | D34: Unknown | E34: Unknown | F34: Unknown | G34: Unknown | H34: Unknown | I34: Yes | J34: Unknown | K34: Unknown | L34: Unknown | M34: ='10 Scoring & Weights'!F97 -> 32.5
A35: M12 | B35: CT30 (band) | C35: 4G | D35: Unknown | E35: Unknown | F35: Unknown | G35: Unknown | H35: Unknown | I35: Yes | J35: Unknown | K35: Unknown | L35: Unknown | M35: ='10 Scoring & Weights'!F98 -> 32.5
A36: M13 | B36: CT31 | C36: 4G | D36: Unknown | E36: Unknown | F36: Unknown | G36: Unknown | H36: Unknown | I36: Yes | J36: Unknown | K36: Unknown | L36: Unknown | M36: ='10 Scoring & Weights'!F99 -> 32.5
A38: 3. Revii-accessible data — can Revii obtain each measurement/event through a documented, authorised interface? (N/A = hardware does not offer it)
A40: ID | B40: Model | C40: Conn. | D40: Fall event | E40: SOS event | F40: Location | G40: Heart rate | H40: HRV | I40: ECG raw waveform | J40: SpO2 | K40: Blood pressure | L40: Sleep | M40: Steps / activity | N40: Temperature | O40: Device status (battery / wear / online) | P40: Accessible (Yes or Conditional)
A41: M01 | B41: VB10 | C41: BLE | D41: Unknown | E41: Unknown | F41: N/A | G41: Conditional | H41: Conditional | I41: Conditional | J41: Conditional | K41: Unknown | L41: Unknown | M41: Unknown | N41: Unknown | O41: Unknown | P41: =COUNTIF(D41:O41,"Yes")+COUNTIF(D41:O41,"Conditional") -> 4
A42: M02 | B42: CT29 | C42: 4G | D42: Unknown | E42: Unknown | F42: Unknown | G42: Unknown | H42: Unknown | I42: Unknown | J42: Unknown | K42: Unknown | L42: Unknown | M42: Unknown | N42: Unknown | O42: Unknown | P42: =COUNTIF(D42:O42,"Yes")+COUNTIF(D42:O42,"Conditional") -> 0
A43: M03 | B43: CT34 | C43: 4G | D43: Conditional | E43: Conditional | F43: Conditional | G43: Unknown | H43: Unknown | I43: Unknown | J43: Unknown | K43: Unknown | L43: Unknown | M43: Unknown | N43: Unknown | O43: Conditional | P43: =COUNTIF(D43:O43,"Yes")+COUNTIF(D43:O43,"Conditional") -> 4
A44: M04 | B44: MF90 | C44: BLE | D44: Unknown | E44: Unknown | F44: N/A | G44: Unknown | H44: Unknown | I44: Unknown | J44: Unknown | K44: Unknown | L44: Unknown | M44: Unknown | N44: Unknown | O44: Unknown | P44: =COUNTIF(D44:O44,"Yes")+COUNTIF(D44:O44,"Conditional") -> 0
A45: M05 | B45: MF91 | C45: BLE | D45: Unknown | E45: Unknown | F45: N/A | G45: Unknown | H45: Unknown | I45: Unknown | J45: Unknown | K45: Unknown | L45: Unknown | M45: Unknown | N45: Unknown | O45: Unknown | P45: =COUNTIF(D45:O45,"Yes")+COUNTIF(D45:O45,"Conditional") -> 0
A46: M06 | B46: MF40 | C46: BLE | D46: Unknown | E46: Unknown | F46: N/A | G46: Unknown | H46: Unknown | I46: Unknown | J46: Unknown | K46: Unknown | L46: Unknown | M46: Unknown | N46: Unknown | O46: Unknown | P46: =COUNTIF(D46:O46,"Yes")+COUNTIF(D46:O46,"Conditional") -> 0
A47: M07 | B47: HW20 | C47: 4G | D47: Unknown | E47: Unknown | F47: Unknown | G47: Unknown | H47: Unknown | I47: Unknown | J47: Unknown | K47: Unknown | L47: Unknown | M47: Unknown | N47: Unknown | O47: Unknown | P47: =COUNTIF(D47:O47,"Yes")+COUNTIF(D47:O47,"Conditional") -> 0
A48: M08 | B48: MF91Pro | C48: BLE | D48: Unknown | E48: Unknown | F48: N/A | G48: Unknown | H48: Unknown | I48: Unknown | J48: Unknown | K48: Unknown | L48: Unknown | M48: Unknown | N48: Unknown | O48: Unknown | P48: =COUNTIF(D48:O48,"Yes")+COUNTIF(D48:O48,"Conditional") -> 0
A49: M09 | B49: HW20Pro | C49: 4G | D49: Unknown | E49: Unknown | F49: Unknown | G49: Unknown | H49: Unknown | I49: Unknown | J49: Unknown | K49: Unknown | L49: Unknown | M49: Unknown | N49: Unknown | O49: Unknown | P49: =COUNTIF(D49:O49,"Yes")+COUNTIF(D49:O49,"Conditional") -> 0
A50: M10 | B50: HW19 | C50: 4G | D50: Conditional | E50: Conditional | F50: Conditional | G50: Conditional | H50: Conditional | I50: Unknown | J50: Conditional | K50: Unknown | L50: Conditional | M50: Unknown | N50: Unknown | O50: Conditional | P50: =COUNTIF(D50:O50,"Yes")+COUNTIF(D50:O50,"Conditional") -> 8
A51: M11 | B51: CT20S | C51: 4G | D51: Unknown | E51: Unknown | F51: Unknown | G51: Unknown | H51: Unknown | I51: Unknown | J51: Unknown | K51: Unknown | L51: Unknown | M51: Unknown | N51: Unknown | O51: Unknown | P51: =COUNTIF(D51:O51,"Yes")+COUNTIF(D51:O51,"Conditional") -> 0
A52: M12 | B52: CT30 (band) | C52: 4G | D52: Unknown | E52: Unknown | F52: Unknown | G52: Unknown | H52: Unknown | I52: Unknown | J52: Unknown | K52: Unknown | L52: Unknown | M52: Unknown | N52: Unknown | O52: Unknown | P52: =COUNTIF(D52:O52,"Yes")+COUNTIF(D52:O52,"Conditional") -> 0
A53: M13 | B53: CT31 | C53: 4G | D53: Unknown | E53: Unknown | F53: Unknown | G53: Unknown | H53: Unknown | I53: Unknown | J53: Unknown | K53: Unknown | L53: Unknown | M53: Unknown | N53: Unknown | O53: Unknown | P53: =COUNTIF(D53:O53,"Yes")+COUNTIF(D53:O53,"Conditional") -> 0
A55: 4. How data reaches Revii — mechanism notes
A56: Wonlex 4G family (CT29, CT34, CT31, CT30, CT20S, HW19, HW20, HW20Pro) | D56: Device opens a TCP connection over 4G to a configurable server and pushes positions, heartbeats and alarms. Wonlex offers the protocol to developers on request (S26) and its KSCtracker page allows integration with your own servers (S18). Third-party decoders exist for the protocol family (S23, S25). Risks: model-specific firmware behaviour, encryption on some devices and a reported paid decryption key (S24).
A57: Wonlex BLE line (VB10, MF91Pro, MF90, MF91, MF40) | D57: Data travels band → phone over BLE. The VB10 page links the HBandSDK (S01), which is Veepoo's SDK for authorised cooperative customers (S21, S22). Revii's app (or a home gateway) must stay paired and sync in the background. About 36% of seniors do not use a smartphone (S40), so a gateway is costed on 08.
A58: Why no model is 'Verified feasible' | D58: No supplier has confirmed in writing, for a specific model, the data fields, licence terms and encryption. A generic manufacturer API statement is not proof that a given model exposes a given metric.

Sheet 05 Market Research
A1: MARKET RESEARCH CONSOLIDATION
A2: All market-research inputs analysed together. Blue cells (need mapping, interview coding) are editable and flow into 06 Needs-Feature Map.
B4: 1. Research files analysed
B5: ID | C5: File | D5: Research type | E5: Respondent population | F5: Sample / participants | G5: Questions / themes | H5: Key findings | I5: Limitations | J5: Source
B6: R1 | C6: quantitative_reearch.pptx | D6: Quantitative | E6: Informal caregivers of 70+ (buyers) and seniors (users), PT/ES/EN, online Qualtrics | F6: 952 started; 615 qualified caregivers; 546 at value questions (497 caregivers, 49-50 seniors) | G6: Demand, concerns, technology acceptance, feature priorities, WTP, channels | H6: Fall detection, early decline and doctor sharing top features; ease of use and privacy top decision drivers; wearables 86%/70% accepted; cameras rejected by seniors | I6: Online, LinkedIn-heavy, higher-educated, urban, PT-dominant; senior sub-sample ~50; Spain ~76 directional | J6: S40
B7: R2 | C7: Revii_Research_Report.docx | D7: Quantitative (report on R1 survey) | E7: Same survey as R1 | F7: 938 initiated; 543 completed (494 caregivers, 49 seniors) | G7: Narrative report of the same survey | H7: Same direction as R1; several magnitudes differ (e.g., fall detection 73% vs 90.5%) | I7: Same respondents as R1 — NOT counted as independent evidence | J7: S41
B8: R3 | C8: Interview_Status_and__analysis.xlsx | D8: Qualitative | E8: Seniors (A), informal caregivers (B), professional caregivers (C), PT (some ES) | F8: 24 structured interview summaries: 5 A, 14 B, 5 C (business plan cites 27) | G8: Daily life, concerns, technology attitudes, privacy, WTP, professional workflow | H8: Core problem is uncertainty; falls when alone dominate; passive, simple, non-intrusive technology preferred; sedentary behaviour and medication rate highly | I8: Convenience sample from team networks; small n; no statistical inference; possible overlap with survey respondents | J8: S42
B9: Not market research: Revii_product_features.xlsx (historical device benchmark, input A) — used on 02/03. Respondent overlap between the survey (team networks via LinkedIn) and interviews (team personal networks) cannot be established: interview evidence is therefore used only as corroboration (30% weight) and never as a prevalence estimate.
B11: 2. Quantitative batteries used for need importance (survey R1 / S40; R2 reports the same respondents and is not counted again)
B12: B1 · Feature importance — Q37-44: % rating 4-5 (very/extremely important) · caregivers n=497 · seniors n≈50
B13: Item | C13: Caregivers % | D13: Seniors % | E13: Mapped need | F13: Blended index (0-1) | G13: Mapping note | H13: Index = (caregiver share × caregiver % + senior share × senior %) ÷ the highest blended value in the same battery. Blending before normalising avoids amplifying the small senior percentages (n≈50: one respondent ≈ 2 points), and normalising within each battery puts rating, concern and top-3 questions on a common 0-1 footing.
B14: Fall detection | C14: 0.905 | D14: 0.62 | E14: N1 | F14: =('06 Needs-Feature Map'!$C$6*C14+'06 Needs-Feature Map'!$C$7*D14)/SUMPRODUCT(MAX('06 Needs-Feature Map'!$C$6*$C$14:$C$21+'06 Needs-Feature Map'!$C$7*$D$14:$D$21)) -> 1
B15: Early decline detection | C15: 0.771 | D15: 0.48 | E15: N3 | F15: =('06 Needs-Feature Map'!$C$6*C15+'06 Needs-Feature Map'!$C$7*D15)/SUMPRODUCT(MAX('06 Needs-Feature Map'!$C$6*$C$14:$C$21+'06 Needs-Feature Map'!$C$7*$D$14:$D$21)) -> 0.8342892
B16: Doctor data sharing | C16: 0.73 | D16: 0.48 | E16: N6 | F16: =('06 Needs-Feature Map'!$C$6*C16+'06 Needs-Feature Map'!$C$7*D16)/SUMPRODUCT(MAX('06 Needs-Feature Map'!$C$6*$C$14:$C$21+'06 Needs-Feature Map'!$C$7*$D$14:$D$21)) -> 0.79926785
B17: Cognitive monitoring | C17: 0.694 | D17: 0.408 | E17: N3 | F17: =('06 Needs-Feature Map'!$C$6*C17+'06 Needs-Feature Map'!$C$7*D17)/SUMPRODUCT(MAX('06 Needs-Feature Map'!$C$6*$C$14:$C$21+'06 Needs-Feature Map'!$C$7*$D$14:$D$21)) -> 0.74215985
B18: Biometric monitoring | C18: 0.62 | D18: 0.26 | E18: N3 | F18: =('06 Needs-Feature Map'!$C$6*C18+'06 Needs-Feature Map'!$C$7*D18)/SUMPRODUCT(MAX('06 Needs-Feature Map'!$C$6*$C$14:$C$21+'06 Needs-Feature Map'!$C$7*$D$14:$D$21)) -> 0.6247712
B19: Daily check-in calls | C19: 0.612 | D19: 0.4 | E19: — | F19: =('06 Needs-Feature Map'!$C$6*C19+'06 Needs-Feature Map'!$C$7*D19)/SUMPRODUCT(MAX('06 Needs-Feature Map'!$C$6*$C$14:$C$21+'06 Needs-Feature Map'!$C$7*$D$14:$D$21)) -> 0.66918853 | G19: Service-level (Revii Voice Care), not a wearable capability
B20: Daily routine app | C20: 0.565 | D20: 0.26 | E20: — | F20: =('06 Needs-Feature Map'!$C$6*C20+'06 Needs-Feature Map'!$C$7*D20)/SUMPRODUCT(MAX('06 Needs-Feature Map'!$C$6*$C$14:$C$21+'06 Needs-Feature Map'!$C$7*$D$14:$D$21)) -> 0.57779134 | G20: App feature, not a device capability
B21: Home environment monitoring | C21: 0.29 | D21: 0.245 | E21: — | F21: =('06 Needs-Feature Map'!$C$6*C21+'06 Needs-Feature Map'!$C$7*D21)/SUMPRODUCT(MAX('06 Needs-Feature Map'!$C$6*$C$14:$C$21+'06 Needs-Feature Map'!$C$7*$D$14:$D$21)) -> 0.33740085 | G21: Ambient IoT, not wrist-worn
B24: B2 · Concerns — Q18-27: % rating 4-5 (high concern) · caregivers n=497 · seniors n≈56
B25: Item | C25: Caregivers % | D25: Seniors % | E25: Mapped need | F25: Blended index (0-1) | G25: Mapping note
B26: Falls / accidents | C26: 0.548 | D26: 0.071 | E26: N1 | F26: =('06 Needs-Feature Map'!$C$6*C26+'06 Needs-Feature Map'!$C$7*D26)/SUMPRODUCT(MAX('06 Needs-Feature Map'!$C$6*$C$26:$C$35+'06 Needs-Feature Map'!$C$7*$D$26:$D$35)) -> 1
B27: Difficulty calling for help | C27: 0.445 | D27: 0.089 | E27: N2 | F27: =('06 Needs-Feature Map'!$C$6*C27+'06 Needs-Feature Map'!$C$7*D27)/SUMPRODUCT(MAX('06 Needs-Feature Map'!$C$6*$C$26:$C$35+'06 Needs-Feature Map'!$C$7*$D$26:$D$35)) -> 0.83526797
B28: Undetected health problems | C28: 0.362 | D28: 0.071 | E28: N3 | F28: =('06 Needs-Feature Map'!$C$6*C28+'06 Needs-Feature Map'!$C$7*D28)/SUMPRODUCT(MAX('06 Needs-Feature Map'!$C$6*$C$26:$C$35+'06 Needs-Feature Map'!$C$7*$D$26:$D$35)) -> 0.67843912
B29: Cognitive decline | C29: 0.419 | D29: 0.071 | E29: N3 | F29: =('06 Needs-Feature Map'!$C$6*C29+'06 Needs-Feature Map'!$C$7*D29)/SUMPRODUCT(MAX('06 Needs-Feature Map'!$C$6*$C$26:$C$35+'06 Needs-Feature Map'!$C$7*$D$26:$D$35)) -> 0.77698197
B30: Physical decline | C30: 0.493 | D30: 0.071 | E30: N3 | F30: =('06 Needs-Feature Map'!$C$6*C30+'06 Needs-Feature Map'!$C$7*D30)/SUMPRODUCT(MAX('06 Needs-Feature Map'!$C$6*$C$26:$C$35+'06 Needs-Feature Map'!$C$7*$D$26:$D$35)) -> 0.90491479
B31: Medication errors | C31: 0.212 | D31: 0 | E31: N8 | F31: =('06 Needs-Feature Map'!$C$6*C31+'06 Needs-Feature Map'!$C$7*D31)/SUMPRODUCT(MAX('06 Needs-Feature Map'!$C$6*$C$26:$C$35+'06 Needs-Feature Map'!$C$7*$D$26:$D$35)) -> 0.36651025
B32: Forgotten appointments | C32: 0.12 | D32: 0 | E32: — | F32: =('06 Needs-Feature Map'!$C$6*C32+'06 Needs-Feature Map'!$C$7*D32)/SUMPRODUCT(MAX('06 Needs-Feature Map'!$C$6*$C$26:$C$35+'06 Needs-Feature Map'!$C$7*$D$26:$D$35)) -> 0.20745863 | G32: Not addressable by the wearable
B33: Safety at home | C33: 0.302 | D33: 0.036 | E33: — | F33: =('06 Needs-Feature Map'!$C$6*C33+'06 Needs-Feature Map'!$C$7*D33)/SUMPRODUCT(MAX('06 Needs-Feature Map'!$C$6*$C$26:$C$35+'06 Needs-Feature Map'!$C$7*$D$26:$D$35)) -> 0.54877748 | G33: Ambient/home hazards — IoT scope
B34: Inactivity | C34: 0.364 | D34: 0.125 | E34: N7 | F34: =('06 Needs-Feature Map'!$C$6*C34+'06 Needs-Feature Map'!$C$7*D34)/SUMPRODUCT(MAX('06 Needs-Feature Map'!$C$6*$C$26:$C$35+'06 Needs-Feature Map'!$C$7*$D$26:$D$35)) -> 0.72190664
B35: Poor diet | C35: 0.228 | D35: 0 | E35: — | F35: =('06 Needs-Feature Map'!$C$6*C35+'06 Needs-Feature Map'!$C$7*D35)/SUMPRODUCT(MAX('06 Needs-Feature Map'!$C$6*$C$26:$C$35+'06 Needs-Feature Map'!$C$7*$D$26:$D$35)) -> 0.3941714 | G35: Not addressable by the wearable
B38: B3 · Decision drivers — Q36: % selecting in top 3 · caregivers n=497 · seniors n≈50
B39: Item | C39: Caregivers % | D39: Seniors % | E39: Mapped need | F39: Blended index (0-1) | G39: Mapping note
B40: That is easy to use | C40: 0.694 | D40: 0.76 | E40: N4 | F40: =('06 Needs-Feature Map'!$C$6*C40+'06 Needs-Feature Map'!$C$7*D40)/SUMPRODUCT(MAX('06 Needs-Feature Map'!$C$6*$C$40:$C$44+'06 Needs-Feature Map'!$C$7*$D$40:$D$44)) -> 1
B41: That respects privacy | C41: 0.551 | D41: 0.42 | E41: N5 | F41: =('06 Needs-Feature Map'!$C$6*C41+'06 Needs-Feature Map'!$C$7*D41)/SUMPRODUCT(MAX('06 Needs-Feature Map'!$C$6*$C$40:$C$44+'06 Needs-Feature Map'!$C$7*$D$40:$D$44)) -> 0.71686747
B42: Peace of mind to the family | C42: 0.491 | D42: 0.22 | E42: — | F42: =('06 Needs-Feature Map'!$C$6*C42+'06 Needs-Feature Map'!$C$7*D42)/SUMPRODUCT(MAX('06 Needs-Feature Map'!$C$6*$C$40:$C$44+'06 Needs-Feature Map'!$C$7*$D$40:$D$44)) -> 0.5739703 | G42: Outcome of all needs — mapping it would double-count
B43: That it is not expensive | C43: 0.437 | D43: 0.3 | E43: — | F43: =('06 Needs-Feature Map'!$C$6*C43+'06 Needs-Feature Map'!$C$7*D43)/SUMPRODUCT(MAX('06 Needs-Feature Map'!$C$6*$C$40:$C$44+'06 Needs-Feature Map'!$C$7*$D$40:$D$44)) -> 0.55463715 | G43: Handled in the Commercial dimension, not market fit
B44: That gives me more security | C44: 0.404 | D44: 0.28 | E44: — | F44: =('06 Needs-Feature Map'!$C$6*C44+'06 Needs-Feature Map'!$C$7*D44)/SUMPRODUCT(MAX('06 Needs-Feature Map'!$C$6*$C$40:$C$44+'06 Needs-Feature Map'!$C$7*$D$40:$D$44)) -> 0.51386943 | G44: Ambiguous (personal safety vs data security) — not mapped
B47: 3. Other quantitative findings (context — not used as weights)
B48: Question | C48: Finding | D48: Result | E48: Implication for wearable selection | F48: Source
B49: Q45-50 | C49: Would accept a biometric bracelet | D49: 86.1% caregivers (for elder) / 70.0% seniors | E49: Form factor accepted — common to all candidates, so not differentiating | F49: S40
B50: Q45-50 | C50: Would accept cameras in common areas | D50: 50.5% / 36.0% | E50: Supports 'no camera' as a privacy attribute | F50: S40
B51: Q45-50 | C51: Would accept family access to health data | D51: 87.5% / 70.0% | E51: Data sharing to family is legitimate | F51: S40
B52: Q45-50 | C52: Would accept AI for monitoring | D52: 70.6% / 42.0% | E52: Seniors cautious — explain, do not hide | F52: S40
B53: Q30 | C53: Caregivers say elder minimises / does not share symptoms | D53: 53% yes today; 29% expect it soon; 17% no concern | E53: Passive, continuous sensing is valued (supports N2, Functional T1) | F53: S40
B54: Q31 | C54: Seniors using a smartphone (caregiver-reported) | D54: 63-64% | E54: ~36% would need a gateway for a BLE-only wearable (TCO assumption) | F54: S40;S41
B55: Q34 | C55: Top caregiver barrier | D55: 'I don't know solutions' 39.6%; 'family member would not accept' 20.1%; too expensive 10.1% | E55: Acceptance by the senior matters more than price | F55: S40
B56: Q34 | C56: Top senior barrier | D56: 'I don't see the need' 58%; difficult to use 12% | E56: Passive, low-effort device reduces resistance | F56: S40
B57: Q33 | C57: Interested / very interested | D57: Caregivers 58.6% (291/497); seniors 38% (19/50) | E57: Buyer = caregiver; user comfort is the design constraint | F57: S40
B58: Q53-54 | C58: Willingness to pay (median, EUR/month) | D58: Basic: caregiver 26 / senior 38. Full service: caregiver 50 / senior 67 | E58: Hardware cost must fit inside a ~EUR 25-50 monthly service | F58: S40
B60: 4. Qualitative thematic coding — 24 interviews (S42). 1 = need explicitly expressed by the interviewee (analyst coding of the summaries; evidence paraphrased with source-cell references)
B61: Interviewee names in the source file are replaced by IDs. A = seniors, B = informal caregivers, C = professional caregivers. Mention frequency describes these interviews only — it is not a market prevalence estimate.
B62: ID | C62: Group | D62: Profile | E62: N1 | F62: N2 | G62: N3 | H62: N4 | I62: N5 | J62: N6 | K62: N7 | L62: N8 | M62: N9 | N62: Evidence (paraphrased; sheet!cell in the interview file)
B63: A1 | C63: Senior | D63: 76, lives with spouse, urban, digital literacy 2/5 | E63: 1 | F63: 0 | G63: 0 | H63: 1 | I63: 1 | J63: 0 | K63: 1 | L63: 0 | M63: 0 | N63: N1: Concern about falls/incidents when alone (A.Seniors!C14) | N4: Must be simple, reliable, useful; excessive alerts annoying (C22,C23) | N5: Open to devices if useful and not intrusive (C17) | N7: Already uses a smartband/step counter (C15)
B64: A2 | C64: Senior | D64: 80, pacemaker, lives with spouse | E64: 1 | F64: 0 | G64: 0 | H64: 1 | I64: 0 | J64: 1 | K64: 0 | L64: 0 | M64: 0 | N64: N1: Falls or sudden health events when alone (D14) | N4: Simple, intuitive, minimal procedures (D22) | N6: Measures BP with own device; health info shared with doctors (D15,D16)
B65: A3 | C65: Senior | D65: 76, rural, lives with spouse | E65: 0 | F65: 1 | G65: 0 | H65: 0 | I65: 0 | J65: 1 | K65: 0 | L65: 0 | M65: 0 | N65: N2: Uses an SOS button in the home-alarm app (E15) | N6: Measures BP when dizzy; 'monitoring' = measuring BP (E15,E39)
B66: A4 | C66: Senior | D66: 71, lives alone | E66: 0 | F66: 0 | G66: 1 | H66: 1 | I66: 0 | J66: 0 | K66: 0 | L66: 0 | M66: 0 | N66: N3: Greatest fear is losing mental faculties (F10,F27) | N4: Frustrated by not knowing how to use everything (F21)
B67: A5 | C67: Senior | D67: 69, lives alone, knee problem | E67: 1 | F67: 0 | G67: 0 | H67: 1 | I67: 0 | J67: 1 | K67: 1 | L67: 0 | M67: 0 | N67: N1: Afraid of falling (G10) | N4: Fears making mistakes with technology (G21) | N6: BP reminders would be useful (G23) | N7: Exercise reminders would be useful (G23)
B68: B1 | C68: Informal caregiver | D68: Father 89, lives alone | E68: 1 | F68: 1 | G68: 0 | H68: 1 | I68: 0 | J68: 0 | K68: 0 | L68: 1 | M68: 0 | N68: N2: Cannot reach the phone to call for help after a fall (C5,C7) | N1: Fall without reaching the phone; help getting up (B!C5,C7) | N4: Father would need convincing or it be imposed (C19) | N8: Confusion taking medication (C7)
B69: B2 | C69: Informal caregiver | D69: Parents 79, live together | E69: 0 | F69: 0 | G69: 1 | H69: 0 | I69: 1 | J69: 0 | K69: 0 | L69: 0 | M69: 0 | N69: N3: Early signs of cognitive decline (D7) | N5: Deviation alerts, not surveillance; avoid intrusive control (D8)
B70: B3 | C70: Informal caregiver | D70: Mother 88, alone, abroad | E70: 1 | F70: 0 | G70: 0 | H70: 1 | I70: 1 | J70: 0 | K70: 1 | L70: 0 | M70: 0 | N70: N1: Falls at home; wants fall detection (E7,E16) | N4: Mother struggles with devices (E19) | N5: Strong concern about intrusiveness (E18) | N7: Inactivity alerts (E16)
B71: B4 | C71: Informal caregiver | D71: Father 92, alone | E71: 1 | F71: 0 | G71: 1 | H71: 0 | I71: 1 | J71: 0 | K71: 0 | L71: 0 | M71: 0 | N71: N1: 'Something can happen at any moment' (F7) | N3: Physical and mental health in general (F7) | N5: How health data is stored and who accesses it (F18)
B72: B5 | C72: Informal caregiver | D72: Mother 85, alone | E72: 1 | F72: 1 | G72: 1 | H72: 0 | I72: 0 | J72: 0 | K72: 0 | L72: 0 | M72: 0 | N72: N2: Immediate activation of emergency services (G22) | N1: 24/7 monitoring, real-time alerts, emergency activation (G22) | N3: Loss of autonomy through illness (G7)
B73: B6 | C73: Informal caregiver | D73: Mother 77, alone, village | E73: 1 | F73: 1 | G73: 1 | H73: 0 | I73: 0 | J73: 0 | K73: 0 | L73: 0 | M73: 0 | N73: N2: Must be able to react quickly (H22) | N1: Unexpected health episodes or falls; react quickly (H7,H22) | N3: Alerts on vital-sign changes (H18)
B74: B7 | C74: Informal caregiver | D74: Mother 73, alone, diabetic | E74: 1 | F74: 0 | G74: 1 | H74: 0 | I74: 1 | J74: 0 | K74: 1 | L74: 0 | M74: 0 | N74: N1: Something happening unnoticed (I7) | N3: Missing early signs; wearable tracking & reports (I7,I16) | N5: Mother must not feel watched; would resist cameras (I18,I19) | N7: Sedentary lifestyle (I7)
... B86: C5 | C86: Professional caregiver | D86: Nurse, public sector, 20 yrs | E86: 1 | F86: 0 | G86: 0 | H86: 1 | I86: 0 | J86: 1 | K86: 0 | L86: 1 | M86: 0 | N86: N1: Fall detection useful for high-risk cases (G13) | N4: Excessive monitoring causes anxiety (G13) | N6: Vital signs; alerts to the right professional (G13,G18) | N8: Duplicate-medication errors (G7)
D87: Interviews expressing the need | E87: =SUM(E63:E86) -> 18 | F87: =SUM(F63:F86) -> 8 | G87: =SUM(G63:G86) -> 11 | H87: =SUM(H63:H86) -> 10 | I87: =SUM(I63:I86) -> 12 | J87: =SUM(J63:J86) -> 9 | K87: =SUM(K63:K86) -> 9 | L87: =SUM(L63:L86) -> 8 | M87: =SUM(M63:M86) -> 1
D88: Share of 24 interviews | E88: =E87/COUNTA($B$63:$B$86) -> 0.75 | F88: =F87/COUNTA($B$63:$B$86) -> 0.33333333 | G88: =G87/COUNTA($B$63:$B$86) -> 0.45833333 | H88: =H87/COUNTA($B$63:$B$86) -> 0.41666667 | I88: =I87/COUNTA($B$63:$B$86) -> 0.5 | J88: =J87/COUNTA($B$63:$B$86) -> 0.375 | K88: =K87/COUNTA($B$63:$B$86) -> 0.375 | L88: =L87/COUNTA($B$63:$B$86) -> 0.33333333 | M88: =M87/COUNTA($B$63:$B$86) -> 0.041666667
D89: Seniors (A) | E89: =SUMIF($C$63:$C$86,"Senior",E63:E86) -> 3 | F89: =SUMIF($C$63:$C$86,"Senior",F63:F86) -> 1 | G89: =SUMIF($C$63:$C$86,"Senior",G63:G86) -> 1 | H89: =SUMIF($C$63:$C$86,"Senior",H63:H86) -> 4 | I89: =SUMIF($C$63:$C$86,"Senior",I63:I86) -> 1 | J89: =SUMIF($C$63:$C$86,"Senior",J63:J86) -> 3 | K89: =SUMIF($C$63:$C$86,"Senior",K63:K86) -> 2 | L89: =SUMIF($C$63:$C$86,"Senior",L63:L86) -> 0 | M89: =SUMIF($C$63:$C$86,"Senior",M63:M86) -> 0
D90: Informal caregivers (B) | E90: =SUMIF($C$63:$C$86,"Informal caregiver",E63:E86) -> 12 | F90: =SUMIF($C$63:$C$86,"Informal caregiver",F63:F86) -> 6 | G90: =SUMIF($C$63:$C$86,"Informal caregiver",G63:G86) -> 7 | H90: =SUMIF($C$63:$C$86,"Informal caregiver",H63:H86) -> 5 | I90: =SUMIF($C$63:$C$86,"Informal caregiver",I63:I86) -> 11 | J90: =SUMIF($C$63:$C$86,"Informal caregiver",J63:J86) -> 2 | K90: =SUMIF($C$63:$C$86,"Informal caregiver",K63:K86) -> 5 | L90: =SUMIF($C$63:$C$86,"Informal caregiver",L63:L86) -> 6 | M90: =SUMIF($C$63:$C$86,"Informal caregiver",M63:M86) -> 0
D91: Professional caregivers (C) | E91: =SUMIF($C$63:$C$86,"Professional caregiver",E63:E86) -> 3 | F91: =SUMIF($C$63:$C$86,"Professional caregiver",F63:F86) -> 1 | G91: =SUMIF($C$63:$C$86,"Professional caregiver",G63:G86) -> 3 | H91: =SUMIF($C$63:$C$86,"Professional caregiver",H63:H86) -> 1 | I91: =SUMIF($C$63:$C$86,"Professional caregiver",I63:I86) -> 0 | J91: =SUMIF($C$63:$C$86,"Professional caregiver",J63:J86) -> 4 | K91: =SUMIF($C$63:$C$86,"Professional caregiver",K63:K86) -> 2 | L91: =SUMIF($C$63:$C$86,"Professional caregiver",L63:L86) -> 2 | M91: =SUMIF($C$63:$C$86,"Professional caregiver",M63:M86) -> 1
B93: 5. Informal caregivers' own 1-5 concern ratings (interview file, rows 9-15) — n = 13-14, descriptive only
B94: Concern item | C94: B1 | D94: B2 | E94: B3 | F94: B4 | G94: B5 | H94: B6 | I94: B7 | J94: B8 | K94: B9 | L94: B10 | M94: B11 | N94: B12 | O94: B13 | P94: B14 | Q94: Mean | R94: n | S94: Survey comparator (S40)
B95: Medication errors | C95: 5 | D95: 1 | E95: 1 | F95: 1 | G95: 2 | H95: 3 | I95: 3 | J95: 1 | K95: 4 | L95: 4 | M95: 5 | N95: 5 | O95: 4 | P95: 2 | Q95: =AVERAGE(C95:P95) -> 2.9285714 | R95: =COUNT(C95:P95) -> 14 | S95: Medication errors 21.2% high concern
B96: Early signs of illness | C96: 1 | D96: 2 | E96: 3 | F96: 3 | G96: 2 | H96: 5 | I96: 4 | J96: 4 | K96: 4 | L96: 3 | M96: 5 | N96: 5 | O96: 5 | Q96: =AVERAGE(C96:P96) -> 3.5384615 | R96: =COUNT(C96:P96) -> 13 | S96: Undetected health problems 36.2%
B97: Skipping medical appointments | C97: 1 | D97: 1 | E97: 1 | F97: 2 | G97: 1 | H97: 1 | I97: 2 | J97: 1 | K97: 2 | L97: 4 | M97: 3 | N97: 5 | O97: 2 | P97: 1 | Q97: =AVERAGE(C97:P97) -> 1.9285714 | R97: =COUNT(C97:P97) -> 14 | S97: Forgotten appointments 12.0%
B98: Unhealthy diet | C98: 1 | D98: 1 | E98: 2 | F98: 1 | G98: 2 | H98: 2 | I98: 4 | J98: 4 | K98: 5 | L98: 5 | M98: 4 | N98: 5 | O98: 1 | P98: 5 | Q98: =AVERAGE(C98:P98) -> 3 | R98: =COUNT(C98:P98) -> 14 | S98: Poor diet 22.8%
B99: Sedentary lifestyle | C99: 5 | D99: 1 | E99: 3 | F99: 4 | G99: 4 | H99: 4 | I99: 4 | J99: 4 | K99: 3 | L99: 5 | M99: 3 | N99: 5 | O99: 5 | P99: 3 | Q99: =AVERAGE(C99:P99) -> 3.7857143 | R99: =COUNT(C99:P99) -> 14 | S99: Inactivity 36.4%
B100: Social isolation | C100: 3 | D100: 1 | E100: 3 | F100: 4 | G100: 2 | H100: 5 | I100: 2 | J100: 4 | K100: 4 | L100: 3 | M100: 5 | N100: 4 | O100: 1 | P100: 3 | Q100: =AVERAGE(C100:P100) -> 3.1428571 | R100: =COUNT(C100:P100) -> 14 | S100: (no survey item)
B101: Detect early signs of physical/cognitive decline | C101: 5 | D101: 3 | E101: 1 | F101: 3 | G101: 3 | H101: 4 | I101: 5 | J101: 4 | K101: 4 | L101: 5 | M101: 1 | N101: 1 | O101: 4 | Q101: =AVERAGE(C101:P101) -> 3.3076923 | R101: =COUNT(C101:P101) -> 13 | S101: Early decline detection 77.1% important
B104: 6. Segments supported by the evidence
B105: Segment axis | C105: Evidence | D105: How it is used in this workbook
B106: Buyer (caregiver) vs user (senior) | C106: Quantitative, both groups measured (S40); concern levels 2-3x higher for caregivers | D106: Blended need importance — caregiver 70% / senior 30% (editable on 06)
B107: Independence level (stable vs vulnerable) | C107: Qualitative: high-dependency cases B11, B12, B14 stress falls, night events, medication; independent seniors A1-A5 stress simplicity and autonomy | D107: Scenarios S6 and S7 on 13 (analyst-defined multipliers — labelled assumptions)
B108: Portugal vs Spain | C108: Spanish sample ~76, almost all caregivers — directional only (S40, S41) | D108: Not segmented
B109: Professional caregivers | C109: Qualitative only, n = 5 | D109: Informs clinical-data (N5) and early-decline (N2) needs; no separate weighting
B112: 7. Contradictions between sources (recorded, not hidden)
B113: Topic | C113: Source / finding 1 | D113: Source / finding 2 | E113: Adopted interpretation
B114: Fall detection importance | C114: Deck: 90.5% caregivers / 62% seniors (S40) | D114: Report: 73% / 52% (S41) | E114: Same survey, different cut/denominator. Deck used (full battery with consistent n). Fall detection is the #1 feature in both, so the ranking of needs is unchanged.
B115: Detection vs summoning help | C115: Survey separates 'fall detection' / 'falls' from 'difficulty calling for help' | D115: Interviews mix both ('fall without reaching the phone') | E115: Modelled as two needs (N1 detection, N2 summoning help) so fall detection is not diluted across five features.
B116: Sample size | C116: Deck: 952 started / 546 at value questions | D116: Report: 938 initiated / 543 completed | E116: Treated as one evidence base; no double counting.
B117: Interview count | C117: Business plan: 27 (5/17/5) | D117: Analysis file: 24 (5/14/5); status tab tallies 4/9/5 | E117: Only the 24 documented interviews are coded.
B118: Sedentary behaviour | C118: Survey: inactivity 36.4% caregivers (mid-ranked) | D118: Interview caregivers rate sedentary lifestyle highest of seven items (mean ~3.8/5) | E118: Qualitative evidence lifts N7 above its survey rank; neither dominates (30% qualitative weight).
B119: Medication | C119: Survey: medication errors 21.2% (low) | D119: Coded in 8/24 interviews; caregiver mean ~2.9/5 | E119: N8 kept low-to-moderate; not a primary wearable job.
B120: Location / GPS | C120: Professional C2 wants to know where the person is | D120: Caregiver B11 worries about GPS location data | E120: N9 receives a low weight; GPS is valued inside N2 (being located in an emergency), not as surveillance.
B121: Senior acceptance | C121: Survey: 70% of seniors would accept a biometric bracelet | D121: Interviews B4, B5 expect their parent to refuse technology | E121: Acceptance risk handled through ease of use (N4) and screenless design, not assumed away.
B122: Senior concern levels | C122: Seniors rate every concern far lower than caregivers (n~50) | D122: Caregivers 2-3x more concerned | E122: Caregiver (buyer) weighted 70%, senior (user) 30% — editable.

Sheet 06 Needs-Feature Map
A1: NEEDS-TO-FEATURE MAPPING
A2: Research finding → customer need → device feature → evaluation criterion → device performance. All weights editable; every step is a formula.
B4: 1. Research-weighting parameters (editable assumptions)
B5: Parameter | C5: Value | D5: Basis
B6: Caregiver (buyer) share in the quantitative blend | C6: 0.7 | D6: Caregivers are the economic buyer (interest 59% vs 38%; WTP; concern 2-3x). Assumption — editable.
B7: Senior (user) share | C7: =1-C6 -> 0.3 | D7: Seniors are the wearer; small n (~50)
B8: Quantitative share of need importance | C8: 0.7 | D8: Survey n=497 vs 24 interviews; qualitative must not dominate by volume. Assumption — editable.
B9: Qualitative share | C9: =1-C8 -> 0.3 | D9: Interviews reveal needs the survey missed and corroborate direction
B10: Discount for needs with qualitative evidence only | C10: 0.5 | D10: Prevents a need with no survey support from receiving full weight. Assumption — editable.
B12: 2. Need importance — normalised survey batteries (05 §2) blended with interview coding (05 §4)
B13: Need | C13: Customer need | D13: What it means | E13: Feature-importance index (B1) | F13: Concern index (B2) | G13: Decision-driver index (B3) | H13: Quantitative index | I13: Interviews (of 24) | J13: Qualitative index | K13: Raw importance | L13: Weight | M13: Rank | N13: Evidence basis
B14: N1 | C14: Automatic fall / incident detection | D14: An alert is raised even if the senior cannot act | E14: =IF(COUNTIF('05 Market Research'!$E$14:$E$21,$B14)=0,"",SUMPRODUCT(MAX(('05 Market Research'!$E$14:$E$21=$B14)*'05 Market Research'!$F$14:$F$21))*100) -> 100 | F14: =IF(COUNTIF('05 Market Research'!$E$26:$E$35,$B14)=0,"",SUMPRODUCT(MAX(('05 Market Research'!$E$26:$E$35=$B14)*'05 Market Research'!$F$26:$F$35))*100) -> 100 | G14: =IF(COUNTIF('05 Market Research'!$E$40:$E$44,$B14)=0,"",SUMPRODUCT(MAX(('05 Market Research'!$E$40:$E$44=$B14)*'05 Market Research'!$F$40:$F$44))*100) | H14: =IF(COUNT(E14:G14)=0,"",AVERAGE(E14:G14)) -> 100 | I14: ='05 Market Research'!E87 -> 18 | J14: =I14/MAX($I$14:$I$22)*100 -> 100 | K14: =IF(H14="",$C$10*J14,$C$8*H14+$C$9*J14) -> 100 | L14: =K14/SUM($K$14:$K$22) -> 0.17061818 | M14: =SUMPRODUCT(--($L$14:$L$22>L14))+1 -> 1 | N14: Fall detection is the #1 feature: 90.5% caregivers / 62% seniors (B1); falls 54.8% high concern (B2); 18 of 24 interviews
B15: N2 | C15: Summoning help & being reached | D15: SOS, two-way calling and locating the person in an emergency | E15: =IF(COUNTIF('05 Market Research'!$E$14:$E$21,$B15)=0,"",SUMPRODUCT(MAX(('05 Market Research'!$E$14:$E$21=$B15)*'05 Market Research'!$F$14:$F$21))*100) | F15: =IF(COUNTIF('05 Market Research'!$E$26:$E$35,$B15)=0,"",SUMPRODUCT(MAX(('05 Market Research'!$E$26:$E$35=$B15)*'05 Market Research'!$F$26:$F$35))*100) -> 83.526797 | G15: =IF(COUNTIF('05 Market Research'!$E$40:$E$44,$B15)=0,"",SUMPRODUCT(MAX(('05 Market Research'!$E$40:$E$44=$B15)*'05 Market Research'!$F$40:$F$44))*100) | H15: =IF(COUNT(E15:G15)=0,"",AVERAGE(E15:G15)) -> 83.526797 | I15: ='05 Market Research'!F87 -> 8 | J15: =I15/MAX($I$14:$I$22)*100 -> 44.444444 | K15: =IF(H15="",$C$10*J15,$C$8*H15+$C$9*J15) -> 71.802091 | L15: =K15/SUM($K$14:$K$22) -> 0.12250742 | M15: =SUMPRODUCT(--($L$14:$L$22>L15))+1 -> 4 | N15: Difficulty calling for help 44.5% high concern (B2); 8 of 24 interviews ('cannot reach the phone', 'emergency button')
B16: N3 | C16: Early detection of physical & cognitive decline | D16: Passive signals that surface what seniors do not report | E16: =IF(COUNTIF('05 Market Research'!$E$14:$E$21,$B16)=0,"",SUMPRODUCT(MAX(('05 Market Research'!$E$14:$E$21=$B16)*'05 Market Research'!$F$14:$F$21))*100) -> 83.42892 | F16: =IF(COUNTIF('05 Market Research'!$E$26:$E$35,$B16)=0,"",SUMPRODUCT(MAX(('05 Market Research'!$E$26:$E$35=$B16)*'05 Market Research'!$F$26:$F$35))*100) -> 90.491479 | G16: =IF(COUNTIF('05 Market Research'!$E$40:$E$44,$B16)=0,"",SUMPRODUCT(MAX(('05 Market Research'!$E$40:$E$44=$B16)*'05 Market Research'!$F$40:$F$44))*100) | H16: =IF(COUNT(E16:G16)=0,"",AVERAGE(E16:G16)) -> 86.9602 | I16: ='05 Market Research'!G87 -> 11 | J16: =I16/MAX($I$14:$I$22)*100 -> 61.111111 | K16: =IF(H16="",$C$10*J16,$C$8*H16+$C$9*J16) -> 79.205473 | L16: =K16/SUM($K$14:$K$22) -> 0.13513894 | M16: =SUMPRODUCT(--($L$14:$L$22>L16))+1 -> 3 | N16: Early decline 77.1% / 48% (B1); physical decline 49.3% (B2); 53% say elder minimises symptoms (Q30); 11 of 24 interviews
B17: N4 | C17: Ease of use & low burden for the senior | D17: Simple, passive, rarely charged, no phone needed, comfortable | E17: =IF(COUNTIF('05 Market Research'!$E$14:$E$21,$B17)=0,"",SUMPRODUCT(MAX(('05 Market Research'!$E$14:$E$21=$B17)*'05 Market Research'!$F$14:$F$21))*100) | F17: =IF(COUNTIF('05 Market Research'!$E$26:$E$35,$B17)=0,"",SUMPRODUCT(MAX(('05 Market Research'!$E$26:$E$35=$B17)*'05 Market Research'!$F$26:$F$35))*100) | G17: =IF(COUNTIF('05 Market Research'!$E$40:$E$44,$B17)=0,"",SUMPRODUCT(MAX(('05 Market Research'!$E$40:$E$44=$B17)*'05 Market Research'!$F$40:$F$44))*100) -> 100 | H17: =IF(COUNT(E17:G17)=0,"",AVERAGE(E17:G17)) -> 100 | I17: ='05 Market Research'!H87 -> 10 | J17: =I17/MAX($I$14:$I$22)*100 -> 55.555556 | K17: =IF(H17="",$C$10*J17,$C$8*H17+$C$9*J17) -> 86.666667 | L17: =K17/SUM($K$14:$K$22) -> 0.14786909 | M17: =SUMPRODUCT(--($L$14:$L$22>L17))+1 -> 2 | N17: Easy to use is the #1 decision driver: 69.4% / 76% (B3); 10 of 24 interviews ('passive', 'no maintenance'); ~36% of seniors have no smartphone (Q31)
B18: N5 | C18: Privacy & non-intrusiveness | D18: No surveillance feel; control over where data goes | E18: =IF(COUNTIF('05 Market Research'!$E$14:$E$21,$B18)=0,"",SUMPRODUCT(MAX(('05 Market Research'!$E$14:$E$21=$B18)*'05 Market Research'!$F$14:$F$21))*100) | F18: =IF(COUNTIF('05 Market Research'!$E$26:$E$35,$B18)=0,"",SUMPRODUCT(MAX(('05 Market Research'!$E$26:$E$35=$B18)*'05 Market Research'!$F$26:$F$35))*100) | G18: =IF(COUNTIF('05 Market Research'!$E$40:$E$44,$B18)=0,"",SUMPRODUCT(MAX(('05 Market Research'!$E$40:$E$44=$B18)*'05 Market Research'!$F$40:$F$44))*100) -> 71.686747 | H18: =IF(COUNT(E18:G18)=0,"",AVERAGE(E18:G18)) -> 71.686747 | I18: ='05 Market Research'!I87 -> 12 | J18: =I18/MAX($I$14:$I$22)*100 -> 66.666667 | K18: =IF(H18="",$C$10*J18,$C$8*H18+$C$9*J18) -> 70.180723 | L18: =K18/SUM($K$14:$K$22) -> 0.11974108 | M18: =SUMPRODUCT(--($L$14:$L$22>L18))+1 -> 6 | N18: Privacy is the #2 decision driver: 55.1% / 42% (B3); cameras rejected by 64% of seniors; 12 of 24 interviews
B19: N6 | C19: Clinical data for the doctor | D19: Vital signs a physician can use | E19: =IF(COUNTIF('05 Market Research'!$E$14:$E$21,$B19)=0,"",SUMPRODUCT(MAX(('05 Market Research'!$E$14:$E$21=$B19)*'05 Market Research'!$F$14:$F$21))*100) -> 79.926785 | F19: =IF(COUNTIF('05 Market Research'!$E$26:$E$35,$B19)=0,"",SUMPRODUCT(MAX(('05 Market Research'!$E$26:$E$35=$B19)*'05 Market Research'!$F$26:$F$35))*100) | G19: =IF(COUNTIF('05 Market Research'!$E$40:$E$44,$B19)=0,"",SUMPRODUCT(MAX(('05 Market Research'!$E$40:$E$44=$B19)*'05 Market Research'!$F$40:$F$44))*100) | H19: =IF(COUNT(E19:G19)=0,"",AVERAGE(E19:G19)) -> 79.926785 | I19: ='05 Market Research'!J87 -> 9 | J19: =I19/MAX($I$14:$I$22)*100 -> 50 | K19: =IF(H19="",$C$10*J19,$C$8*H19+$C$9*J19) -> 70.948749 | L19: =K19/SUM($K$14:$K$22) -> 0.12105147 | M19: =SUMPRODUCT(--($L$14:$L$22>L19))+1 -> 5 | N19: Doctor data sharing 73% / 48% (B1); professionals want vital signs (C1, C3, C5); 9 of 24 interviews
B20: N7 | C20: Activity & sedentary behaviour | D20: Movement and inactivity | E20: =IF(COUNTIF('05 Market Research'!$E$14:$E$21,$B20)=0,"",SUMPRODUCT(MAX(('05 Market Research'!$E$14:$E$21=$B20)*'05 Market Research'!$F$14:$F$21))*100) | F20: =IF(COUNTIF('05 Market Research'!$E$26:$E$35,$B20)=0,"",SUMPRODUCT(MAX(('05 Market Research'!$E$26:$E$35=$B20)*'05 Market Research'!$F$26:$F$35))*100) -> 72.190664 | G20: =IF(COUNTIF('05 Market Research'!$E$40:$E$44,$B20)=0,"",SUMPRODUCT(MAX(('05 Market Research'!$E$40:$E$44=$B20)*'05 Market Research'!$F$40:$F$44))*100) | H20: =IF(COUNT(E20:G20)=0,"",AVERAGE(E20:G20)) -> 72.190664 | I20: ='05 Market Research'!K87 -> 9 | J20: =I20/MAX($I$14:$I$22)*100 -> 50 | K20: =IF(H20="",$C$10*J20,$C$8*H20+$C$9*J20) -> 65.533465 | L20: =K20/SUM($K$14:$K$22) -> 0.11181201 | M20: =SUMPRODUCT(--($L$14:$L$22>L20))+1 -> 7 | N20: Inactivity 36.4% (B2); sedentary lifestyle is caregivers' highest-rated interview concern (mean ~3.8/5); 9 of 24 interviews
B21: N8 | C21: Medication adherence | D21: Reminders / adherence support | E21: =IF(COUNTIF('05 Market Research'!$E$14:$E$21,$B21)=0,"",SUMPRODUCT(MAX(('05 Market Research'!$E$14:$E$21=$B21)*'05 Market Research'!$F$14:$F$21))*100) | F21: =IF(COUNTIF('05 Market Research'!$E$26:$E$35,$B21)=0,"",SUMPRODUCT(MAX(('05 Market Research'!$E$26:$E$35=$B21)*'05 Market Research'!$F$26:$F$35))*100) -> 36.651025 | G21: =IF(COUNTIF('05 Market Research'!$E$40:$E$44,$B21)=0,"",SUMPRODUCT(MAX(('05 Market Research'!$E$40:$E$44=$B21)*'05 Market Research'!$F$40:$F$44))*100) | H21: =IF(COUNT(E21:G21)=0,"",AVERAGE(E21:G21)) -> 36.651025 | I21: ='05 Market Research'!L87 -> 8 | J21: =I21/MAX($I$14:$I$22)*100 -> 44.444444 | K21: =IF(H21="",$C$10*J21,$C$8*H21+$C$9*J21) -> 38.989051 | L21: =K21/SUM($K$14:$K$22) -> 0.066522411 | M21: =SUMPRODUCT(--($L$14:$L$22>L21))+1 -> 8 | N21: Medication errors 21.2% (B2); 8 of 24 interviews
B22: N9 | C22: Location & wandering | D22: Knowing where the person is | E22: =IF(COUNTIF('05 Market Research'!$E$14:$E$21,$B22)=0,"",SUMPRODUCT(MAX(('05 Market Research'!$E$14:$E$21=$B22)*'05 Market Research'!$F$14:$F$21))*100) | F22: =IF(COUNTIF('05 Market Research'!$E$26:$E$35,$B22)=0,"",SUMPRODUCT(MAX(('05 Market Research'!$E$26:$E$35=$B22)*'05 Market Research'!$F$26:$F$35))*100) | G22: =IF(COUNTIF('05 Market Research'!$E$40:$E$44,$B22)=0,"",SUMPRODUCT(MAX(('05 Market Research'!$E$40:$E$44=$B22)*'05 Market Research'!$F$40:$F$44))*100) | H22: =IF(COUNT(E22:G22)=0,"",AVERAGE(E22:G22)) | I22: ='05 Market Research'!M87 -> 1 | J22: =I22/MAX($I$14:$I$22)*100 -> 5.5555556 | K22: =IF(H22="",$C$10*J22,$C$8*H22+$C$9*J22) -> 2.7777778 | L22: =K22/SUM($K$14:$K$22) -> 0.004739394 | M22: =SUMPRODUCT(--($L$14:$L$22>L22))+1 -> 9 | N22: No survey item; 1 of 24 interviews positive (C2) and 1 privacy concern about GPS (B11)
K23: Total | L23: =SUM(L14:L22) -> 1
B24: 3. Within-need contributions — which device features deliver each need (editable; each need column must total 100%)
B25: Code | C25: Feature / attribute | D25: N1 | E25: N2 | F25: N3 | G25: N4 | H25: N5 | I25: N6 | J25: N7 | K25: N8 | L25: N9 | M25: Research importance of feature | N25: Category
C26: Need weight → | D26: =$L$14 -> 0.17061818 | E26: =$L$15 -> 0.12250742 | F26: =$L$16 -> 0.13513894 | G26: =$L$17 -> 0.14786909 | H26: =$L$18 -> 0.11974108 | I26: =$L$19 -> 0.12105147 | J26: =$L$20 -> 0.11181201 | K26: =$L$21 -> 0.066522411 | L26: =$L$22 -> 0.004739394
B27: F01 | C27: Heart rate | D27: 0 | E27: 0 | F27: 0.15 | G27: 0 | H27: 0 | I27: 0.1 | J27: 0 | K27: 0 | L27: 0 | M27: =SUMPRODUCT($D$26:$L$26,D27:L27) -> 0.032375988 | N27: Physiological | O27: N5 note: wrist devices differ little in physical intrusiveness (none has a camera). Privacy differences sit in data handling, scored in Integration (I8) and Regulatory (R3) rather than here — avoiding double counting.
B28: F02 | C28: Heart-rate variability (HRV) | D28: 0 | E28: 0 | F28: 0.15 | G28: 0 | H28: 0 | I28: 0 | J28: 0 | K28: 0 | L28: 0 | M28: =SUMPRODUCT($D$26:$L$26,D28:L28) -> 0.020270841 | N28: Physiological
B29: F03 | C29: ECG | D29: 0 | E29: 0 | F29: 0 | G29: 0 | H29: 0 | I29: 0.3 | J29: 0 | K29: 0 | L29: 0 | M29: =SUMPRODUCT($D$26:$L$26,D29:L29) -> 0.03631544 | N29: Physiological
B30: F04 | C30: SpO2 | D30: 0 | E30: 0 | F30: 0.1 | G30: 0 | H30: 0 | I30: 0.2 | J30: 0 | K30: 0 | L30: 0 | M30: =SUMPRODUCT($D$26:$L$26,D30:L30) -> 0.037724188 | N30: Physiological
B31: F05 | C31: Blood pressure | D31: 0 | E31: 0 | F31: 0 | G31: 0 | H31: 0 | I31: 0.3 | J31: 0 | K31: 0 | L31: 0 | M31: =SUMPRODUCT($D$26:$L$26,D31:L31) -> 0.03631544 | N31: Physiological
B32: F06 | C32: Body / skin temperature | D32: 0 | E32: 0 | F32: 0.1 | G32: 0 | H32: 0 | I32: 0.1 | J32: 0 | K32: 0 | L32: 0 | M32: =SUMPRODUCT($D$26:$L$26,D32:L32) -> 0.025619041 | N32: Physiological
B33: F07 | C33: Sleep monitoring | D33: 0 | E33: 0 | F33: 0.2 | G33: 0 | H33: 0 | I33: 0 | J33: 0 | K33: 0 | L33: 0 | M33: =SUMPRODUCT($D$26:$L$26,D33:L33) -> 0.027027788 | N33: Physiological
B34: F08 | C34: Steps & activity | D34: 0 | E34: 0 | F34: 0.15 | G34: 0 | H34: 0 | I34: 0 | J34: 1 | K34: 0 | L34: 0 | M34: =SUMPRODUCT($D$26:$L$26,D34:L34) -> 0.13208285 | N34: Physiological
B35: F09 | C35: Stress indicator | D35: 0 | E35: 0 | F35: 0.15 | G35: 0 | H35: 0 | I35: 0 | J35: 0 | K35: 0 | L35: 0 | M35: =SUMPRODUCT($D$26:$L$26,D35:L35) -> 0.020270841 | N35: Physiological
B36: F10 | C36: Automatic fall detection | D36: 1 | E36: 0 | F36: 0 | G36: 0 | H36: 0 | I36: 0 | J36: 0 | K36: 0 | L36: 0 | M36: =SUMPRODUCT($D$26:$L$26,D36:L36) -> 0.17061818 | N36: Safety
B37: F11 | C37: SOS button | D37: 0 | E37: 0.4 | F37: 0 | G37: 0 | H37: 0 | I37: 0 | J37: 0 | K37: 0 | L37: 0 | M37: =SUMPRODUCT($D$26:$L$26,D37:L37) -> 0.04900297 | N37: Safety
B38: F12 | C38: Two-way voice calling | D38: 0 | E38: 0.3 | F38: 0 | G38: 0 | H38: 0 | I38: 0 | J38: 0 | K38: 0 | L38: 0 | M38: =SUMPRODUCT($D$26:$L$26,D38:L38) -> 0.036752227 | N38: Safety
B39: F13 | C39: GNSS positioning | D39: 0 | E39: 0.15 | F39: 0 | G39: 0 | H39: 0 | I39: 0 | J39: 0 | K39: 0 | L39: 0.6 | M39: =SUMPRODUCT($D$26:$L$26,D39:L39) -> 0.02121975 | N39: Safety
... B50: WGT | C50: Weight / comfort class (from 03 specs) | D50: 0 | E50: 0 | F50: 0 | G50: 0.2 | H50: 0 | I50: 0 | J50: 0 | K50: 0 | L50: 0 | M50: =SUMPRODUCT($D$26:$L$26,D50:L50) -> 0.029573819 | N50: Usability
C51: Column total (must be 100%) | D51: =SUM(D27:D50) -> 1 | E51: =SUM(E27:E50) -> 1 | F51: =SUM(F27:F50) -> 1 | G51: =SUM(G27:G50) -> 1 | H51: =SUM(H27:H50) -> 1 | I51: =SUM(I27:I50) -> 1 | J51: =SUM(J27:J50) -> 1 | K51: =SUM(K27:K50) -> 1 | L51: =SUM(L27:L50) -> 1
B53: 4. Device credit per feature — status on 03 × status credits on 10 (Unknown receives partial credit, never full)
B55: Code | C55: Feature / attribute | D55: VB10 | E55: CT29 | F55: CT34 | G55: MF90 | H55: MF91 | I55: MF40 | J55: HW20 | K55: MF91Pro | L55: HW20Pro | M55: HW19 | N55: CT20S | O55: CT30 (band) | P55: CT31
B56: F01 | C56: Heart rate | D56: =(('03 Feature Comparison'!F6="Yes")*'10 Scoring & Weights'!$C$7+('03 Feature Comparison'!F6="Conditional")*'10 Scoring & Weights'!$C$8+('03 Feature Comparison'!F6="Unknown")*'10 Scoring & Weights'!$C$9+('03 Feature Comparison'!F6="No")*'10 Scoring & Weights'!$C$10) -> 1 | E56: =(('03 Feature Comparison'!F7="Yes")*'10 Scoring & Weights'!$C$7+('03 Feature Comparison'!F7="Conditional")*'10 Scoring & Weights'!$C$8+('03 Feature Comparison'!F7="Unknown")*'10 Scoring & Weights'!$C$9+('03 Feature Comparison'!F7="No")*'10 Scoring & Weights'!$C$10) -> 0.25 | F56: =(('03 Feature Comparison'!F8="Yes")*'10 Scoring & Weights'!$C$7+('03 Feature Comparison'!F8="Conditional")*'10 Scoring & Weights'!$C$8+('03 Feature Comparison'!F8="Unknown")*'10 Scoring & Weights'!$C$9+('03 Feature Comparison'!F8="No")*'10 Scoring & Weights'!$C$10) -> 0.25 | G56: =(('03 Feature Comparison'!F9="Yes")*'10 Scoring & Weights'!$C$7+('03 Feature Comparison'!F9="Conditional")*'10 Scoring & Weights'!$C$8+('03 Feature Comparison'!F9="Unknown")*'10 Scoring & Weights'!$C$9+('03 Feature Comparison'!F9="No")*'10 Scoring & Weights'!$C$10) -> 1 | H56: =(('03 Feature Comparison'!F10="Yes")*'10 Scoring & Weights'!$C$7+('03 Feature Comparison'!F10="Conditional")*'10 Scoring & Weights'!$C$8+('03 Feature Comparison'!F10="Unknown")*'10 Scoring & Weights'!$C$9+('03 Feature Comparison'!F10="No")*'10 Scoring & Weights'!$C$10) -> 1 | I56: =(('03 Feature Comparison'!F11="Yes")*'10 Scoring & Weights'!$C$7+('03 Feature Comparison'!F11="Conditional")*'10 Scoring & Weights'!$C$8+('03 Feature Comparison'!F11="Unknown")*'10 Scoring & Weights'!$C$9+('03 Feature Comparison'!F11="No")*'10 Scoring & Weights'!$C$10) -> 1 | J56: =(('03 Feature Comparison'!F12="Yes")*'10 Scoring & Weights'!$C$7+('03 Feature Comparison'!F12="Conditional")*'10 Scoring & Weights'!$C$8+('03 Feature Comparison'!F12="Unknown")*'10 Scoring & Weights'!$C$9+('03 Feature Comparison'!F12="No")*'10 Scoring & Weights'!$C$10) -> 1 | K56: =(('03 Feature Comparison'!F13="Yes")*'10 Scoring & Weights'!$C$7+('03 Feature Comparison'!F13="Conditional")*'10 Scoring & Weights'!$C$8+('03 Feature Comparison'!F13="Unknown")*'10 Scoring & Weights'!$C$9+('03 Feature Comparison'!F13="No")*'10 Scoring & Weights'!$C$10) -> 1 | L56: =(('03 Feature Comparison'!F14="Yes")*'10 Scoring & Weights'!$C$7+('03 Feature Comparison'!F14="Conditional")*'10 Scoring & Weights'!$C$8+('03 Feature Comparison'!F14="Unknown")*'10 Scoring & Weights'!$C$9+('03 Feature Comparison'!F14="No")*'10 Scoring & Weights'!$C$10) -> 0.25 | M56: =(('03 Feature Comparison'!F15="Yes")*'10 Scoring & Weights'!$C$7+('03 Feature Comparison'!F15="Conditional")*'10 Scoring & Weights'!$C$8+('03 Feature Comparison'!F15="Unknown")*'10 Scoring & Weights'!$C$9+('03 Feature Comparison'!F15="No")*'10 Scoring & Weights'!$C$10) -> 1 | N56: =(('03 Feature Comparison'!F16="Yes")*'10 Scoring & Weights'!$C$7+('03 Feature Comparison'!F16="Conditional")*'10 Scoring & Weights'!$C$8+('03 Feature Comparison'!F16="Unknown")*'10 Scoring & Weights'!$C$9+('03 Feature Comparison'!F16="No")*'10 Scoring & Weights'!$C$10) -> 1 | O56: =(('03 Feature Comparison'!F17="Yes")*'10 Scoring & Weights'!$C$7+('03 Feature Comparison'!F17="Conditional")*'10 Scoring & Weights'!$C$8+('03 Feature Comparison'!F17="Unknown")*'10 Scoring & Weights'!$C$9+('03 Feature Comparison'!F17="No")*'10 Scoring & Weights'!$C$10) -> 1 | P56: =(('03 Feature Comparison'!F18="Yes")*'10 Scoring & Weights'!$C$7+('03 Feature Comparison'!F18="Conditional")*'10 Scoring & Weights'!$C$8+('03 Feature Comparison'!F18="Unknown")*'10 Scoring & Weights'!$C$9+('03 Feature Comparison'!F18="No")*'10 Scoring & Weights'!$C$10) -> 1
B57: F02 | C57: Heart-rate variability (HRV) | D57: =(('03 Feature Comparison'!G6="Yes")*'10 Scoring & Weights'!$C$7+('03 Feature Comparison'!G6="Conditional")*'10 Scoring & Weights'!$C$8+('03 Feature Comparison'!G6="Unknown")*'10 Scoring & Weights'!$C$9+('03 Feature Comparison'!G6="No")*'10 Scoring & Weights'!$C$10) -> 1 | E57: =(('03 Feature Comparison'!G7="Yes")*'10 Scoring & Weights'!$C$7+('03 Feature Comparison'!G7="Conditional")*'10 Scoring & Weights'!$C$8+('03 Feature Comparison'!G7="Unknown")*'10 Scoring & Weights'!$C$9+('03 Feature Comparison'!G7="No")*'10 Scoring & Weights'!$C$10) -> 0.25 | F57: =(('03 Feature Comparison'!G8="Yes")*'10 Scoring & Weights'!$C$7+('03 Feature Comparison'!G8="Conditional")*'10 Scoring & Weights'!$C$8+('03 Feature Comparison'!G8="Unknown")*'10 Scoring & Weights'!$C$9+('03 Feature Comparison'!G8="No")*'10 Scoring & Weights'!$C$10) -> 0.25 | G57: =(('03 Feature Comparison'!G9="Yes")*'10 Scoring & Weights'!$C$7+('03 Feature Comparison'!G9="Conditional")*'10 Scoring & Weights'!$C$8+('03 Feature Comparison'!G9="Unknown")*'10 Scoring & Weights'!$C$9+('03 Feature Comparison'!G9="No")*'10 Scoring & Weights'!$C$10) -> 1 | H57: =(('03 Feature Comparison'!G10="Yes")*'10 Scoring & Weights'!$C$7+('03 Feature Comparison'!G10="Conditional")*'10 Scoring & Weights'!$C$8+('03 Feature Comparison'!G10="Unknown")*'10 Scoring & Weights'!$C$9+('03 Feature Comparison'!G10="No")*'10 Scoring & Weights'!$C$10) -> 1 | I57: =(('03 Feature Comparison'!G11="Yes")*'10 Scoring & Weights'!$C$7+('03 Feature Comparison'!G11="Conditional")*'10 Scoring & Weights'!$C$8+('03 Feature Comparison'!G11="Unknown")*'10 Scoring & Weights'!$C$9+('03 Feature Comparison'!G11="No")*'10 Scoring & Weights'!$C$10) -> 0.25 | J57: =(('03 Feature Comparison'!G12="Yes")*'10 Scoring & Weights'!$C$7+('03 Feature Comparison'!G12="Conditional")*'10 Scoring & Weights'!$C$8+('03 Feature Comparison'!G12="Unknown")*'10 Scoring & Weights'!$C$9+('03 Feature Comparison'!G12="No")*'10 Scoring & Weights'!$C$10) -> 0.25 | K57: =(('03 Feature Comparison'!G13="Yes")*'10 Scoring & Weights'!$C$7+('03 Feature Comparison'!G13="Conditional")*'10 Scoring & Weights'!$C$8+('03 Feature Comparison'!G13="Unknown")*'10 Scoring & Weights'!$C$9+('03 Feature Comparison'!G13="No")*'10 Scoring & Weights'!$C$10) -> 1 | L57: =(('03 Feature Comparison'!G14="Yes")*'10 Scoring & Weights'!$C$7+('03 Feature Comparison'!G14="Conditional")*'10 Scoring & Weights'!$C$8+('03 Feature Comparison'!G14="Unknown")*'10 Scoring & Weights'!$C$9+('03 Feature Comparison'!G14="No")*'10 Scoring & Weights'!$C$10) -> 0.25 | M57: =(('03 Feature Comparison'!G15="Yes")*'10 Scoring & Weights'!$C$7+('03 Feature Comparison'!G15="Conditional")*'10 Scoring & Weights'!$C$8+('03 Feature Comparison'!G15="Unknown")*'10 Scoring & Weights'!$C$9+('03 Feature Comparison'!G15="No")*'10 Scoring & Weights'!$C$10) -> 1 | N57: =(('03 Feature Comparison'!G16="Yes")*'10 Scoring & Weights'!$C$7+('03 Feature Comparison'!G16="Conditional")*'10 Scoring & Weights'!$C$8+('03 Feature Comparison'!G16="Unknown")*'10 Scoring & Weights'!$C$9+('03 Feature Comparison'!G16="No")*'10 Scoring & Weights'!$C$10) -> 0.25 | O57: =(('03 Feature Comparison'!G17="Yes")*'10 Scoring & Weights'!$C$7+('03 Feature Comparison'!G17="Conditional")*'10 Scoring & Weights'!$C$8+('03 Feature Comparison'!G17="Unknown")*'10 Scoring & Weights'!$C$9+('03 Feature Comparison'!G17="No")*'10 Scoring & Weights'!$C$10) -> 0.25 | P57: =(('03 Feature Comparison'!G18="Yes")*'10 Scoring & Weights'!$C$7+('03 Feature Comparison'!G18="Conditional")*'10 Scoring & Weights'!$C$8+('03 Feature Comparison'!G18="Unknown")*'10 Scoring & Weights'!$C$9+('03 Feature Comparison'!G18="No")*'10 Scoring & Weights'!$C$10) -> 0.25
B58: F03 | C58: ECG | D58: =(('03 Feature Comparison'!H6="Yes")*'10 Scoring & Weights'!$C$7+('03 Feature Comparison'!H6="Conditional")*'10 Scoring & Weights'!$C$8+('03 Feature Comparison'!H6="Unknown")*'10 Scoring & Weights'!$C$9+('03 Feature Comparison'!H6="No")*'10 Scoring & Weights'!$C$10) -> 1 | E58: =(('03 Feature Comparison'!H7="Yes")*'10 Scoring & Weights'!$C$7+('03 Feature Comparison'!H7="Conditional")*'10 Scoring & Weights'!$C$8+('03 Feature Comparison'!H7="Unknown")*'10 Scoring & Weights'!$C$9+('03 Feature Comparison'!H7="No")*'10 Scoring & Weights'!$C$10) -> 0.25 | F58: =(('03 Feature Comparison'!H8="Yes")*'10 Scoring & Weights'!$C$7+('03 Feature Comparison'!H8="Conditional")*'10 Scoring & Weights'!$C$8+('03 Feature Comparison'!H8="Unknown")*'10 Scoring & Weights'!$C$9+('03 Feature Comparison'!H8="No")*'10 Scoring & Weights'!$C$10) -> 0.25 | G58: =(('03 Feature Comparison'!H9="Yes")*'10 Scoring & Weights'!$C$7+('03 Feature Comparison'!H9="Conditional")*'10 Scoring & Weights'!$C$8+('03 Feature Comparison'!H9="Unknown")*'10 Scoring & Weights'!$C$9+('03 Feature Comparison'!H9="No")*'10 Scoring & Weights'!$C$10) -> 1 | H58: =(('03 Feature Comparison'!H10="Yes")*'10 Scoring & Weights'!$C$7+('03 Feature Comparison'!H10="Conditional")*'10 Scoring & Weights'!$C$8+('03 Feature Comparison'!H10="Unknown")*'10 Scoring & Weights'!$C$9+('03 Feature Comparison'!H10="No")*'10 Scoring & Weights'!$C$10) -> 0.25 | I58: =(('03 Feature Comparison'!H11="Yes")*'10 Scoring & Weights'!$C$7+('03 Feature Comparison'!H11="Conditional")*'10 Scoring & Weights'!$C$8+('03 Feature Comparison'!H11="Unknown")*'10 Scoring & Weights'!$C$9+('03 Feature Comparison'!H11="No")*'10 Scoring & Weights'!$C$10) -> 1 | J58: =(('03 Feature Comparison'!H12="Yes")*'10 Scoring & Weights'!$C$7+('03 Feature Comparison'!H12="Conditional")*'10 Scoring & Weights'!$C$8+('03 Feature Comparison'!H12="Unknown")*'10 Scoring & Weights'!$C$9+('03 Feature Comparison'!H12="No")*'10 Scoring & Weights'!$C$10) -> 0.25 | K58: =(('03 Feature Comparison'!H13="Yes")*'10 Scoring & Weights'!$C$7+('03 Feature Comparison'!H13="Conditional")*'10 Scoring & Weights'!$C$8+('03 Feature Comparison'!H13="Unknown")*'10 Scoring & Weights'!$C$9+('03 Feature Comparison'!H13="No")*'10 Scoring & Weights'!$C$10) -> 1 | L58: =(('03 Feature Comparison'!H14="Yes")*'10 Scoring & Weights'!$C$7+('03 Feature Comparison'!H14="Conditional")*'10 Scoring & Weights'!$C$8+('03 Feature Comparison'!H14="Unknown")*'10 Scoring & Weights'!$C$9+('03 Feature Comparison'!H14="No")*'10 Scoring & Weights'!$C$10) -> 0.25 | M58: =(('03 Feature Comparison'!H15="Yes")*'10 Scoring & Weights'!$C$7+('03 Feature Comparison'!H15="Conditional")*'10 Scoring & Weights'!$C$8+('03 Feature Comparison'!H15="Unknown")*'10 Scoring & Weights'!$C$9+('03 Feature Comparison'!H15="No")*'10 Scoring & Weights'!$C$10) -> 0.25 | N58: =(('03 Feature Comparison'!H16="Yes")*'10 Scoring & Weights'!$C$7+('03 Feature Comparison'!H16="Conditional")*'10 Scoring & Weights'!$C$8+('03 Feature Comparison'!H16="Unknown")*'10 Scoring & Weights'!$C$9+('03 Feature Comparison'!H16="No")*'10 Scoring & Weights'!$C$10) -> 0.25 | O58: =(('03 Feature Comparison'!H17="Yes")*'10 Scoring & Weights'!$C$7+('03 Feature Comparison'!H17="Conditional")*'10 Scoring & Weights'!$C$8+('03 Feature Comparison'!H17="Unknown")*'10 Scoring & Weights'!$C$9+('03 Feature Comparison'!H17="No")*'10 Scoring & Weights'!$C$10) -> 0.25 | P58: =(('03 Feature Comparison'!H18="Yes")*'10 Scoring & Weights'!$C$7+('03 Feature Comparison'!H18="Conditional")*'10 Scoring & Weights'!$C$8+('03 Feature Comparison'!H18="Unknown")*'10 Scoring & Weights'!$C$9+('03 Feature Comparison'!H18="No")*'10 Scoring & Weights'!$C$10) -> 0.25
B59: F04 | C59: SpO2 | D59: =(('03 Feature Comparison'!I6="Yes")*'10 Scoring & Weights'!$C$7+('03 Feature Comparison'!I6="Conditional")*'10 Scoring & Weights'!$C$8+('03 Feature Comparison'!I6="Unknown")*'10 Scoring & Weights'!$C$9+('03 Feature Comparison'!I6="No")*'10 Scoring & Weights'!$C$10) -> 1 | E59: =(('03 Feature Comparison'!I7="Yes")*'10 Scoring & Weights'!$C$7+('03 Feature Comparison'!I7="Conditional")*'10 Scoring & Weights'!$C$8+('03 Feature Comparison'!I7="Unknown")*'10 Scoring & Weights'!$C$9+('03 Feature Comparison'!I7="No")*'10 Scoring & Weights'!$C$10) -> 0.25 | F59: =(('03 Feature Comparison'!I8="Yes")*'10 Scoring & Weights'!$C$7+('03 Feature Comparison'!I8="Conditional")*'10 Scoring & Weights'!$C$8+('03 Feature Comparison'!I8="Unknown")*'10 Scoring & Weights'!$C$9+('03 Feature Comparison'!I8="No")*'10 Scoring & Weights'!$C$10) -> 0.25 | G59: =(('03 Feature Comparison'!I9="Yes")*'10 Scoring & Weights'!$C$7+('03 Feature Comparison'!I9="Conditional")*'10 Scoring & Weights'!$C$8+('03 Feature Comparison'!I9="Unknown")*'10 Scoring & Weights'!$C$9+('03 Feature Comparison'!I9="No")*'10 Scoring & Weights'!$C$10) -> 1 | H59: =(('03 Feature Comparison'!I10="Yes")*'10 Scoring & Weights'!$C$7+('03 Feature Comparison'!I10="Conditional")*'10 Scoring & Weights'!$C$8+('03 Feature Comparison'!I10="Unknown")*'10 Scoring & Weights'!$C$9+('03 Feature Comparison'!I10="No")*'10 Scoring & Weights'!$C$10) -> 1 | I59: =(('03 Feature Comparison'!I11="Yes")*'10 Scoring & Weights'!$C$7+('03 Feature Comparison'!I11="Conditional")*'10 Scoring & Weights'!$C$8+('03 Feature Comparison'!I11="Unknown")*'10 Scoring & Weights'!$C$9+('03 Feature Comparison'!I11="No")*'10 Scoring & Weights'!$C$10) -> 1 | J59: =(('03 Feature Comparison'!I12="Yes")*'10 Scoring & Weights'!$C$7+('03 Feature Comparison'!I12="Conditional")*'10 Scoring & Weights'!$C$8+('03 Feature Comparison'!I12="Unknown")*'10 Scoring & Weights'!$C$9+('03 Feature Comparison'!I12="No")*'10 Scoring & Weights'!$C$10) -> 1 | K59: =(('03 Feature Comparison'!I13="Yes")*'10 Scoring & Weights'!$C$7+('03 Feature Comparison'!I13="Conditional")*'10 Scoring & Weights'!$C$8+('03 Feature Comparison'!I13="Unknown")*'10 Scoring & Weights'!$C$9+('03 Feature Comparison'!I13="No")*'10 Scoring & Weights'!$C$10) -> 0.25 | L59: =(('03 Feature Comparison'!I14="Yes")*'10 Scoring & Weights'!$C$7+('03 Feature Comparison'!I14="Conditional")*'10 Scoring & Weights'!$C$8+('03 Feature Comparison'!I14="Unknown")*'10 Scoring & Weights'!$C$9+('03 Feature Comparison'!I14="No")*'10 Scoring & Weights'!$C$10) -> 0.25 | M59: =(('03 Feature Comparison'!I15="Yes")*'10 Scoring & Weights'!$C$7+('03 Feature Comparison'!I15="Conditional")*'10 Scoring & Weights'!$C$8+('03 Feature Comparison'!I15="Unknown")*'10 Scoring & Weights'!$C$9+('03 Feature Comparison'!I15="No")*'10 Scoring & Weights'!$C$10) -> 1 | N59: =(('03 Feature Comparison'!I16="Yes")*'10 Scoring & Weights'!$C$7+('03 Feature Comparison'!I16="Conditional")*'10 Scoring & Weights'!$C$8+('03 Feature Comparison'!I16="Unknown")*'10 Scoring & Weights'!$C$9+('03 Feature Comparison'!I16="No")*'10 Scoring & Weights'!$C$10) -> 0.25 | O59: =(('03 Feature Comparison'!I17="Yes")*'10 Scoring & Weights'!$C$7+('03 Feature Comparison'!I17="Conditional")*'10 Scoring & Weights'!$C$8+('03 Feature Comparison'!I17="Unknown")*'10 Scoring & Weights'!$C$9+('03 Feature Comparison'!I17="No")*'10 Scoring & Weights'!$C$10) -> 0.25 | P59: =(('03 Feature Comparison'!I18="Yes")*'10 Scoring & Weights'!$C$7+('03 Feature Comparison'!I18="Conditional")*'10 Scoring & Weights'!$C$8+('03 Feature Comparison'!I18="Unknown")*'10 Scoring & Weights'!$C$9+('03 Feature Comparison'!I18="No")*'10 Scoring & Weights'!$C$10) -> 1
B60: F05 | C60: Blood pressure | D60: =(('03 Feature Comparison'!J6="Yes")*'10 Scoring & Weights'!$C$7+('03 Feature Comparison'!J6="Conditional")*'10 Scoring & Weights'!$C$8+('03 Feature Comparison'!J6="Unknown")*'10 Scoring & Weights'!$C$9+('03 Feature Comparison'!J6="No")*'10 Scoring & Weights'!$C$10) -> 0.25 | E60: =(('03 Feature Comparison'!J7="Yes")*'10 Scoring & Weights'!$C$7+('03 Feature Comparison'!J7="Conditional")*'10 Scoring & Weights'!$C$8+('03 Feature Comparison'!J7="Unknown")*'10 Scoring & Weights'!$C$9+('03 Feature Comparison'!J7="No")*'10 Scoring & Weights'!$C$10) -> 0.25 | F60: =(('03 Feature Comparison'!J8="Yes")*'10 Scoring & Weights'!$C$7+('03 Feature Comparison'!J8="Conditional")*'10 Scoring & Weights'!$C$8+('03 Feature Comparison'!J8="Unknown")*'10 Scoring & Weights'!$C$9+('03 Feature Comparison'!J8="No")*'10 Scoring & Weights'!$C$10) -> 0.25 | G60: =(('03 Feature Comparison'!J9="Yes")*'10 Scoring & Weights'!$C$7+('03 Feature Comparison'!J9="Conditional")*'10 Scoring & Weights'!$C$8+('03 Feature Comparison'!J9="Unknown")*'10 Scoring & Weights'!$C$9+('03 Feature Comparison'!J9="No")*'10 Scoring & Weights'!$C$10) -> 0.5 | H60: =(('03 Feature Comparison'!J10="Yes")*'10 Scoring & Weights'!$C$7+('03 Feature Comparison'!J10="Conditional")*'10 Scoring & Weights'!$C$8+('03 Feature Comparison'!J10="Unknown")*'10 Scoring & Weights'!$C$9+('03 Feature Comparison'!J10="No")*'10 Scoring & Weights'!$C$10) -> 0.5 | I60: =(('03 Feature Comparison'!J11="Yes")*'10 Scoring & Weights'!$C$7+('03 Feature Comparison'!J11="Conditional")*'10 Scoring & Weights'!$C$8+('03 Feature Comparison'!J11="Unknown")*'10 Scoring & Weights'!$C$9+('03 Feature Comparison'!J11="No")*'10 Scoring & Weights'!$C$10) -> 1 | J60: =(('03 Feature Comparison'!J12="Yes")*'10 Scoring & Weights'!$C$7+('03 Feature Comparison'!J12="Conditional")*'10 Scoring & Weights'!$C$8+('03 Feature Comparison'!J12="Unknown")*'10 Scoring & Weights'!$C$9+('03 Feature Comparison'!J12="No")*'10 Scoring & Weights'!$C$10) -> 1 | K60: =(('03 Feature Comparison'!J13="Yes")*'10 Scoring & Weights'!$C$7+('03 Feature Comparison'!J13="Conditional")*'10 Scoring & Weights'!$C$8+('03 Feature Comparison'!J13="Unknown")*'10 Scoring & Weights'!$C$9+('03 Feature Comparison'!J13="No")*'10 Scoring & Weights'!$C$10) -> 0.25 | L60: =(('03 Feature Comparison'!J14="Yes")*'10 Scoring & Weights'!$C$7+('03 Feature Comparison'!J14="Conditional")*'10 Scoring & Weights'!$C$8+('03 Feature Comparison'!J14="Unknown")*'10 Scoring & Weights'!$C$9+('03 Feature Comparison'!J14="No")*'10 Scoring & Weights'!$C$10) -> 1 | M60: =(('03 Feature Comparison'!J15="Yes")*'10 Scoring & Weights'!$C$7+('03 Feature Comparison'!J15="Conditional")*'10 Scoring & Weights'!$C$8+('03 Feature Comparison'!J15="Unknown")*'10 Scoring & Weights'!$C$9+('03 Feature Comparison'!J15="No")*'10 Scoring & Weights'!$C$10) -> 0.5 | N60: =(('03 Feature Comparison'!J16="Yes")*'10 Scoring & Weights'!$C$7+('03 Feature Comparison'!J16="Conditional")*'10 Scoring & Weights'!$C$8+('03 Feature Comparison'!J16="Unknown")*'10 Scoring & Weights'!$C$9+('03 Feature Comparison'!J16="No")*'10 Scoring & Weights'!$C$10) -> 0.25 | O60: =(('03 Feature Comparison'!J17="Yes")*'10 Scoring & Weights'!$C$7+('03 Feature Comparison'!J17="Conditional")*'10 Scoring & Weights'!$C$8+('03 Feature Comparison'!J17="Unknown")*'10 Scoring & Weights'!$C$9+('03 Feature Comparison'!J17="No")*'10 Scoring & Weights'!$C$10) -> 0.5 | P60: =(('03 Feature Comparison'!J18="Yes")*'10 Scoring & Weights'!$C$7+('03 Feature Comparison'!J18="Conditional")*'10 Scoring & Weights'!$C$8+('03 Feature Comparison'!J18="Unknown")*'10 Scoring & Weights'!$C$9+('03 Feature Comparison'!J18="No")*'10 Scoring & Weights'!$C$10) -> 0.5
B61: F06 | C61: Body / skin temperature | D61: =(('03 Feature Comparison'!K6="Yes")*'10 Scoring & Weights'!$C$7+('03 Feature Comparison'!K6="Conditional")*'10 Scoring & Weights'!$C$8+('03 Feature Comparison'!K6="Unknown")*'10 Scoring & Weights'!$C$9+('03 Feature Comparison'!K6="No")*'10 Scoring & Weights'!$C$10) -> 1 | E61: =(('03 Feature Comparison'!K7="Yes")*'10 Scoring & Weights'!$C$7+('03 Feature Comparison'!K7="Conditional")*'10 Scoring & Weights'!$C$8+('03 Feature Comparison'!K7="Unknown")*'10 Scoring & Weights'!$C$9+('03 Feature Comparison'!K7="No")*'10 Scoring & Weights'!$C$10) -> 0.25 | F61: =(('03 Feature Comparison'!K8="Yes")*'10 Scoring & Weights'!$C$7+('03 Feature Comparison'!K8="Conditional")*'10 Scoring & Weights'!$C$8+('03 Feature Comparison'!K8="Unknown")*'10 Scoring & Weights'!$C$9+('03 Feature Comparison'!K8="No")*'10 Scoring & Weights'!$C$10) -> 0.25 | G61: =(('03 Feature Comparison'!K9="Yes")*'10 Scoring & Weights'!$C$7+('03 Feature Comparison'!K9="Conditional")*'10 Scoring & Weights'!$C$8+('03 Feature Comparison'!K9="Unknown")*'10 Scoring & Weights'!$C$9+('03 Feature Comparison'!K9="No")*'10 Scoring & Weights'!$C$10) -> 1 | H61: =(('03 Feature Comparison'!K10="Yes")*'10 Scoring & Weights'!$C$7+('03 Feature Comparison'!K10="Conditional")*'10 Scoring & Weights'!$C$8+('03 Feature Comparison'!K10="Unknown")*'10 Scoring & Weights'!$C$9+('03 Feature Comparison'!K10="No")*'10 Scoring & Weights'!$C$10) -> 1 | I61: =(('03 Feature Comparison'!K11="Yes")*'10 Scoring & Weights'!$C$7+('03 Feature Comparison'!K11="Conditional")*'10 Scoring & Weights'!$C$8+('03 Feature Comparison'!K11="Unknown")*'10 Scoring & Weights'!$C$9+('03 Feature Comparison'!K11="No")*'10 Scoring & Weights'!$C$10) -> 0.25 | J61: =(('03 Feature Comparison'!K12="Yes")*'10 Scoring & Weights'!$C$7+('03 Feature Comparison'!K12="Conditional")*'10 Scoring & Weights'!$C$8+('03 Feature Comparison'!K12="Unknown")*'10 Scoring & Weights'!$C$9+('03 Feature Comparison'!K12="No")*'10 Scoring & Weights'!$C$10) -> 0.25 | K61: =(('03 Feature Comparison'!K13="Yes")*'10 Scoring & Weights'!$C$7+('03 Feature Comparison'!K13="Conditional")*'10 Scoring & Weights'!$C$8+('03 Feature Comparison'!K13="Unknown")*'10 Scoring & Weights'!$C$9+('03 Feature Comparison'!K13="No")*'10 Scoring & Weights'!$C$10) -> 0.25 | L61: =(('03 Feature Comparison'!K14="Yes")*'10 Scoring & Weights'!$C$7+('03 Feature Comparison'!K14="Conditional")*'10 Scoring & Weights'!$C$8+('03 Feature Comparison'!K14="Unknown")*'10 Scoring & Weights'!$C$9+('03 Feature Comparison'!K14="No")*'10 Scoring & Weights'!$C$10) -> 0.25 | M61: =(('03 Feature Comparison'!K15="Yes")*'10 Scoring & Weights'!$C$7+('03 Feature Comparison'!K15="Conditional")*'10 Scoring & Weights'!$C$8+('03 Feature Comparison'!K15="Unknown")*'10 Scoring & Weights'!$C$9+('03 Feature Comparison'!K15="No")*'10 Scoring & Weights'!$C$10) -> 0.25 | N61: =(('03 Feature Comparison'!K16="Yes")*'10 Scoring & Weights'!$C$7+('03 Feature Comparison'!K16="Conditional")*'10 Scoring & Weights'!$C$8+('03 Feature Comparison'!K16="Unknown")*'10 Scoring & Weights'!$C$9+('03 Feature Comparison'!K16="No")*'10 Scoring & Weights'!$C$10) -> 1 | O61: =(('03 Feature Comparison'!K17="Yes")*'10 Scoring & Weights'!$C$7+('03 Feature Comparison'!K17="Conditional")*'10 Scoring & Weights'!$C$8+('03 Feature Comparison'!K17="Unknown")*'10 Scoring & Weights'!$C$9+('03 Feature Comparison'!K17="No")*'10 Scoring & Weights'!$C$10) -> 0.25 | P61: =(('03 Feature Comparison'!K18="Yes")*'10 Scoring & Weights'!$C$7+('03 Feature Comparison'!K18="Conditional")*'10 Scoring & Weights'!$C$8+('03 Feature Comparison'!K18="Unknown")*'10 Scoring & Weights'!$C$9+('03 Feature Comparison'!K18="No")*'10 Scoring & Weights'!$C$10) -> 1
B62: F07 | C62: Sleep monitoring | D62: =(('03 Feature Comparison'!L6="Yes")*'10 Scoring & Weights'!$C$7+('03 Feature Comparison'!L6="Conditional")*'10 Scoring & Weights'!$C$8+('03 Feature Comparison'!L6="Unknown")*'10 Scoring & Weights'!$C$9+('03 Feature Comparison'!L6="No")*'10 Scoring & Weights'!$C$10) -> 1 | E62: =(('03 Feature Comparison'!L7="Yes")*'10 Scoring & Weights'!$C$7+('03 Feature Comparison'!L7="Conditional")*'10 Scoring & Weights'!$C$8+('03 Feature Comparison'!L7="Unknown")*'10 Scoring & Weights'!$C$9+('03 Feature Comparison'!L7="No")*'10 Scoring & Weights'!$C$10) -> 0.25 | F62: =(('03 Feature Comparison'!L8="Yes")*'10 Scoring & Weights'!$C$7+('03 Feature Comparison'!L8="Conditional")*'10 Scoring & Weights'!$C$8+('03 Feature Comparison'!L8="Unknown")*'10 Scoring & Weights'!$C$9+('03 Feature Comparison'!L8="No")*'10 Scoring & Weights'!$C$10) -> 0.25 | G62: =(('03 Feature Comparison'!L9="Yes")*'10 Scoring & Weights'!$C$7+('03 Feature Comparison'!L9="Conditional")*'10 Scoring & Weights'!$C$8+('03 Feature Comparison'!L9="Unknown")*'10 Scoring & Weights'!$C$9+('03 Feature Comparison'!L9="No")*'10 Scoring & Weights'!$C$10) -> 1 | H62: =(('03 Feature Comparison'!L10="Yes")*'10 Scoring & Weights'!$C$7+('03 Feature Comparison'!L10="Conditional")*'10 Scoring & Weights'!$C$8+('03 Feature Comparison'!L10="Unknown")*'10 Scoring & Weights'!$C$9+('03 Feature Comparison'!L10="No")*'10 Scoring & Weights'!$C$10) -> 1 | I62: =(('03 Feature Comparison'!L11="Yes")*'10 Scoring & Weights'!$C$7+('03 Feature Comparison'!L11="Conditional")*'10 Scoring & Weights'!$C$8+('03 Feature Comparison'!L11="Unknown")*'10 Scoring & Weights'!$C$9+('03 Feature Comparison'!L11="No")*'10 Scoring & Weights'!$C$10) -> 1 | J62: =(('03 Feature Comparison'!L12="Yes")*'10 Scoring & Weights'!$C$7+('03 Feature Comparison'!L12="Conditional")*'10 Scoring & Weights'!$C$8+('03 Feature Comparison'!L12="Unknown")*'10 Scoring & Weights'!$C$9+('03 Feature Comparison'!L12="No")*'10 Scoring & Weights'!$C$10) -> 1 | K62: =(('03 Feature Comparison'!L13="Yes")*'10 Scoring & Weights'!$C$7+('03 Feature Comparison'!L13="Conditional")*'10 Scoring & Weights'!$C$8+('03 Feature Comparison'!L13="Unknown")*'10 Scoring & Weights'!$C$9+('03 Feature Comparison'!L13="No")*'10 Scoring & Weights'!$C$10) -> 0.25 | L62: =(('03 Feature Comparison'!L14="Yes")*'10 Scoring & Weights'!$C$7+('03 Feature Comparison'!L14="Conditional")*'10 Scoring & Weights'!$C$8+('03 Feature Comparison'!L14="Unknown")*'10 Scoring & Weights'!$C$9+('03 Feature Comparison'!L14="No")*'10 Scoring & Weights'!$C$10) -> 0.25 | M62: =(('03 Feature Comparison'!L15="Yes")*'10 Scoring & Weights'!$C$7+('03 Feature Comparison'!L15="Conditional")*'10 Scoring & Weights'!$C$8+('03 Feature Comparison'!L15="Unknown")*'10 Scoring & Weights'!$C$9+('03 Feature Comparison'!L15="No")*'10 Scoring & Weights'!$C$10) -> 1 | N62: =(('03 Feature Comparison'!L16="Yes")*'10 Scoring & Weights'!$C$7+('03 Feature Comparison'!L16="Conditional")*'10 Scoring & Weights'!$C$8+('03 Feature Comparison'!L16="Unknown")*'10 Scoring & Weights'!$C$9+('03 Feature Comparison'!L16="No")*'10 Scoring & Weights'!$C$10) -> 1 | O62: =(('03 Feature Comparison'!L17="Yes")*'10 Scoring & Weights'!$C$7+('03 Feature Comparison'!L17="Conditional")*'10 Scoring & Weights'!$C$8+('03 Feature Comparison'!L17="Unknown")*'10 Scoring & Weights'!$C$9+('03 Feature Comparison'!L17="No")*'10 Scoring & Weights'!$C$10) -> 0.25 | P62: =(('03 Feature Comparison'!L18="Yes")*'10 Scoring & Weights'!$C$7+('03 Feature Comparison'!L18="Conditional")*'10 Scoring & Weights'!$C$8+('03 Feature Comparison'!L18="Unknown")*'10 Scoring & Weights'!$C$9+('03 Feature Comparison'!L18="No")*'10 Scoring & Weights'!$C$10) -> 0.25
B63: F08 | C63: Steps & activity | D63: =(('03 Feature Comparison'!M6="Yes")*'10 Scoring & Weights'!$C$7+('03 Feature Comparison'!M6="Conditional")*'10 Scoring & Weights'!$C$8+('03 Feature Comparison'!M6="Unknown")*'10 Scoring & Weights'!$C$9+('03 Feature Comparison'!M6="No")*'10 Scoring & Weights'!$C$10) -> 1 | E63: =(('03 Feature Comparison'!M7="Yes")*'10 Scoring & Weights'!$C$7+('03 Feature Comparison'!M7="Conditional")*'10 Scoring & Weights'!$C$8+('03 Feature Comparison'!M7="Unknown")*'10 Scoring & Weights'!$C$9+('03 Feature Comparison'!M7="No")*'10 Scoring & Weights'!$C$10) -> 0.25 | F63: =(('03 Feature Comparison'!M8="Yes")*'10 Scoring & Weights'!$C$7+('03 Feature Comparison'!M8="Conditional")*'10 Scoring & Weights'!$C$8+('03 Feature Comparison'!M8="Unknown")*'10 Scoring & Weights'!$C$9+('03 Feature Comparison'!M8="No")*'10 Scoring & Weights'!$C$10) -> 0.25 | G63: =(('03 Feature Comparison'!M9="Yes")*'10 Scoring & Weights'!$C$7+('03 Feature Comparison'!M9="Conditional")*'10 Scoring & Weights'!$C$8+('03 Feature Comparison'!M9="Unknown")*'10 Scoring & Weights'!$C$9+('03 Feature Comparison'!M9="No")*'10 Scoring & Weights'!$C$10) -> 1 | H63: =(('03 Feature Comparison'!M10="Yes")*'10 Scoring & Weights'!$C$7+('03 Feature Comparison'!M10="Conditional")*'10 Scoring & Weights'!$C$8+('03 Feature Comparison'!M10="Unknown")*'10 Scoring & Weights'!$C$9+('03 Feature Comparison'!M10="No")*'10 Scoring & Weights'!$C$10) -> 1 | I63: =(('03 Feature Comparison'!M11="Yes")*'10 Scoring & Weights'!$C$7+('03 Feature Comparison'!M11="Conditional")*'10 Scoring & Weights'!$C$8+('03 Feature Comparison'!M11="Unknown")*'10 Scoring & Weights'!$C$9+('03 Feature Comparison'!M11="No")*'10 Scoring & Weights'!$C$10) -> 1 | J63: =(('03 Feature Comparison'!M12="Yes")*'10 Scoring & Weights'!$C$7+('03 Feature Comparison'!M12="Conditional")*'10 Scoring & Weights'!$C$8+('03 Feature Comparison'!M12="Unknown")*'10 Scoring & Weights'!$C$9+('03 Feature Comparison'!M12="No")*'10 Scoring & Weights'!$C$10) -> 1 | K63: =(('03 Feature Comparison'!M13="Yes")*'10 Scoring & Weights'!$C$7+('03 Feature Comparison'!M13="Conditional")*'10 Scoring & Weights'!$C$8+('03 Feature Comparison'!M13="Unknown")*'10 Scoring & Weights'!$C$9+('03 Feature Comparison'!M13="No")*'10 Scoring & Weights'!$C$10) -> 0.25 | L63: =(('03 Feature Comparison'!M14="Yes")*'10 Scoring & Weights'!$C$7+('03 Feature Comparison'!M14="Conditional")*'10 Scoring & Weights'!$C$8+('03 Feature Comparison'!M14="Unknown")*'10 Scoring & Weights'!$C$9+('03 Feature Comparison'!M14="No")*'10 Scoring & Weights'!$C$10) -> 0.25 | M63: =(('03 Feature Comparison'!M15="Yes")*'10 Scoring & Weights'!$C$7+('03 Feature Comparison'!M15="Conditional")*'10 Scoring & Weights'!$C$8+('03 Feature Comparison'!M15="Unknown")*'10 Scoring & Weights'!$C$9+('03 Feature Comparison'!M15="No")*'10 Scoring & Weights'!$C$10) -> 0.25 | N63: =(('03 Feature Comparison'!M16="Yes")*'10 Scoring & Weights'!$C$7+('03 Feature Comparison'!M16="Conditional")*'10 Scoring & Weights'!$C$8+('03 Feature Comparison'!M16="Unknown")*'10 Scoring & Weights'!$C$9+('03 Feature Comparison'!M16="No")*'10 Scoring & Weights'!$C$10) -> 0.25 | O63: =(('03 Feature Comparison'!M17="Yes")*'10 Scoring & Weights'!$C$7+('03 Feature Comparison'!M17="Conditional")*'10 Scoring & Weights'!$C$8+('03 Feature Comparison'!M17="Unknown")*'10 Scoring & Weights'!$C$9+('03 Feature Comparison'!M17="No")*'10 Scoring & Weights'!$C$10) -> 1 | P63: =(('03 Feature Comparison'!M18="Yes")*'10 Scoring & Weights'!$C$7+('03 Feature Comparison'!M18="Conditional")*'10 Scoring & Weights'!$C$8+('03 Feature Comparison'!M18="Unknown")*'10 Scoring & Weights'!$C$9+('03 Feature Comparison'!M18="No")*'10 Scoring & Weights'!$C$10) -> 0.25
B64: F09 | C64: Stress indicator | D64: =(('03 Feature Comparison'!N6="Yes")*'10 Scoring & Weights'!$C$7+('03 Feature Comparison'!N6="Conditional")*'10 Scoring & Weights'!$C$8+('03 Feature Comparison'!N6="Unknown")*'10 Scoring & Weights'!$C$9+('03 Feature Comparison'!N6="No")*'10 Scoring & Weights'!$C$10) -> 1 | E64: =(('03 Feature Comparison'!N7="Yes")*'10 Scoring & Weights'!$C$7+('03 Feature Comparison'!N7="Conditional")*'10 Scoring & Weights'!$C$8+('03 Feature Comparison'!N7="Unknown")*'10 Scoring & Weights'!$C$9+('03 Feature Comparison'!N7="No")*'10 Scoring & Weights'!$C$10) -> 0.25 | F64: =(('03 Feature Comparison'!N8="Yes")*'10 Scoring & Weights'!$C$7+('03 Feature Comparison'!N8="Conditional")*'10 Scoring & Weights'!$C$8+('03 Feature Comparison'!N8="Unknown")*'10 Scoring & Weights'!$C$9+('03 Feature Comparison'!N8="No")*'10 Scoring & Weights'!$C$10) -> 0.25 | G64: =(('03 Feature Comparison'!N9="Yes")*'10 Scoring & Weights'!$C$7+('03 Feature Comparison'!N9="Conditional")*'10 Scoring & Weights'!$C$8+('03 Feature Comparison'!N9="Unknown")*'10 Scoring & Weights'!$C$9+('03 Feature Comparison'!N9="No")*'10 Scoring & Weights'!$C$10) -> 1 | H64: =(('03 Feature Comparison'!N10="Yes")*'10 Scoring & Weights'!$C$7+('03 Feature Comparison'!N10="Conditional")*'10 Scoring & Weights'!$C$8+('03 Feature Comparison'!N10="Unknown")*'10 Scoring & Weights'!$C$9+('03 Feature Comparison'!N10="No")*'10 Scoring & Weights'!$C$10) -> 1 | I64: =(('03 Feature Comparison'!N11="Yes")*'10 Scoring & Weights'!$C$7+('03 Feature Comparison'!N11="Conditional")*'10 Scoring & Weights'!$C$8+('03 Feature Comparison'!N11="Unknown")*'10 Scoring & Weights'!$C$9+('03 Feature Comparison'!N11="No")*'10 Scoring & Weights'!$C$10) -> 1 | J64: =(('03 Feature Comparison'!N12="Yes")*'10 Scoring & Weights'!$C$7+('03 Feature Comparison'!N12="Conditional")*'10 Scoring & Weights'!$C$8+('03 Feature Comparison'!N12="Unknown")*'10 Scoring & Weights'!$C$9+('03 Feature Comparison'!N12="No")*'10 Scoring & Weights'!$C$10) -> 0.25 | K64: =(('03 Feature Comparison'!N13="Yes")*'10 Scoring & Weights'!$C$7+('03 Feature Comparison'!N13="Conditional")*'10 Scoring & Weights'!$C$8+('03 Feature Comparison'!N13="Unknown")*'10 Scoring & Weights'!$C$9+('03 Feature Comparison'!N13="No")*'10 Scoring & Weights'!$C$10) -> 0.25 | L64: =(('03 Feature Comparison'!N14="Yes")*'10 Scoring & Weights'!$C$7+('03 Feature Comparison'!N14="Conditional")*'10 Scoring & Weights'!$C$8+('03 Feature Comparison'!N14="Unknown")*'10 Scoring & Weights'!$C$9+('03 Feature Comparison'!N14="No")*'10 Scoring & Weights'!$C$10) -> 0.25 | M64: =(('03 Feature Comparison'!N15="Yes")*'10 Scoring & Weights'!$C$7+('03 Feature Comparison'!N15="Conditional")*'10 Scoring & Weights'!$C$8+('03 Feature Comparison'!N15="Unknown")*'10 Scoring & Weights'!$C$9+('03 Feature Comparison'!N15="No")*'10 Scoring & Weights'!$C$10) -> 0.25 | N64: =(('03 Feature Comparison'!N16="Yes")*'10 Scoring & Weights'!$C$7+('03 Feature Comparison'!N16="Conditional")*'10 Scoring & Weights'!$C$8+('03 Feature Comparison'!N16="Unknown")*'10 Scoring & Weights'!$C$9+('03 Feature Comparison'!N16="No")*'10 Scoring & Weights'!$C$10) -> 0.25 | O64: =(('03 Feature Comparison'!N17="Yes")*'10 Scoring & Weights'!$C$7+('03 Feature Comparison'!N17="Conditional")*'10 Scoring & Weights'!$C$8+('03 Feature Comparison'!N17="Unknown")*'10 Scoring & Weights'!$C$9+('03 Feature Comparison'!N17="No")*'10 Scoring & Weights'!$C$10) -> 0.25 | P64: =(('03 Feature Comparison'!N18="Yes")*'10 Scoring & Weights'!$C$7+('03 Feature Comparison'!N18="Conditional")*'10 Scoring & Weights'!$C$8+('03 Feature Comparison'!N18="Unknown")*'10 Scoring & Weights'!$C$9+('03 Feature Comparison'!N18="No")*'10 Scoring & Weights'!$C$10) -> 0.25
B65: F10 | C65: Automatic fall detection | D65: =(('03 Feature Comparison'!O6="Yes")*'10 Scoring & Weights'!$C$7+('03 Feature Comparison'!O6="Conditional")*'10 Scoring & Weights'!$C$8+('03 Feature Comparison'!O6="Unknown")*'10 Scoring & Weights'!$C$9+('03 Feature Comparison'!O6="No")*'10 Scoring & Weights'!$C$10) -> 0.25 | E65: =(('03 Feature Comparison'!O7="Yes")*'10 Scoring & Weights'!$C$7+('03 Feature Comparison'!O7="Conditional")*'10 Scoring & Weights'!$C$8+('03 Feature Comparison'!O7="Unknown")*'10 Scoring & Weights'!$C$9+('03 Feature Comparison'!O7="No")*'10 Scoring & Weights'!$C$10) -> 1 | F65: =(('03 Feature Comparison'!O8="Yes")*'10 Scoring & Weights'!$C$7+('03 Feature Comparison'!O8="Conditional")*'10 Scoring & Weights'!$C$8+('03 Feature Comparison'!O8="Unknown")*'10 Scoring & Weights'!$C$9+('03 Feature Comparison'!O8="No")*'10 Scoring & Weights'!$C$10) -> 1 | G65: =(('03 Feature Comparison'!O9="Yes")*'10 Scoring & Weights'!$C$7+('03 Feature Comparison'!O9="Conditional")*'10 Scoring & Weights'!$C$8+('03 Feature Comparison'!O9="Unknown")*'10 Scoring & Weights'!$C$9+('03 Feature Comparison'!O9="No")*'10 Scoring & Weights'!$C$10) -> 0.25 | H65: =(('03 Feature Comparison'!O10="Yes")*'10 Scoring & Weights'!$C$7+('03 Feature Comparison'!O10="Conditional")*'10 Scoring & Weights'!$C$8+('03 Feature Comparison'!O10="Unknown")*'10 Scoring & Weights'!$C$9+('03 Feature Comparison'!O10="No")*'10 Scoring & Weights'!$C$10) -> 0.25 | I65: =(('03 Feature Comparison'!O11="Yes")*'10 Scoring & Weights'!$C$7+('03 Feature Comparison'!O11="Conditional")*'10 Scoring & Weights'!$C$8+('03 Feature Comparison'!O11="Unknown")*'10 Scoring & Weights'!$C$9+('03 Feature Comparison'!O11="No")*'10 Scoring & Weights'!$C$10) -> 0.25 | J65: =(('03 Feature Comparison'!O12="Yes")*'10 Scoring & Weights'!$C$7+('03 Feature Comparison'!O12="Conditional")*'10 Scoring & Weights'!$C$8+('03 Feature Comparison'!O12="Unknown")*'10 Scoring & Weights'!$C$9+('03 Feature Comparison'!O12="No")*'10 Scoring & Weights'!$C$10) -> 1 | K65: =(('03 Feature Comparison'!O13="Yes")*'10 Scoring & Weights'!$C$7+('03 Feature Comparison'!O13="Conditional")*'10 Scoring & Weights'!$C$8+('03 Feature Comparison'!O13="Unknown")*'10 Scoring & Weights'!$C$9+('03 Feature Comparison'!O13="No")*'10 Scoring & Weights'!$C$10) -> 0.25 | L65: =(('03 Feature Comparison'!O14="Yes")*'10 Scoring & Weights'!$C$7+('03 Feature Comparison'!O14="Conditional")*'10 Scoring & Weights'!$C$8+('03 Feature Comparison'!O14="Unknown")*'10 Scoring & Weights'!$C$9+('03 Feature Comparison'!O14="No")*'10 Scoring & Weights'!$C$10) -> 1 | M65: =(('03 Feature Comparison'!O15="Yes")*'10 Scoring & Weights'!$C$7+('03 Feature Comparison'!O15="Conditional")*'10 Scoring & Weights'!$C$8+('03 Feature Comparison'!O15="Unknown")*'10 Scoring & Weights'!$C$9+('03 Feature Comparison'!O15="No")*'10 Scoring & Weights'!$C$10) -> 1 | N65: =(('03 Feature Comparison'!O16="Yes")*'10 Scoring & Weights'!$C$7+('03 Feature Comparison'!O16="Conditional")*'10 Scoring & Weights'!$C$8+('03 Feature Comparison'!O16="Unknown")*'10 Scoring & Weights'!$C$9+('03 Feature Comparison'!O16="No")*'10 Scoring & Weights'!$C$10) -> 1 | O65: =(('03 Feature Comparison'!O17="Yes")*'10 Scoring & Weights'!$C$7+('03 Feature Comparison'!O17="Conditional")*'10 Scoring & Weights'!$C$8+('03 Feature Comparison'!O17="Unknown")*'10 Scoring & Weights'!$C$9+('03 Feature Comparison'!O17="No")*'10 Scoring & Weights'!$C$10) -> 0.25 | P65: =(('03 Feature Comparison'!O18="Yes")*'10 Scoring & Weights'!$C$7+('03 Feature Comparison'!O18="Conditional")*'10 Scoring & Weights'!$C$8+('03 Feature Comparison'!O18="Unknown")*'10 Scoring & Weights'!$C$9+('03 Feature Comparison'!O18="No")*'10 Scoring & Weights'!$C$10) -> 0.25
B66: F11 | C66: SOS button | D66: =(('03 Feature Comparison'!P6="Yes")*'10 Scoring & Weights'!$C$7+('03 Feature Comparison'!P6="Conditional")*'10 Scoring & Weights'!$C$8+('03 Feature Comparison'!P6="Unknown")*'10 Scoring & Weights'!$C$9+('03 Feature Comparison'!P6="No")*'10 Scoring & Weights'!$C$10) -> 0.25 | E66: =(('03 Feature Comparison'!P7="Yes")*'10 Scoring & Weights'!$C$7+('03 Feature Comparison'!P7="Conditional")*'10 Scoring & Weights'!$C$8+('03 Feature Comparison'!P7="Unknown")*'10 Scoring & Weights'!$C$9+('03 Feature Comparison'!P7="No")*'10 Scoring & Weights'!$C$10) -> 0.25 | F66: =(('03 Feature Comparison'!P8="Yes")*'10 Scoring & Weights'!$C$7+('03 Feature Comparison'!P8="Conditional")*'10 Scoring & Weights'!$C$8+('03 Feature Comparison'!P8="Unknown")*'10 Scoring & Weights'!$C$9+('03 Feature Comparison'!P8="No")*'10 Scoring & Weights'!$C$10) -> 1 | G66: =(('03 Feature Comparison'!P9="Yes")*'10 Scoring & Weights'!$C$7+('03 Feature Comparison'!P9="Conditional")*'10 Scoring & Weights'!$C$8+('03 Feature Comparison'!P9="Unknown")*'10 Scoring & Weights'!$C$9+('03 Feature Comparison'!P9="No")*'10 Scoring & Weights'!$C$10) -> 0.25 | H66: =(('03 Feature Comparison'!P10="Yes")*'10 Scoring & Weights'!$C$7+('03 Feature Comparison'!P10="Conditional")*'10 Scoring & Weights'!$C$8+('03 Feature Comparison'!P10="Unknown")*'10 Scoring & Weights'!$C$9+('03 Feature Comparison'!P10="No")*'10 Scoring & Weights'!$C$10) -> 0.25 | I66: =(('03 Feature Comparison'!P11="Yes")*'10 Scoring & Weights'!$C$7+('03 Feature Comparison'!P11="Conditional")*'10 Scoring & Weights'!$C$8+('03 Feature Comparison'!P11="Unknown")*'10 Scoring & Weights'!$C$9+('03 Feature Comparison'!P11="No")*'10 Scoring & Weights'!$C$10) -> 0.25 | J66: =(('03 Feature Comparison'!P12="Yes")*'10 Scoring & Weights'!$C$7+('03 Feature Comparison'!P12="Conditional")*'10 Scoring & Weights'!$C$8+('03 Feature Comparison'!P12="Unknown")*'10 Scoring & Weights'!$C$9+('03 Feature Comparison'!P12="No")*'10 Scoring & Weights'!$C$10) -> 1 | K66: =(('03 Feature Comparison'!P13="Yes")*'10 Scoring & Weights'!$C$7+('03 Feature Comparison'!P13="Conditional")*'10 Scoring & Weights'!$C$8+('03 Feature Comparison'!P13="Unknown")*'10 Scoring & Weights'!$C$9+('03 Feature Comparison'!P13="No")*'10 Scoring & Weights'!$C$10) -> 0.25 | L66: =(('03 Feature Comparison'!P14="Yes")*'10 Scoring & Weights'!$C$7+('03 Feature Comparison'!P14="Conditional")*'10 Scoring & Weights'!$C$8+('03 Feature Comparison'!P14="Unknown")*'10 Scoring & Weights'!$C$9+('03 Feature Comparison'!P14="No")*'10 Scoring & Weights'!$C$10) -> 1 | M66: =(('03 Feature Comparison'!P15="Yes")*'10 Scoring & Weights'!$C$7+('03 Feature Comparison'!P15="Conditional")*'10 Scoring & Weights'!$C$8+('03 Feature Comparison'!P15="Unknown")*'10 Scoring & Weights'!$C$9+('03 Feature Comparison'!P15="No")*'10 Scoring & Weights'!$C$10) -> 1 | N66: =(('03 Feature Comparison'!P16="Yes")*'10 Scoring & Weights'!$C$7+('03 Feature Comparison'!P16="Conditional")*'10 Scoring & Weights'!$C$8+('03 Feature Comparison'!P16="Unknown")*'10 Scoring & Weights'!$C$9+('03 Feature Comparison'!P16="No")*'10 Scoring & Weights'!$C$10) -> 1 | O66: =(('03 Feature Comparison'!P17="Yes")*'10 Scoring & Weights'!$C$7+('03 Feature Comparison'!P17="Conditional")*'10 Scoring & Weights'!$C$8+('03 Feature Comparison'!P17="Unknown")*'10 Scoring & Weights'!$C$9+('03 Feature Comparison'!P17="No")*'10 Scoring & Weights'!$C$10) -> 1 | P66: =(('03 Feature Comparison'!P18="Yes")*'10 Scoring & Weights'!$C$7+('03 Feature Comparison'!P18="Conditional")*'10 Scoring & Weights'!$C$8+('03 Feature Comparison'!P18="Unknown")*'10 Scoring & Weights'!$C$9+('03 Feature Comparison'!P18="No")*'10 Scoring & Weights'!$C$10) -> 1
B67: F12 | C67: Two-way voice calling | D67: =(('03 Feature Comparison'!Q6="Yes")*'10 Scoring & Weights'!$C$7+('03 Feature Comparison'!Q6="Conditional")*'10 Scoring & Weights'!$C$8+('03 Feature Comparison'!Q6="Unknown")*'10 Scoring & Weights'!$C$9+('03 Feature Comparison'!Q6="No")*'10 Scoring & Weights'!$C$10) -> 0.25 | E67: =(('03 Feature Comparison'!Q7="Yes")*'10 Scoring & Weights'!$C$7+('03 Feature Comparison'!Q7="Conditional")*'10 Scoring & Weights'!$C$8+('03 Feature Comparison'!Q7="Unknown")*'10 Scoring & Weights'!$C$9+('03 Feature Comparison'!Q7="No")*'10 Scoring & Weights'!$C$10) -> 0.25 | F67: =(('03 Feature Comparison'!Q8="Yes")*'10 Scoring & Weights'!$C$7+('03 Feature Comparison'!Q8="Conditional")*'10 Scoring & Weights'!$C$8+('03 Feature Comparison'!Q8="Unknown")*'10 Scoring & Weights'!$C$9+('03 Feature Comparison'!Q8="No")*'10 Scoring & Weights'!$C$10) -> 0.5 | G67: =(('03 Feature Comparison'!Q9="Yes")*'10 Scoring & Weights'!$C$7+('03 Feature Comparison'!Q9="Conditional")*'10 Scoring & Weights'!$C$8+('03 Feature Comparison'!Q9="Unknown")*'10 Scoring & Weights'!$C$9+('03 Feature Comparison'!Q9="No")*'10 Scoring & Weights'!$C$10) -> 0.25 | H67: =(('03 Feature Comparison'!Q10="Yes")*'10 Scoring & Weights'!$C$7+('03 Feature Comparison'!Q10="Conditional")*'10 Scoring & Weights'!$C$8+('03 Feature Comparison'!Q10="Unknown")*'10 Scoring & Weights'!$C$9+('03 Feature Comparison'!Q10="No")*'10 Scoring & Weights'!$C$10) -> 0.25 | I67: =(('03 Feature Comparison'!Q11="Yes")*'10 Scoring & Weights'!$C$7+('03 Feature Comparison'!Q11="Conditional")*'10 Scoring & Weights'!$C$8+('03 Feature Comparison'!Q11="Unknown")*'10 Scoring & Weights'!$C$9+('03 Feature Comparison'!Q11="No")*'10 Scoring & Weights'!$C$10) -> 0.25 | J67: =(('03 Feature Comparison'!Q12="Yes")*'10 Scoring & Weights'!$C$7+('03 Feature Comparison'!Q12="Conditional")*'10 Scoring & Weights'!$C$8+('03 Feature Comparison'!Q12="Unknown")*'10 Scoring & Weights'!$C$9+('03 Feature Comparison'!Q12="No")*'10 Scoring & Weights'!$C$10) -> 1 | K67: =(('03 Feature Comparison'!Q13="Yes")*'10 Scoring & Weights'!$C$7+('03 Feature Comparison'!Q13="Conditional")*'10 Scoring & Weights'!$C$8+('03 Feature Comparison'!Q13="Unknown")*'10 Scoring & Weights'!$C$9+('03 Feature Comparison'!Q13="No")*'10 Scoring & Weights'!$C$10) -> 0.25 | L67: =(('03 Feature Comparison'!Q14="Yes")*'10 Scoring & Weights'!$C$7+('03 Feature Comparison'!Q14="Conditional")*'10 Scoring & Weights'!$C$8+('03 Feature Comparison'!Q14="Unknown")*'10 Scoring & Weights'!$C$9+('03 Feature Comparison'!Q14="No")*'10 Scoring & Weights'!$C$10) -> 1 | M67: =(('03 Feature Comparison'!Q15="Yes")*'10 Scoring & Weights'!$C$7+('03 Feature Comparison'!Q15="Conditional")*'10 Scoring & Weights'!$C$8+('03 Feature Comparison'!Q15="Unknown")*'10 Scoring & Weights'!$C$9+('03 Feature Comparison'!Q15="No")*'10 Scoring & Weights'!$C$10) -> 1 | N67: =(('03 Feature Comparison'!Q16="Yes")*'10 Scoring & Weights'!$C$7+('03 Feature Comparison'!Q16="Conditional")*'10 Scoring & Weights'!$C$8+('03 Feature Comparison'!Q16="Unknown")*'10 Scoring & Weights'!$C$9+('03 Feature Comparison'!Q16="No")*'10 Scoring & Weights'!$C$10) -> 0.25 | O67: =(('03 Feature Comparison'!Q17="Yes")*'10 Scoring & Weights'!$C$7+('03 Feature Comparison'!Q17="Conditional")*'10 Scoring & Weights'!$C$8+('03 Feature Comparison'!Q17="Unknown")*'10 Scoring & Weights'!$C$9+('03 Feature Comparison'!Q17="No")*'10 Scoring & Weights'!$C$10) -> 1 | P67: =(('03 Feature Comparison'!Q18="Yes")*'10 Scoring & Weights'!$C$7+('03 Feature Comparison'!Q18="Conditional")*'10 Scoring & Weights'!$C$8+('03 Feature Comparison'!Q18="Unknown")*'10 Scoring & Weights'!$C$9+('03 Feature Comparison'!Q18="No")*'10 Scoring & Weights'!$C$10) -> 1
B68: F13 | C68: GNSS positioning | D68: =(('03 Feature Comparison'!R6="Yes")*'10 Scoring & Weights'!$C$7+('03 Feature Comparison'!R6="Conditional")*'10 Scoring & Weights'!$C$8+('03 Feature Comparison'!R6="Unknown")*'10 Scoring & Weights'!$C$9+('03 Feature Comparison'!R6="No")*'10 Scoring & Weights'!$C$10) -> 0 | E68: =(('03 Feature Comparison'!R7="Yes")*'10 Scoring & Weights'!$C$7+('03 Feature Comparison'!R7="Conditional")*'10 Scoring & Weights'!$C$8+('03 Feature Comparison'!R7="Unknown")*'10 Scoring & Weights'!$C$9+('03 Feature Comparison'!R7="No")*'10 Scoring & Weights'!$C$10) -> 0.25 | F68: =(('03 Feature Comparison'!R8="Yes")*'10 Scoring & Weights'!$C$7+('03 Feature Comparison'!R8="Conditional")*'10 Scoring & Weights'!$C$8+('03 Feature Comparison'!R8="Unknown")*'10 Scoring & Weights'!$C$9+('03 Feature Comparison'!R8="No")*'10 Scoring & Weights'!$C$10) -> 1 | G68: =(('03 Feature Comparison'!R9="Yes")*'10 Scoring & Weights'!$C$7+('03 Feature Comparison'!R9="Conditional")*'10 Scoring & Weights'!$C$8+('03 Feature Comparison'!R9="Unknown")*'10 Scoring & Weights'!$C$9+('03 Feature Comparison'!R9="No")*'10 Scoring & Weights'!$C$10) -> 0 | H68: =(('03 Feature Comparison'!R10="Yes")*'10 Scoring & Weights'!$C$7+('03 Feature Comparison'!R10="Conditional")*'10 Scoring & Weights'!$C$8+('03 Feature Comparison'!R10="Unknown")*'10 Scoring & Weights'!$C$9+('03 Feature Comparison'!R10="No")*'10 Scoring & Weights'!$C$10) -> 0 | I68: =(('03 Feature Comparison'!R11="Yes")*'10 Scoring & Weights'!$C$7+('03 Feature Comparison'!R11="Conditional")*'10 Scoring & Weights'!$C$8+('03 Feature Comparison'!R11="Unknown")*'10 Scoring & Weights'!$C$9+('03 Feature Comparison'!R11="No")*'10 Scoring & Weights'!$C$10) -> 0 | J68: =(('03 Feature Comparison'!R12="Yes")*'10 Scoring & Weights'!$C$7+('03 Feature Comparison'!R12="Conditional")*'10 Scoring & Weights'!$C$8+('03 Feature Comparison'!R12="Unknown")*'10 Scoring & Weights'!$C$9+('03 Feature Comparison'!R12="No")*'10 Scoring & Weights'!$C$10) -> 1 | K68: =(('03 Feature Comparison'!R13="Yes")*'10 Scoring & Weights'!$C$7+('03 Feature Comparison'!R13="Conditional")*'10 Scoring & Weights'!$C$8+('03 Feature Comparison'!R13="Unknown")*'10 Scoring & Weights'!$C$9+('03 Feature Comparison'!R13="No")*'10 Scoring & Weights'!$C$10) -> 0 | L68: =(('03 Feature Comparison'!R14="Yes")*'10 Scoring & Weights'!$C$7+('03 Feature Comparison'!R14="Conditional")*'10 Scoring & Weights'!$C$8+('03 Feature Comparison'!R14="Unknown")*'10 Scoring & Weights'!$C$9+('03 Feature Comparison'!R14="No")*'10 Scoring & Weights'!$C$10) -> 1 | M68: =(('03 Feature Comparison'!R15="Yes")*'10 Scoring & Weights'!$C$7+('03 Feature Comparison'!R15="Conditional")*'10 Scoring & Weights'!$C$8+('03 Feature Comparison'!R15="Unknown")*'10 Scoring & Weights'!$C$9+('03 Feature Comparison'!R15="No")*'10 Scoring & Weights'!$C$10) -> 1 | N68: =(('03 Feature Comparison'!R16="Yes")*'10 Scoring & Weights'!$C$7+('03 Feature Comparison'!R16="Conditional")*'10 Scoring & Weights'!$C$8+('03 Feature Comparison'!R16="Unknown")*'10 Scoring & Weights'!$C$9+('03 Feature Comparison'!R16="No")*'10 Scoring & Weights'!$C$10) -> 1 | O68: =(('03 Feature Comparison'!R17="Yes")*'10 Scoring & Weights'!$C$7+('03 Feature Comparison'!R17="Conditional")*'10 Scoring & Weights'!$C$8+('03 Feature Comparison'!R17="Unknown")*'10 Scoring & Weights'!$C$9+('03 Feature Comparison'!R17="No")*'10 Scoring & Weights'!$C$10) -> 1 | P68: =(('03 Feature Comparison'!R18="Yes")*'10 Scoring & Weights'!$C$7+('03 Feature Comparison'!R18="Conditional")*'10 Scoring & Weights'!$C$8+('03 Feature Comparison'!R18="Unknown")*'10 Scoring & Weights'!$C$9+('03 Feature Comparison'!R18="No")*'10 Scoring & Weights'!$C$10) -> 1
B69: F14 | C69: Geofencing | D69: =(('03 Feature Comparison'!S6="Yes")*'10 Scoring & Weights'!$C$7+('03 Feature Comparison'!S6="Conditional")*'10 Scoring & Weights'!$C$8+('03 Feature Comparison'!S6="Unknown")*'10 Scoring & Weights'!$C$9+('03 Feature Comparison'!S6="No")*'10 Scoring & Weights'!$C$10) -> 0 | E69: =(('03 Feature Comparison'!S7="Yes")*'10 Scoring & Weights'!$C$7+('03 Feature Comparison'!S7="Conditional")*'10 Scoring & Weights'!$C$8+('03 Feature Comparison'!S7="Unknown")*'10 Scoring & Weights'!$C$9+('03 Feature Comparison'!S7="No")*'10 Scoring & Weights'!$C$10) -> 0.25 | F69: =(('03 Feature Comparison'!S8="Yes")*'10 Scoring & Weights'!$C$7+('03 Feature Comparison'!S8="Conditional")*'10 Scoring & Weights'!$C$8+('03 Feature Comparison'!S8="Unknown")*'10 Scoring & Weights'!$C$9+('03 Feature Comparison'!S8="No")*'10 Scoring & Weights'!$C$10) -> 0.25 | G69: =(('03 Feature Comparison'!S9="Yes")*'10 Scoring & Weights'!$C$7+('03 Feature Comparison'!S9="Conditional")*'10 Scoring & Weights'!$C$8+('03 Feature Comparison'!S9="Unknown")*'10 Scoring & Weights'!$C$9+('03 Feature Comparison'!S9="No")*'10 Scoring & Weights'!$C$10) -> 0 | H69: =(('03 Feature Comparison'!S10="Yes")*'10 Scoring & Weights'!$C$7+('03 Feature Comparison'!S10="Conditional")*'10 Scoring & Weights'!$C$8+('03 Feature Comparison'!S10="Unknown")*'10 Scoring & Weights'!$C$9+('03 Feature Comparison'!S10="No")*'10 Scoring & Weights'!$C$10) -> 0 | I69: =(('03 Feature Comparison'!S11="Yes")*'10 Scoring & Weights'!$C$7+('03 Feature Comparison'!S11="Conditional")*'10 Scoring & Weights'!$C$8+('03 Feature Comparison'!S11="Unknown")*'10 Scoring & Weights'!$C$9+('03 Feature Comparison'!S11="No")*'10 Scoring & Weights'!$C$10) -> 0 | J69: =(('03 Feature Comparison'!S12="Yes")*'10 Scoring & Weights'!$C$7+('03 Feature Comparison'!S12="Conditional")*'10 Scoring & Weights'!$C$8+('03 Feature Comparison'!S12="Unknown")*'10 Scoring & Weights'!$C$9+('03 Feature Comparison'!S12="No")*'10 Scoring & Weights'!$C$10) -> 0.25 | K69: =(('03 Feature Comparison'!S13="Yes")*'10 Scoring & Weights'!$C$7+('03 Feature Comparison'!S13="Conditional")*'10 Scoring & Weights'!$C$8+('03 Feature Comparison'!S13="Unknown")*'10 Scoring & Weights'!$C$9+('03 Feature Comparison'!S13="No")*'10 Scoring & Weights'!$C$10) -> 0 | L69: =(('03 Feature Comparison'!S14="Yes")*'10 Scoring & Weights'!$C$7+('03 Feature Comparison'!S14="Conditional")*'10 Scoring & Weights'!$C$8+('03 Feature Comparison'!S14="Unknown")*'10 Scoring & Weights'!$C$9+('03 Feature Comparison'!S14="No")*'10 Scoring & Weights'!$C$10) -> 0.25 | M69: =(('03 Feature Comparison'!S15="Yes")*'10 Scoring & Weights'!$C$7+('03 Feature Comparison'!S15="Conditional")*'10 Scoring & Weights'!$C$8+('03 Feature Comparison'!S15="Unknown")*'10 Scoring & Weights'!$C$9+('03 Feature Comparison'!S15="No")*'10 Scoring & Weights'!$C$10) -> 0.25 | N69: =(('03 Feature Comparison'!S16="Yes")*'10 Scoring & Weights'!$C$7+('03 Feature Comparison'!S16="Conditional")*'10 Scoring & Weights'!$C$8+('03 Feature Comparison'!S16="Unknown")*'10 Scoring & Weights'!$C$9+('03 Feature Comparison'!S16="No")*'10 Scoring & Weights'!$C$10) -> 1 | O69: =(('03 Feature Comparison'!S17="Yes")*'10 Scoring & Weights'!$C$7+('03 Feature Comparison'!S17="Conditional")*'10 Scoring & Weights'!$C$8+('03 Feature Comparison'!S17="Unknown")*'10 Scoring & Weights'!$C$9+('03 Feature Comparison'!S17="No")*'10 Scoring & Weights'!$C$10) -> 0.25 | P69: =(('03 Feature Comparison'!S18="Yes")*'10 Scoring & Weights'!$C$7+('03 Feature Comparison'!S18="Conditional")*'10 Scoring & Weights'!$C$8+('03 Feature Comparison'!S18="Unknown")*'10 Scoring & Weights'!$C$9+('03 Feature Comparison'!S18="No")*'10 Scoring & Weights'!$C$10) -> 0.25
B70: F15 | C70: Standalone 4G/LTE | D70: =(('03 Feature Comparison'!T6="Yes")*'10 Scoring & Weights'!$C$7+('03 Feature Comparison'!T6="Conditional")*'10 Scoring & Weights'!$C$8+('03 Feature Comparison'!T6="Unknown")*'10 Scoring & Weights'!$C$9+('03 Feature Comparison'!T6="No")*'10 Scoring & Weights'!$C$10) -> 0 | E70: =(('03 Feature Comparison'!T7="Yes")*'10 Scoring & Weights'!$C$7+('03 Feature Comparison'!T7="Conditional")*'10 Scoring & Weights'!$C$8+('03 Feature Comparison'!T7="Unknown")*'10 Scoring & Weights'!$C$9+('03 Feature Comparison'!T7="No")*'10 Scoring & Weights'!$C$10) -> 1 | F70: =(('03 Feature Comparison'!T8="Yes")*'10 Scoring & Weights'!$C$7+('03 Feature Comparison'!T8="Conditional")*'10 Scoring & Weights'!$C$8+('03 Feature Comparison'!T8="Unknown")*'10 Scoring & Weights'!$C$9+('03 Feature Comparison'!T8="No")*'10 Scoring & Weights'!$C$10) -> 1 | G70: =(('03 Feature Comparison'!T9="Yes")*'10 Scoring & Weights'!$C$7+('03 Feature Comparison'!T9="Conditional")*'10 Scoring & Weights'!$C$8+('03 Feature Comparison'!T9="Unknown")*'10 Scoring & Weights'!$C$9+('03 Feature Comparison'!T9="No")*'10 Scoring & Weights'!$C$10) -> 0 | H70: =(('03 Feature Comparison'!T10="Yes")*'10 Scoring & Weights'!$C$7+('03 Feature Comparison'!T10="Conditional")*'10 Scoring & Weights'!$C$8+('03 Feature Comparison'!T10="Unknown")*'10 Scoring & Weights'!$C$9+('03 Feature Comparison'!T10="No")*'10 Scoring & Weights'!$C$10) -> 0 | I70: =(('03 Feature Comparison'!T11="Yes")*'10 Scoring & Weights'!$C$7+('03 Feature Comparison'!T11="Conditional")*'10 Scoring & Weights'!$C$8+('03 Feature Comparison'!T11="Unknown")*'10 Scoring & Weights'!$C$9+('03 Feature Comparison'!T11="No")*'10 Scoring & Weights'!$C$10) -> 0 | J70: =(('03 Feature Comparison'!T12="Yes")*'10 Scoring & Weights'!$C$7+('03 Feature Comparison'!T12="Conditional")*'10 Scoring & Weights'!$C$8+('03 Feature Comparison'!T12="Unknown")*'10 Scoring & Weights'!$C$9+('03 Feature Comparison'!T12="No")*'10 Scoring & Weights'!$C$10) -> 1 | K70: =(('03 Feature Comparison'!T13="Yes")*'10 Scoring & Weights'!$C$7+('03 Feature Comparison'!T13="Conditional")*'10 Scoring & Weights'!$C$8+('03 Feature Comparison'!T13="Unknown")*'10 Scoring & Weights'!$C$9+('03 Feature Comparison'!T13="No")*'10 Scoring & Weights'!$C$10) -> 0 | L70: =(('03 Feature Comparison'!T14="Yes")*'10 Scoring & Weights'!$C$7+('03 Feature Comparison'!T14="Conditional")*'10 Scoring & Weights'!$C$8+('03 Feature Comparison'!T14="Unknown")*'10 Scoring & Weights'!$C$9+('03 Feature Comparison'!T14="No")*'10 Scoring & Weights'!$C$10) -> 1 | M70: =(('03 Feature Comparison'!T15="Yes")*'10 Scoring & Weights'!$C$7+('03 Feature Comparison'!T15="Conditional")*'10 Scoring & Weights'!$C$8+('03 Feature Comparison'!T15="Unknown")*'10 Scoring & Weights'!$C$9+('03 Feature Comparison'!T15="No")*'10 Scoring & Weights'!$C$10) -> 1 | N70: =(('03 Feature Comparison'!T16="Yes")*'10 Scoring & Weights'!$C$7+('03 Feature Comparison'!T16="Conditional")*'10 Scoring & Weights'!$C$8+('03 Feature Comparison'!T16="Unknown")*'10 Scoring & Weights'!$C$9+('03 Feature Comparison'!T16="No")*'10 Scoring & Weights'!$C$10) -> 1 | O70: =(('03 Feature Comparison'!T17="Yes")*'10 Scoring & Weights'!$C$7+('03 Feature Comparison'!T17="Conditional")*'10 Scoring & Weights'!$C$8+('03 Feature Comparison'!T17="Unknown")*'10 Scoring & Weights'!$C$9+('03 Feature Comparison'!T17="No")*'10 Scoring & Weights'!$C$10) -> 1 | P70: =(('03 Feature Comparison'!T18="Yes")*'10 Scoring & Weights'!$C$7+('03 Feature Comparison'!T18="Conditional")*'10 Scoring & Weights'!$C$8+('03 Feature Comparison'!T18="Unknown")*'10 Scoring & Weights'!$C$9+('03 Feature Comparison'!T18="No")*'10 Scoring & Weights'!$C$10) -> 1
B71: F16 | C71: Works without a smartphone | D71: =(('03 Feature Comparison'!U6="Yes")*'10 Scoring & Weights'!$C$7+('03 Feature Comparison'!U6="Conditional")*'10 Scoring & Weights'!$C$8+('03 Feature Comparison'!U6="Unknown")*'10 Scoring & Weights'!$C$9+('03 Feature Comparison'!U6="No")*'10 Scoring & Weights'!$C$10) -> 0 | E71: =(('03 Feature Comparison'!U7="Yes")*'10 Scoring & Weights'!$C$7+('03 Feature Comparison'!U7="Conditional")*'10 Scoring & Weights'!$C$8+('03 Feature Comparison'!U7="Unknown")*'10 Scoring & Weights'!$C$9+('03 Feature Comparison'!U7="No")*'10 Scoring & Weights'!$C$10) -> 0.5 | F71: =(('03 Feature Comparison'!U8="Yes")*'10 Scoring & Weights'!$C$7+('03 Feature Comparison'!U8="Conditional")*'10 Scoring & Weights'!$C$8+('03 Feature Comparison'!U8="Unknown")*'10 Scoring & Weights'!$C$9+('03 Feature Comparison'!U8="No")*'10 Scoring & Weights'!$C$10) -> 1 | G71: =(('03 Feature Comparison'!U9="Yes")*'10 Scoring & Weights'!$C$7+('03 Feature Comparison'!U9="Conditional")*'10 Scoring & Weights'!$C$8+('03 Feature Comparison'!U9="Unknown")*'10 Scoring & Weights'!$C$9+('03 Feature Comparison'!U9="No")*'10 Scoring & Weights'!$C$10) -> 0 | H71: =(('03 Feature Comparison'!U10="Yes")*'10 Scoring & Weights'!$C$7+('03 Feature Comparison'!U10="Conditional")*'10 Scoring & Weights'!$C$8+('03 Feature Comparison'!U10="Unknown")*'10 Scoring & Weights'!$C$9+('03 Feature Comparison'!U10="No")*'10 Scoring & Weights'!$C$10) -> 0 | I71: =(('03 Feature Comparison'!U11="Yes")*'10 Scoring & Weights'!$C$7+('03 Feature Comparison'!U11="Conditional")*'10 Scoring & Weights'!$C$8+('03 Feature Comparison'!U11="Unknown")*'10 Scoring & Weights'!$C$9+('03 Feature Comparison'!U11="No")*'10 Scoring & Weights'!$C$10) -> 0 | J71: =(('03 Feature Comparison'!U12="Yes")*'10 Scoring & Weights'!$C$7+('03 Feature Comparison'!U12="Conditional")*'10 Scoring & Weights'!$C$8+('03 Feature Comparison'!U12="Unknown")*'10 Scoring & Weights'!$C$9+('03 Feature Comparison'!U12="No")*'10 Scoring & Weights'!$C$10) -> 1 | K71: =(('03 Feature Comparison'!U13="Yes")*'10 Scoring & Weights'!$C$7+('03 Feature Comparison'!U13="Conditional")*'10 Scoring & Weights'!$C$8+('03 Feature Comparison'!U13="Unknown")*'10 Scoring & Weights'!$C$9+('03 Feature Comparison'!U13="No")*'10 Scoring & Weights'!$C$10) -> 0 | L71: =(('03 Feature Comparison'!U14="Yes")*'10 Scoring & Weights'!$C$7+('03 Feature Comparison'!U14="Conditional")*'10 Scoring & Weights'!$C$8+('03 Feature Comparison'!U14="Unknown")*'10 Scoring & Weights'!$C$9+('03 Feature Comparison'!U14="No")*'10 Scoring & Weights'!$C$10) -> 1 | M71: =(('03 Feature Comparison'!U15="Yes")*'10 Scoring & Weights'!$C$7+('03 Feature Comparison'!U15="Conditional")*'10 Scoring & Weights'!$C$8+('03 Feature Comparison'!U15="Unknown")*'10 Scoring & Weights'!$C$9+('03 Feature Comparison'!U15="No")*'10 Scoring & Weights'!$C$10) -> 1 | N71: =(('03 Feature Comparison'!U16="Yes")*'10 Scoring & Weights'!$C$7+('03 Feature Comparison'!U16="Conditional")*'10 Scoring & Weights'!$C$8+('03 Feature Comparison'!U16="Unknown")*'10 Scoring & Weights'!$C$9+('03 Feature Comparison'!U16="No")*'10 Scoring & Weights'!$C$10) -> 1 | O71: =(('03 Feature Comparison'!U17="Yes")*'10 Scoring & Weights'!$C$7+('03 Feature Comparison'!U17="Conditional")*'10 Scoring & Weights'!$C$8+('03 Feature Comparison'!U17="Unknown")*'10 Scoring & Weights'!$C$9+('03 Feature Comparison'!U17="No")*'10 Scoring & Weights'!$C$10) -> 1 | P71: =(('03 Feature Comparison'!U18="Yes")*'10 Scoring & Weights'!$C$7+('03 Feature Comparison'!U18="Conditional")*'10 Scoring & Weights'!$C$8+('03 Feature Comparison'!U18="Unknown")*'10 Scoring & Weights'!$C$9+('03 Feature Comparison'!U18="No")*'10 Scoring & Weights'!$C$10) -> 1
B72: F17 | C72: Screenless / minimal interface | D72: =(('03 Feature Comparison'!V6="Yes")*'10 Scoring & Weights'!$C$7+('03 Feature Comparison'!V6="Conditional")*'10 Scoring & Weights'!$C$8+('03 Feature Comparison'!V6="Unknown")*'10 Scoring & Weights'!$C$9+('03 Feature Comparison'!V6="No")*'10 Scoring & Weights'!$C$10) -> 1 | E72: =(('03 Feature Comparison'!V7="Yes")*'10 Scoring & Weights'!$C$7+('03 Feature Comparison'!V7="Conditional")*'10 Scoring & Weights'!$C$8+('03 Feature Comparison'!V7="Unknown")*'10 Scoring & Weights'!$C$9+('03 Feature Comparison'!V7="No")*'10 Scoring & Weights'!$C$10) -> 0.25 | F72: =(('03 Feature Comparison'!V8="Yes")*'10 Scoring & Weights'!$C$7+('03 Feature Comparison'!V8="Conditional")*'10 Scoring & Weights'!$C$8+('03 Feature Comparison'!V8="Unknown")*'10 Scoring & Weights'!$C$9+('03 Feature Comparison'!V8="No")*'10 Scoring & Weights'!$C$10) -> 1 | G72: =(('03 Feature Comparison'!V9="Yes")*'10 Scoring & Weights'!$C$7+('03 Feature Comparison'!V9="Conditional")*'10 Scoring & Weights'!$C$8+('03 Feature Comparison'!V9="Unknown")*'10 Scoring & Weights'!$C$9+('03 Feature Comparison'!V9="No")*'10 Scoring & Weights'!$C$10) -> 1 | H72: =(('03 Feature Comparison'!V10="Yes")*'10 Scoring & Weights'!$C$7+('03 Feature Comparison'!V10="Conditional")*'10 Scoring & Weights'!$C$8+('03 Feature Comparison'!V10="Unknown")*'10 Scoring & Weights'!$C$9+('03 Feature Comparison'!V10="No")*'10 Scoring & Weights'!$C$10) -> 1 | I72: =(('03 Feature Comparison'!V11="Yes")*'10 Scoring & Weights'!$C$7+('03 Feature Comparison'!V11="Conditional")*'10 Scoring & Weights'!$C$8+('03 Feature Comparison'!V11="Unknown")*'10 Scoring & Weights'!$C$9+('03 Feature Comparison'!V11="No")*'10 Scoring & Weights'!$C$10) -> 0 | J72: =(('03 Feature Comparison'!V12="Yes")*'10 Scoring & Weights'!$C$7+('03 Feature Comparison'!V12="Conditional")*'10 Scoring & Weights'!$C$8+('03 Feature Comparison'!V12="Unknown")*'10 Scoring & Weights'!$C$9+('03 Feature Comparison'!V12="No")*'10 Scoring & Weights'!$C$10) -> 0 | K72: =(('03 Feature Comparison'!V13="Yes")*'10 Scoring & Weights'!$C$7+('03 Feature Comparison'!V13="Conditional")*'10 Scoring & Weights'!$C$8+('03 Feature Comparison'!V13="Unknown")*'10 Scoring & Weights'!$C$9+('03 Feature Comparison'!V13="No")*'10 Scoring & Weights'!$C$10) -> 1 | L72: =(('03 Feature Comparison'!V14="Yes")*'10 Scoring & Weights'!$C$7+('03 Feature Comparison'!V14="Conditional")*'10 Scoring & Weights'!$C$8+('03 Feature Comparison'!V14="Unknown")*'10 Scoring & Weights'!$C$9+('03 Feature Comparison'!V14="No")*'10 Scoring & Weights'!$C$10) -> 0 | M72: =(('03 Feature Comparison'!V15="Yes")*'10 Scoring & Weights'!$C$7+('03 Feature Comparison'!V15="Conditional")*'10 Scoring & Weights'!$C$8+('03 Feature Comparison'!V15="Unknown")*'10 Scoring & Weights'!$C$9+('03 Feature Comparison'!V15="No")*'10 Scoring & Weights'!$C$10) -> 0 | N72: =(('03 Feature Comparison'!V16="Yes")*'10 Scoring & Weights'!$C$7+('03 Feature Comparison'!V16="Conditional")*'10 Scoring & Weights'!$C$8+('03 Feature Comparison'!V16="Unknown")*'10 Scoring & Weights'!$C$9+('03 Feature Comparison'!V16="No")*'10 Scoring & Weights'!$C$10) -> 0 | O72: =(('03 Feature Comparison'!V17="Yes")*'10 Scoring & Weights'!$C$7+('03 Feature Comparison'!V17="Conditional")*'10 Scoring & Weights'!$C$8+('03 Feature Comparison'!V17="Unknown")*'10 Scoring & Weights'!$C$9+('03 Feature Comparison'!V17="No")*'10 Scoring & Weights'!$C$10) -> 0.25 | P72: =(('03 Feature Comparison'!V18="Yes")*'10 Scoring & Weights'!$C$7+('03 Feature Comparison'!V18="Conditional")*'10 Scoring & Weights'!$C$8+('03 Feature Comparison'!V18="Unknown")*'10 Scoring & Weights'!$C$9+('03 Feature Comparison'!V18="No")*'10 Scoring & Weights'!$C$10) -> 1
B73: F18 | C73: Medication reminder | D73: =(('03 Feature Comparison'!W6="Yes")*'10 Scoring & Weights'!$C$7+('03 Feature Comparison'!W6="Conditional")*'10 Scoring & Weights'!$C$8+('03 Feature Comparison'!W6="Unknown")*'10 Scoring & Weights'!$C$9+('03 Feature Comparison'!W6="No")*'10 Scoring & Weights'!$C$10) -> 0.25 | E73: =(('03 Feature Comparison'!W7="Yes")*'10 Scoring & Weights'!$C$7+('03 Feature Comparison'!W7="Conditional")*'10 Scoring & Weights'!$C$8+('03 Feature Comparison'!W7="Unknown")*'10 Scoring & Weights'!$C$9+('03 Feature Comparison'!W7="No")*'10 Scoring & Weights'!$C$10) -> 0.25 | F73: =(('03 Feature Comparison'!W8="Yes")*'10 Scoring & Weights'!$C$7+('03 Feature Comparison'!W8="Conditional")*'10 Scoring & Weights'!$C$8+('03 Feature Comparison'!W8="Unknown")*'10 Scoring & Weights'!$C$9+('03 Feature Comparison'!W8="No")*'10 Scoring & Weights'!$C$10) -> 0.25 | G73: =(('03 Feature Comparison'!W9="Yes")*'10 Scoring & Weights'!$C$7+('03 Feature Comparison'!W9="Conditional")*'10 Scoring & Weights'!$C$8+('03 Feature Comparison'!W9="Unknown")*'10 Scoring & Weights'!$C$9+('03 Feature Comparison'!W9="No")*'10 Scoring & Weights'!$C$10) -> 1 | H73: =(('03 Feature Comparison'!W10="Yes")*'10 Scoring & Weights'!$C$7+('03 Feature Comparison'!W10="Conditional")*'10 Scoring & Weights'!$C$8+('03 Feature Comparison'!W10="Unknown")*'10 Scoring & Weights'!$C$9+('03 Feature Comparison'!W10="No")*'10 Scoring & Weights'!$C$10) -> 1 | I73: =(('03 Feature Comparison'!W11="Yes")*'10 Scoring & Weights'!$C$7+('03 Feature Comparison'!W11="Conditional")*'10 Scoring & Weights'!$C$8+('03 Feature Comparison'!W11="Unknown")*'10 Scoring & Weights'!$C$9+('03 Feature Comparison'!W11="No")*'10 Scoring & Weights'!$C$10) -> 0.25 | J73: =(('03 Feature Comparison'!W12="Yes")*'10 Scoring & Weights'!$C$7+('03 Feature Comparison'!W12="Conditional")*'10 Scoring & Weights'!$C$8+('03 Feature Comparison'!W12="Unknown")*'10 Scoring & Weights'!$C$9+('03 Feature Comparison'!W12="No")*'10 Scoring & Weights'!$C$10) -> 0.25 | K73: =(('03 Feature Comparison'!W13="Yes")*'10 Scoring & Weights'!$C$7+('03 Feature Comparison'!W13="Conditional")*'10 Scoring & Weights'!$C$8+('03 Feature Comparison'!W13="Unknown")*'10 Scoring & Weights'!$C$9+('03 Feature Comparison'!W13="No")*'10 Scoring & Weights'!$C$10) -> 0.25 | L73: =(('03 Feature Comparison'!W14="Yes")*'10 Scoring & Weights'!$C$7+('03 Feature Comparison'!W14="Conditional")*'10 Scoring & Weights'!$C$8+('03 Feature Comparison'!W14="Unknown")*'10 Scoring & Weights'!$C$9+('03 Feature Comparison'!W14="No")*'10 Scoring & Weights'!$C$10) -> 0.25 | M73: =(('03 Feature Comparison'!W15="Yes")*'10 Scoring & Weights'!$C$7+('03 Feature Comparison'!W15="Conditional")*'10 Scoring & Weights'!$C$8+('03 Feature Comparison'!W15="Unknown")*'10 Scoring & Weights'!$C$9+('03 Feature Comparison'!W15="No")*'10 Scoring & Weights'!$C$10) -> 0.25 | N73: =(('03 Feature Comparison'!W16="Yes")*'10 Scoring & Weights'!$C$7+('03 Feature Comparison'!W16="Conditional")*'10 Scoring & Weights'!$C$8+('03 Feature Comparison'!W16="Unknown")*'10 Scoring & Weights'!$C$9+('03 Feature Comparison'!W16="No")*'10 Scoring & Weights'!$C$10) -> 0.25 | O73: =(('03 Feature Comparison'!W17="Yes")*'10 Scoring & Weights'!$C$7+('03 Feature Comparison'!W17="Conditional")*'10 Scoring & Weights'!$C$8+('03 Feature Comparison'!W17="Unknown")*'10 Scoring & Weights'!$C$9+('03 Feature Comparison'!W17="No")*'10 Scoring & Weights'!$C$10) -> 0.25 | P73: =(('03 Feature Comparison'!W18="Yes")*'10 Scoring & Weights'!$C$7+('03 Feature Comparison'!W18="Conditional")*'10 Scoring & Weights'!$C$8+('03 Feature Comparison'!W18="Unknown")*'10 Scoring & Weights'!$C$9+('03 Feature Comparison'!W18="No")*'10 Scoring & Weights'!$C$10) -> 0.25
B74: F19 | C74: Non-invasive glucose / lipid estimation | D74: =(('03 Feature Comparison'!X6="Yes")*'10 Scoring & Weights'!$C$7+('03 Feature Comparison'!X6="Conditional")*'10 Scoring & Weights'!$C$8+('03 Feature Comparison'!X6="Unknown")*'10 Scoring & Weights'!$C$9+('03 Feature Comparison'!X6="No")*'10 Scoring & Weights'!$C$10) -> 1 | E74: =(('03 Feature Comparison'!X7="Yes")*'10 Scoring & Weights'!$C$7+('03 Feature Comparison'!X7="Conditional")*'10 Scoring & Weights'!$C$8+('03 Feature Comparison'!X7="Unknown")*'10 Scoring & Weights'!$C$9+('03 Feature Comparison'!X7="No")*'10 Scoring & Weights'!$C$10) -> 0.25 | F74: =(('03 Feature Comparison'!X8="Yes")*'10 Scoring & Weights'!$C$7+('03 Feature Comparison'!X8="Conditional")*'10 Scoring & Weights'!$C$8+('03 Feature Comparison'!X8="Unknown")*'10 Scoring & Weights'!$C$9+('03 Feature Comparison'!X8="No")*'10 Scoring & Weights'!$C$10) -> 0.25 | G74: =(('03 Feature Comparison'!X9="Yes")*'10 Scoring & Weights'!$C$7+('03 Feature Comparison'!X9="Conditional")*'10 Scoring & Weights'!$C$8+('03 Feature Comparison'!X9="Unknown")*'10 Scoring & Weights'!$C$9+('03 Feature Comparison'!X9="No")*'10 Scoring & Weights'!$C$10) -> 1 | H74: =(('03 Feature Comparison'!X10="Yes")*'10 Scoring & Weights'!$C$7+('03 Feature Comparison'!X10="Conditional")*'10 Scoring & Weights'!$C$8+('03 Feature Comparison'!X10="Unknown")*'10 Scoring & Weights'!$C$9+('03 Feature Comparison'!X10="No")*'10 Scoring & Weights'!$C$10) -> 1 | I74: =(('03 Feature Comparison'!X11="Yes")*'10 Scoring & Weights'!$C$7+('03 Feature Comparison'!X11="Conditional")*'10 Scoring & Weights'!$C$8+('03 Feature Comparison'!X11="Unknown")*'10 Scoring & Weights'!$C$9+('03 Feature Comparison'!X11="No")*'10 Scoring & Weights'!$C$10) -> 0.25 | J74: =(('03 Feature Comparison'!X12="Yes")*'10 Scoring & Weights'!$C$7+('03 Feature Comparison'!X12="Conditional")*'10 Scoring & Weights'!$C$8+('03 Feature Comparison'!X12="Unknown")*'10 Scoring & Weights'!$C$9+('03 Feature Comparison'!X12="No")*'10 Scoring & Weights'!$C$10) -> 1 | K74: =(('03 Feature Comparison'!X13="Yes")*'10 Scoring & Weights'!$C$7+('03 Feature Comparison'!X13="Conditional")*'10 Scoring & Weights'!$C$8+('03 Feature Comparison'!X13="Unknown")*'10 Scoring & Weights'!$C$9+('03 Feature Comparison'!X13="No")*'10 Scoring & Weights'!$C$10) -> 1 | L74: =(('03 Feature Comparison'!X14="Yes")*'10 Scoring & Weights'!$C$7+('03 Feature Comparison'!X14="Conditional")*'10 Scoring & Weights'!$C$8+('03 Feature Comparison'!X14="Unknown")*'10 Scoring & Weights'!$C$9+('03 Feature Comparison'!X14="No")*'10 Scoring & Weights'!$C$10) -> 1 | M74: =(('03 Feature Comparison'!X15="Yes")*'10 Scoring & Weights'!$C$7+('03 Feature Comparison'!X15="Conditional")*'10 Scoring & Weights'!$C$8+('03 Feature Comparison'!X15="Unknown")*'10 Scoring & Weights'!$C$9+('03 Feature Comparison'!X15="No")*'10 Scoring & Weights'!$C$10) -> 1 | N74: =(('03 Feature Comparison'!X16="Yes")*'10 Scoring & Weights'!$C$7+('03 Feature Comparison'!X16="Conditional")*'10 Scoring & Weights'!$C$8+('03 Feature Comparison'!X16="Unknown")*'10 Scoring & Weights'!$C$9+('03 Feature Comparison'!X16="No")*'10 Scoring & Weights'!$C$10) -> 0.25 | O74: =(('03 Feature Comparison'!X17="Yes")*'10 Scoring & Weights'!$C$7+('03 Feature Comparison'!X17="Conditional")*'10 Scoring & Weights'!$C$8+('03 Feature Comparison'!X17="Unknown")*'10 Scoring & Weights'!$C$9+('03 Feature Comparison'!X17="No")*'10 Scoring & Weights'!$C$10) -> 0.25 | P74: =(('03 Feature Comparison'!X18="Yes")*'10 Scoring & Weights'!$C$7+('03 Feature Comparison'!X18="Conditional")*'10 Scoring & Weights'!$C$8+('03 Feature Comparison'!X18="Unknown")*'10 Scoring & Weights'!$C$9+('03 Feature Comparison'!X18="No")*'10 Scoring & Weights'!$C$10) -> 0.25
B75: F20 | C75: No camera | D75: =(('03 Feature Comparison'!Y6="Yes")*'10 Scoring & Weights'!$C$7+('03 Feature Comparison'!Y6="Conditional")*'10 Scoring & Weights'!$C$8+('03 Feature Comparison'!Y6="Unknown")*'10 Scoring & Weights'!$C$9+('03 Feature Comparison'!Y6="No")*'10 Scoring & Weights'!$C$10) -> 1 | E75: =(('03 Feature Comparison'!Y7="Yes")*'10 Scoring & Weights'!$C$7+('03 Feature Comparison'!Y7="Conditional")*'10 Scoring & Weights'!$C$8+('03 Feature Comparison'!Y7="Unknown")*'10 Scoring & Weights'!$C$9+('03 Feature Comparison'!Y7="No")*'10 Scoring & Weights'!$C$10) -> 0.25 | F75: =(('03 Feature Comparison'!Y8="Yes")*'10 Scoring & Weights'!$C$7+('03 Feature Comparison'!Y8="Conditional")*'10 Scoring & Weights'!$C$8+('03 Feature Comparison'!Y8="Unknown")*'10 Scoring & Weights'!$C$9+('03 Feature Comparison'!Y8="No")*'10 Scoring & Weights'!$C$10) -> 1 | G75: =(('03 Feature Comparison'!Y9="Yes")*'10 Scoring & Weights'!$C$7+('03 Feature Comparison'!Y9="Conditional")*'10 Scoring & Weights'!$C$8+('03 Feature Comparison'!Y9="Unknown")*'10 Scoring & Weights'!$C$9+('03 Feature Comparison'!Y9="No")*'10 Scoring & Weights'!$C$10) -> 1 | H75: =(('03 Feature Comparison'!Y10="Yes")*'10 Scoring & Weights'!$C$7+('03 Feature Comparison'!Y10="Conditional")*'10 Scoring & Weights'!$C$8+('03 Feature Comparison'!Y10="Unknown")*'10 Scoring & Weights'!$C$9+('03 Feature Comparison'!Y10="No")*'10 Scoring & Weights'!$C$10) -> 1 | I75: =(('03 Feature Comparison'!Y11="Yes")*'10 Scoring & Weights'!$C$7+('03 Feature Comparison'!Y11="Conditional")*'10 Scoring & Weights'!$C$8+('03 Feature Comparison'!Y11="Unknown")*'10 Scoring & Weights'!$C$9+('03 Feature Comparison'!Y11="No")*'10 Scoring & Weights'!$C$10) -> 1 | J75: =(('03 Feature Comparison'!Y12="Yes")*'10 Scoring & Weights'!$C$7+('03 Feature Comparison'!Y12="Conditional")*'10 Scoring & Weights'!$C$8+('03 Feature Comparison'!Y12="Unknown")*'10 Scoring & Weights'!$C$9+('03 Feature Comparison'!Y12="No")*'10 Scoring & Weights'!$C$10) -> 1 | K75: =(('03 Feature Comparison'!Y13="Yes")*'10 Scoring & Weights'!$C$7+('03 Feature Comparison'!Y13="Conditional")*'10 Scoring & Weights'!$C$8+('03 Feature Comparison'!Y13="Unknown")*'10 Scoring & Weights'!$C$9+('03 Feature Comparison'!Y13="No")*'10 Scoring & Weights'!$C$10) -> 1 | L75: =(('03 Feature Comparison'!Y14="Yes")*'10 Scoring & Weights'!$C$7+('03 Feature Comparison'!Y14="Conditional")*'10 Scoring & Weights'!$C$8+('03 Feature Comparison'!Y14="Unknown")*'10 Scoring & Weights'!$C$9+('03 Feature Comparison'!Y14="No")*'10 Scoring & Weights'!$C$10) -> 1 | M75: =(('03 Feature Comparison'!Y15="Yes")*'10 Scoring & Weights'!$C$7+('03 Feature Comparison'!Y15="Conditional")*'10 Scoring & Weights'!$C$8+('03 Feature Comparison'!Y15="Unknown")*'10 Scoring & Weights'!$C$9+('03 Feature Comparison'!Y15="No")*'10 Scoring & Weights'!$C$10) -> 1 | N75: =(('03 Feature Comparison'!Y16="Yes")*'10 Scoring & Weights'!$C$7+('03 Feature Comparison'!Y16="Conditional")*'10 Scoring & Weights'!$C$8+('03 Feature Comparison'!Y16="Unknown")*'10 Scoring & Weights'!$C$9+('03 Feature Comparison'!Y16="No")*'10 Scoring & Weights'!$C$10) -> 1 | O75: =(('03 Feature Comparison'!Y17="Yes")*'10 Scoring & Weights'!$C$7+('03 Feature Comparison'!Y17="Conditional")*'10 Scoring & Weights'!$C$8+('03 Feature Comparison'!Y17="Unknown")*'10 Scoring & Weights'!$C$9+('03 Feature Comparison'!Y17="No")*'10 Scoring & Weights'!$C$10) -> 1 | P75: =(('03 Feature Comparison'!Y18="Yes")*'10 Scoring & Weights'!$C$7+('03 Feature Comparison'!Y18="Conditional")*'10 Scoring & Weights'!$C$8+('03 Feature Comparison'!Y18="Unknown")*'10 Scoring & Weights'!$C$9+('03 Feature Comparison'!Y18="No")*'10 Scoring & Weights'!$C$10) -> 1
B76: F21 | C76: Offline on-device data storage | D76: =(('03 Feature Comparison'!Z6="Yes")*'10 Scoring & Weights'!$C$7+('03 Feature Comparison'!Z6="Conditional")*'10 Scoring & Weights'!$C$8+('03 Feature Comparison'!Z6="Unknown")*'10 Scoring & Weights'!$C$9+('03 Feature Comparison'!Z6="No")*'10 Scoring & Weights'!$C$10) -> 0.25 | E76: =(('03 Feature Comparison'!Z7="Yes")*'10 Scoring & Weights'!$C$7+('03 Feature Comparison'!Z7="Conditional")*'10 Scoring & Weights'!$C$8+('03 Feature Comparison'!Z7="Unknown")*'10 Scoring & Weights'!$C$9+('03 Feature Comparison'!Z7="No")*'10 Scoring & Weights'!$C$10) -> 0.25 | F76: =(('03 Feature Comparison'!Z8="Yes")*'10 Scoring & Weights'!$C$7+('03 Feature Comparison'!Z8="Conditional")*'10 Scoring & Weights'!$C$8+('03 Feature Comparison'!Z8="Unknown")*'10 Scoring & Weights'!$C$9+('03 Feature Comparison'!Z8="No")*'10 Scoring & Weights'!$C$10) -> 0.25 | G76: =(('03 Feature Comparison'!Z9="Yes")*'10 Scoring & Weights'!$C$7+('03 Feature Comparison'!Z9="Conditional")*'10 Scoring & Weights'!$C$8+('03 Feature Comparison'!Z9="Unknown")*'10 Scoring & Weights'!$C$9+('03 Feature Comparison'!Z9="No")*'10 Scoring & Weights'!$C$10) -> 0.25 | H76: =(('03 Feature Comparison'!Z10="Yes")*'10 Scoring & Weights'!$C$7+('03 Feature Comparison'!Z10="Conditional")*'10 Scoring & Weights'!$C$8+('03 Feature Comparison'!Z10="Unknown")*'10 Scoring & Weights'!$C$9+('03 Feature Comparison'!Z10="No")*'10 Scoring & Weights'!$C$10) -> 0.25 | I76: =(('03 Feature Comparison'!Z11="Yes")*'10 Scoring & Weights'!$C$7+('03 Feature Comparison'!Z11="Conditional")*'10 Scoring & Weights'!$C$8+('03 Feature Comparison'!Z11="Unknown")*'10 Scoring & Weights'!$C$9+('03 Feature Comparison'!Z11="No")*'10 Scoring & Weights'!$C$10) -> 0.25 | J76: =(('03 Feature Comparison'!Z12="Yes")*'10 Scoring & Weights'!$C$7+('03 Feature Comparison'!Z12="Conditional")*'10 Scoring & Weights'!$C$8+('03 Feature Comparison'!Z12="Unknown")*'10 Scoring & Weights'!$C$9+('03 Feature Comparison'!Z12="No")*'10 Scoring & Weights'!$C$10) -> 0.25 | K76: =(('03 Feature Comparison'!Z13="Yes")*'10 Scoring & Weights'!$C$7+('03 Feature Comparison'!Z13="Conditional")*'10 Scoring & Weights'!$C$8+('03 Feature Comparison'!Z13="Unknown")*'10 Scoring & Weights'!$C$9+('03 Feature Comparison'!Z13="No")*'10 Scoring & Weights'!$C$10) -> 0.25 | L76: =(('03 Feature Comparison'!Z14="Yes")*'10 Scoring & Weights'!$C$7+('03 Feature Comparison'!Z14="Conditional")*'10 Scoring & Weights'!$C$8+('03 Feature Comparison'!Z14="Unknown")*'10 Scoring & Weights'!$C$9+('03 Feature Comparison'!Z14="No")*'10 Scoring & Weights'!$C$10) -> 0.25 | M76: =(('03 Feature Comparison'!Z15="Yes")*'10 Scoring & Weights'!$C$7+('03 Feature Comparison'!Z15="Conditional")*'10 Scoring & Weights'!$C$8+('03 Feature Comparison'!Z15="Unknown")*'10 Scoring & Weights'!$C$9+('03 Feature Comparison'!Z15="No")*'10 Scoring & Weights'!$C$10) -> 0.25 | N76: =(('03 Feature Comparison'!Z16="Yes")*'10 Scoring & Weights'!$C$7+('03 Feature Comparison'!Z16="Conditional")*'10 Scoring & Weights'!$C$8+('03 Feature Comparison'!Z16="Unknown")*'10 Scoring & Weights'!$C$9+('03 Feature Comparison'!Z16="No")*'10 Scoring & Weights'!$C$10) -> 0.25 | O76: =(('03 Feature Comparison'!Z17="Yes")*'10 Scoring & Weights'!$C$7+('03 Feature Comparison'!Z17="Conditional")*'10 Scoring & Weights'!$C$8+('03 Feature Comparison'!Z17="Unknown")*'10 Scoring & Weights'!$C$9+('03 Feature Comparison'!Z17="No")*'10 Scoring & Weights'!$C$10) -> 0.25 | P76: =(('03 Feature Comparison'!Z18="Yes")*'10 Scoring & Weights'!$C$7+('03 Feature Comparison'!Z18="Conditional")*'10 Scoring & Weights'!$C$8+('03 Feature Comparison'!Z18="Unknown")*'10 Scoring & Weights'!$C$9+('03 Feature Comparison'!Z18="No")*'10 Scoring & Weights'!$C$10) -> 0.25
B77: F22 | C77: Water resistance IP67 or better | D77: =(('03 Feature Comparison'!AA6="Yes")*'10 Scoring & Weights'!$C$7+('03 Feature Comparison'!AA6="Conditional")*'10 Scoring & Weights'!$C$8+('03 Feature Comparison'!AA6="Unknown")*'10 Scoring & Weights'!$C$9+('03 Feature Comparison'!AA6="No")*'10 Scoring & Weights'!$C$10) -> 1 | E77: =(('03 Feature Comparison'!AA7="Yes")*'10 Scoring & Weights'!$C$7+('03 Feature Comparison'!AA7="Conditional")*'10 Scoring & Weights'!$C$8+('03 Feature Comparison'!AA7="Unknown")*'10 Scoring & Weights'!$C$9+('03 Feature Comparison'!AA7="No")*'10 Scoring & Weights'!$C$10) -> 0.25 | F77: =(('03 Feature Comparison'!AA8="Yes")*'10 Scoring & Weights'!$C$7+('03 Feature Comparison'!AA8="Conditional")*'10 Scoring & Weights'!$C$8+('03 Feature Comparison'!AA8="Unknown")*'10 Scoring & Weights'!$C$9+('03 Feature Comparison'!AA8="No")*'10 Scoring & Weights'!$C$10) -> 1 | G77: =(('03 Feature Comparison'!AA9="Yes")*'10 Scoring & Weights'!$C$7+('03 Feature Comparison'!AA9="Conditional")*'10 Scoring & Weights'!$C$8+('03 Feature Comparison'!AA9="Unknown")*'10 Scoring & Weights'!$C$9+('03 Feature Comparison'!AA9="No")*'10 Scoring & Weights'!$C$10) -> 1 | H77: =(('03 Feature Comparison'!AA10="Yes")*'10 Scoring & Weights'!$C$7+('03 Feature Comparison'!AA10="Conditional")*'10 Scoring & Weights'!$C$8+('03 Feature Comparison'!AA10="Unknown")*'10 Scoring & Weights'!$C$9+('03 Feature Comparison'!AA10="No")*'10 Scoring & Weights'!$C$10) -> 1 | I77: =(('03 Feature Comparison'!AA11="Yes")*'10 Scoring & Weights'!$C$7+('03 Feature Comparison'!AA11="Conditional")*'10 Scoring & Weights'!$C$8+('03 Feature Comparison'!AA11="Unknown")*'10 Scoring & Weights'!$C$9+('03 Feature Comparison'!AA11="No")*'10 Scoring & Weights'!$C$10) -> 0 | J77: =(('03 Feature Comparison'!AA12="Yes")*'10 Scoring & Weights'!$C$7+('03 Feature Comparison'!AA12="Conditional")*'10 Scoring & Weights'!$C$8+('03 Feature Comparison'!AA12="Unknown")*'10 Scoring & Weights'!$C$9+('03 Feature Comparison'!AA12="No")*'10 Scoring & Weights'!$C$10) -> 0.25 | K77: =(('03 Feature Comparison'!AA13="Yes")*'10 Scoring & Weights'!$C$7+('03 Feature Comparison'!AA13="Conditional")*'10 Scoring & Weights'!$C$8+('03 Feature Comparison'!AA13="Unknown")*'10 Scoring & Weights'!$C$9+('03 Feature Comparison'!AA13="No")*'10 Scoring & Weights'!$C$10) -> 0.25 | L77: =(('03 Feature Comparison'!AA14="Yes")*'10 Scoring & Weights'!$C$7+('03 Feature Comparison'!AA14="Conditional")*'10 Scoring & Weights'!$C$8+('03 Feature Comparison'!AA14="Unknown")*'10 Scoring & Weights'!$C$9+('03 Feature Comparison'!AA14="No")*'10 Scoring & Weights'!$C$10) -> 1 | M77: =(('03 Feature Comparison'!AA15="Yes")*'10 Scoring & Weights'!$C$7+('03 Feature Comparison'!AA15="Conditional")*'10 Scoring & Weights'!$C$8+('03 Feature Comparison'!AA15="Unknown")*'10 Scoring & Weights'!$C$9+('03 Feature Comparison'!AA15="No")*'10 Scoring & Weights'!$C$10) -> 0.25 | N77: =(('03 Feature Comparison'!AA16="Yes")*'10 Scoring & Weights'!$C$7+('03 Feature Comparison'!AA16="Conditional")*'10 Scoring & Weights'!$C$8+('03 Feature Comparison'!AA16="Unknown")*'10 Scoring & Weights'!$C$9+('03 Feature Comparison'!AA16="No")*'10 Scoring & Weights'!$C$10) -> 1 | O77: =(('03 Feature Comparison'!AA17="Yes")*'10 Scoring & Weights'!$C$7+('03 Feature Comparison'!AA17="Conditional")*'10 Scoring & Weights'!$C$8+('03 Feature Comparison'!AA17="Unknown")*'10 Scoring & Weights'!$C$9+('03 Feature Comparison'!AA17="No")*'10 Scoring & Weights'!$C$10) -> 0.25 | P77: =(('03 Feature Comparison'!AA18="Yes")*'10 Scoring & Weights'!$C$7+('03 Feature Comparison'!AA18="Conditional")*'10 Scoring & Weights'!$C$8+('03 Feature Comparison'!AA18="Unknown")*'10 Scoring & Weights'!$C$9+('03 Feature Comparison'!AA18="No")*'10 Scoring & Weights'!$C$10) -> 1
B78: BAT | C78: Battery-life class (from 03 specs) | D78: =IF('03 Feature Comparison'!AG6="",'10 Scoring & Weights'!$C$9,IF('03 Feature Comparison'!AH6="X",'10 Scoring & Weights'!$C$8,IF('03 Feature Comparison'!AG6>='10 Scoring & Weights'!$C$14,'10 Scoring & Weights'!$D$14,IF('03 Feature Comparison'!AG6>='10 Scoring & Weights'!$C$15,'10 Scoring & Weights'!$D$15,'10 Scoring & Weights'!$D$16)))) -> 0.5 | E78: =IF('03 Feature Comparison'!AG7="",'10 Scoring & Weights'!$C$9,IF('03 Feature Comparison'!AH7="X",'10 Scoring & Weights'!$C$8,IF('03 Feature Comparison'!AG7>='10 Scoring & Weights'!$C$14,'10 Scoring & Weights'!$D$14,IF('03 Feature Comparison'!AG7>='10 Scoring & Weights'!$C$15,'10 Scoring & Weights'!$D$15,'10 Scoring & Weights'!$D$16)))) -> 0.25 | F78: =IF('03 Feature Comparison'!AG8="",'10 Scoring & Weights'!$C$9,IF('03 Feature Comparison'!AH8="X",'10 Scoring & Weights'!$C$8,IF('03 Feature Comparison'!AG8>='10 Scoring & Weights'!$C$14,'10 Scoring & Weights'!$D$14,IF('03 Feature Comparison'!AG8>='10 Scoring & Weights'!$C$15,'10 Scoring & Weights'!$D$15,'10 Scoring & Weights'!$D$16)))) -> 0.6 | G78: =IF('03 Feature Comparison'!AG9="",'10 Scoring & Weights'!$C$9,IF('03 Feature Comparison'!AH9="X",'10 Scoring & Weights'!$C$8,IF('03 Feature Comparison'!AG9>='10 Scoring & Weights'!$C$14,'10 Scoring & Weights'!$D$14,IF('03 Feature Comparison'!AG9>='10 Scoring & Weights'!$C$15,'10 Scoring & Weights'!$D$15,'10 Scoring & Weights'!$D$16)))) -> 1 | H78: =IF('03 Feature Comparison'!AG10="",'10 Scoring & Weights'!$C$9,IF('03 Feature Comparison'!AH10="X",'10 Scoring & Weights'!$C$8,IF('03 Feature Comparison'!AG10>='10 Scoring & Weights'!$C$14,'10 Scoring & Weights'!$D$14,IF('03 Feature Comparison'!AG10>='10 Scoring & Weights'!$C$15,'10 Scoring & Weights'!$D$15,'10 Scoring & Weights'!$D$16)))) -> 1 | I78: =IF('03 Feature Comparison'!AG11="",'10 Scoring & Weights'!$C$9,IF('03 Feature Comparison'!AH11="X",'10 Scoring & Weights'!$C$8,IF('03 Feature Comparison'!AG11>='10 Scoring & Weights'!$C$14,'10 Scoring & Weights'!$D$14,IF('03 Feature Comparison'!AG11>='10 Scoring & Weights'!$C$15,'10 Scoring & Weights'!$D$15,'10 Scoring & Weights'!$D$16)))) -> 0.25 | J78: =IF('03 Feature Comparison'!AG12="",'10 Scoring & Weights'!$C$9,IF('03 Feature Comparison'!AH12="X",'10 Scoring & Weights'!$C$8,IF('03 Feature Comparison'!AG12>='10 Scoring & Weights'!$C$14,'10 Scoring & Weights'!$D$14,IF('03 Feature Comparison'!AG12>='10 Scoring & Weights'!$C$15,'10 Scoring & Weights'!$D$15,'10 Scoring & Weights'!$D$16)))) -> 0.25 | K78: =IF('03 Feature Comparison'!AG13="",'10 Scoring & Weights'!$C$9,IF('03 Feature Comparison'!AH13="X",'10 Scoring & Weights'!$C$8,IF('03 Feature Comparison'!AG13>='10 Scoring & Weights'!$C$14,'10 Scoring & Weights'!$D$14,IF('03 Feature Comparison'!AG13>='10 Scoring & Weights'!$C$15,'10 Scoring & Weights'!$D$15,'10 Scoring & Weights'!$D$16)))) -> 0.25 | L78: =IF('03 Feature Comparison'!AG14="",'10 Scoring & Weights'!$C$9,IF('03 Feature Comparison'!AH14="X",'10 Scoring & Weights'!$C$8,IF('03 Feature Comparison'!AG14>='10 Scoring & Weights'!$C$14,'10 Scoring & Weights'!$D$14,IF('03 Feature Comparison'!AG14>='10 Scoring & Weights'!$C$15,'10 Scoring & Weights'!$D$15,'10 Scoring & Weights'!$D$16)))) -> 0.6 | M78: =IF('03 Feature Comparison'!AG15="",'10 Scoring & Weights'!$C$9,IF('03 Feature Comparison'!AH15="X",'10 Scoring & Weights'!$C$8,IF('03 Feature Comparison'!AG15>='10 Scoring & Weights'!$C$14,'10 Scoring & Weights'!$D$14,IF('03 Feature Comparison'!AG15>='10 Scoring & Weights'!$C$15,'10 Scoring & Weights'!$D$15,'10 Scoring & Weights'!$D$16)))) -> 0.25 | N78: =IF('03 Feature Comparison'!AG16="",'10 Scoring & Weights'!$C$9,IF('03 Feature Comparison'!AH16="X",'10 Scoring & Weights'!$C$8,IF('03 Feature Comparison'!AG16>='10 Scoring & Weights'!$C$14,'10 Scoring & Weights'!$D$14,IF('03 Feature Comparison'!AG16>='10 Scoring & Weights'!$C$15,'10 Scoring & Weights'!$D$15,'10 Scoring & Weights'!$D$16)))) -> 0.25 | O78: =IF('03 Feature Comparison'!AG17="",'10 Scoring & Weights'!$C$9,IF('03 Feature Comparison'!AH17="X",'10 Scoring & Weights'!$C$8,IF('03 Feature Comparison'!AG17>='10 Scoring & Weights'!$C$14,'10 Scoring & Weights'!$D$14,IF('03 Feature Comparison'!AG17>='10 Scoring & Weights'!$C$15,'10 Scoring & Weights'!$D$15,'10 Scoring & Weights'!$D$16)))) -> 0.25 | P78: =IF('03 Feature Comparison'!AG18="",'10 Scoring & Weights'!$C$9,IF('03 Feature Comparison'!AH18="X",'10 Scoring & Weights'!$C$8,IF('03 Feature Comparison'!AG18>='10 Scoring & Weights'!$C$14,'10 Scoring & Weights'!$D$14,IF('03 Feature Comparison'!AG18>='10 Scoring & Weights'!$C$15,'10 Scoring & Weights'!$D$15,'10 Scoring & Weights'!$D$16)))) -> 0.25
B79: WGT | C79: Weight / comfort class (from 03 specs) | D79: =IF('03 Feature Comparison'!AJ6="",'10 Scoring & Weights'!$C$9,IF('03 Feature Comparison'!AJ6<='10 Scoring & Weights'!$C$17,'10 Scoring & Weights'!$D$17,IF('03 Feature Comparison'!AJ6<='10 Scoring & Weights'!$C$18,'10 Scoring & Weights'!$D$18,'10 Scoring & Weights'!$D$19))) -> 0.25 | E79: =IF('03 Feature Comparison'!AJ7="",'10 Scoring & Weights'!$C$9,IF('03 Feature Comparison'!AJ7<='10 Scoring & Weights'!$C$17,'10 Scoring & Weights'!$D$17,IF('03 Feature Comparison'!AJ7<='10 Scoring & Weights'!$C$18,'10 Scoring & Weights'!$D$18,'10 Scoring & Weights'!$D$19))) -> 0.25 | F79: =IF('03 Feature Comparison'!AJ8="",'10 Scoring & Weights'!$C$9,IF('03 Feature Comparison'!AJ8<='10 Scoring & Weights'!$C$17,'10 Scoring & Weights'!$D$17,IF('03 Feature Comparison'!AJ8<='10 Scoring & Weights'!$C$18,'10 Scoring & Weights'!$D$18,'10 Scoring & Weights'!$D$19))) -> 0.25 | G79: =IF('03 Feature Comparison'!AJ9="",'10 Scoring & Weights'!$C$9,IF('03 Feature Comparison'!AJ9<='10 Scoring & Weights'!$C$17,'10 Scoring & Weights'!$D$17,IF('03 Feature Comparison'!AJ9<='10 Scoring & Weights'!$C$18,'10 Scoring & Weights'!$D$18,'10 Scoring & Weights'!$D$19))) -> 0.25 | H79: =IF('03 Feature Comparison'!AJ10="",'10 Scoring & Weights'!$C$9,IF('03 Feature Comparison'!AJ10<='10 Scoring & Weights'!$C$17,'10 Scoring & Weights'!$D$17,IF('03 Feature Comparison'!AJ10<='10 Scoring & Weights'!$C$18,'10 Scoring & Weights'!$D$18,'10 Scoring & Weights'!$D$19))) -> 1 | I79: =IF('03 Feature Comparison'!AJ11="",'10 Scoring & Weights'!$C$9,IF('03 Feature Comparison'!AJ11<='10 Scoring & Weights'!$C$17,'10 Scoring & Weights'!$D$17,IF('03 Feature Comparison'!AJ11<='10 Scoring & Weights'!$C$18,'10 Scoring & Weights'!$D$18,'10 Scoring & Weights'!$D$19))) -> 0.25 | J79: =IF('03 Feature Comparison'!AJ12="",'10 Scoring & Weights'!$C$9,IF('03 Feature Comparison'!AJ12<='10 Scoring & Weights'!$C$17,'10 Scoring & Weights'!$D$17,IF('03 Feature Comparison'!AJ12<='10 Scoring & Weights'!$C$18,'10 Scoring & Weights'!$D$18,'10 Scoring & Weights'!$D$19))) -> 0.25 | K79: =IF('03 Feature Comparison'!AJ13="",'10 Scoring & Weights'!$C$9,IF('03 Feature Comparison'!AJ13<='10 Scoring & Weights'!$C$17,'10 Scoring & Weights'!$D$17,IF('03 Feature Comparison'!AJ13<='10 Scoring & Weights'!$C$18,'10 Scoring & Weights'!$D$18,'10 Scoring & Weights'!$D$19))) -> 0.25 | L79: =IF('03 Feature Comparison'!AJ14="",'10 Scoring & Weights'!$C$9,IF('03 Feature Comparison'!AJ14<='10 Scoring & Weights'!$C$17,'10 Scoring & Weights'!$D$17,IF('03 Feature Comparison'!AJ14<='10 Scoring & Weights'!$C$18,'10 Scoring & Weights'!$D$18,'10 Scoring & Weights'!$D$19))) -> 0.25 | M79: =IF('03 Feature Comparison'!AJ15="",'10 Scoring & Weights'!$C$9,IF('03 Feature Comparison'!AJ15<='10 Scoring & Weights'!$C$17,'10 Scoring & Weights'!$D$17,IF('03 Feature Comparison'!AJ15<='10 Scoring & Weights'!$C$18,'10 Scoring & Weights'!$D$18,'10 Scoring & Weights'!$D$19))) -> 0.25 | N79: =IF('03 Feature Comparison'!AJ16="",'10 Scoring & Weights'!$C$9,IF('03 Feature Comparison'!AJ16<='10 Scoring & Weights'!$C$17,'10 Scoring & Weights'!$D$17,IF('03 Feature Comparison'!AJ16<='10 Scoring & Weights'!$C$18,'10 Scoring & Weights'!$D$18,'10 Scoring & Weights'!$D$19))) -> 0.25 | O79: =IF('03 Feature Comparison'!AJ17="",'10 Scoring & Weights'!$C$9,IF('03 Feature Comparison'!AJ17<='10 Scoring & Weights'!$C$17,'10 Scoring & Weights'!$D$17,IF('03 Feature Comparison'!AJ17<='10 Scoring & Weights'!$C$18,'10 Scoring & Weights'!$D$18,'10 Scoring & Weights'!$D$19))) -> 0.25 | P79: =IF('03 Feature Comparison'!AJ18="",'10 Scoring & Weights'!$C$9,IF('03 Feature Comparison'!AJ18<='10 Scoring & Weights'!$C$17,'10 Scoring & Weights'!$D$17,IF('03 Feature Comparison'!AJ18<='10 Scoring & Weights'!$C$18,'10 Scoring & Weights'!$D$18,'10 Scoring & Weights'!$D$19))) -> 0.7
B82: 5. Unknown indicator — 1 where the status is Unknown (drives the confirmed / potential market-fit range)
B84: Code | C84: Feature / attribute | D84: VB10 | E84: CT29 | F84: CT34 | G84: MF90 | H84: MF91 | I84: MF40 | J84: HW20 | K84: MF91Pro | L84: HW20Pro | M84: HW19 | N84: CT20S | O84: CT30 (band) | P84: CT31
B85: F01 | C85: Heart rate | D85: =IF('03 Feature Comparison'!F6="Unknown",1,0) -> 0 | E85: =IF('03 Feature Comparison'!F7="Unknown",1,0) -> 1 | F85: =IF('03 Feature Comparison'!F8="Unknown",1,0) -> 1 | G85: =IF('03 Feature Comparison'!F9="Unknown",1,0) -> 0 | H85: =IF('03 Feature Comparison'!F10="Unknown",1,0) -> 0 | I85: =IF('03 Feature Comparison'!F11="Unknown",1,0) -> 0 | J85: =IF('03 Feature Comparison'!F12="Unknown",1,0) -> 0 | K85: =IF('03 Feature Comparison'!F13="Unknown",1,0) -> 0 | L85: =IF('03 Feature Comparison'!F14="Unknown",1,0) -> 1 | M85: =IF('03 Feature Comparison'!F15="Unknown",1,0) -> 0 | N85: =IF('03 Feature Comparison'!F16="Unknown",1,0) -> 0 | O85: =IF('03 Feature Comparison'!F17="Unknown",1,0) -> 0 | P85: =IF('03 Feature Comparison'!F18="Unknown",1,0) -> 0
B86: F02 | C86: Heart-rate variability (HRV) | D86: =IF('03 Feature Comparison'!G6="Unknown",1,0) -> 0 | E86: =IF('03 Feature Comparison'!G7="Unknown",1,0) -> 1 | F86: =IF('03 Feature Comparison'!G8="Unknown",1,0) -> 1 | G86: =IF('03 Feature Comparison'!G9="Unknown",1,0) -> 0 | H86: =IF('03 Feature Comparison'!G10="Unknown",1,0) -> 0 | I86: =IF('03 Feature Comparison'!G11="Unknown",1,0) -> 1 | J86: =IF('03 Feature Comparison'!G12="Unknown",1,0) -> 1 | K86: =IF('03 Feature Comparison'!G13="Unknown",1,0) -> 0 | L86: =IF('03 Feature Comparison'!G14="Unknown",1,0) -> 1 | M86: =IF('03 Feature Comparison'!G15="Unknown",1,0) -> 0 | N86: =IF('03 Feature Comparison'!G16="Unknown",1,0) -> 1 | O86: =IF('03 Feature Comparison'!G17="Unknown",1,0) -> 1 | P86: =IF('03 Feature Comparison'!G18="Unknown",1,0) -> 1
B87: F03 | C87: ECG | D87: =IF('03 Feature Comparison'!H6="Unknown",1,0) -> 0 | E87: =IF('03 Feature Comparison'!H7="Unknown",1,0) -> 1 | F87: =IF('03 Feature Comparison'!H8="Unknown",1,0) -> 1 | G87: =IF('03 Feature Comparison'!H9="Unknown",1,0) -> 0 | H87: =IF('03 Feature Comparison'!H10="Unknown",1,0) -> 1 | I87: =IF('03 Feature Comparison'!H11="Unknown",1,0) -> 0 | J87: =IF('03 Feature Comparison'!H12="Unknown",1,0) -> 1 | K87: =IF('03 Feature Comparison'!H13="Unknown",1,0) -> 0 | L87: =IF('03 Feature Comparison'!H14="Unknown",1,0) -> 1 | M87: =IF('03 Feature Comparison'!H15="Unknown",1,0) -> 1 | N87: =IF('03 Feature Comparison'!H16="Unknown",1,0) -> 1 | O87: =IF('03 Feature Comparison'!H17="Unknown",1,0) -> 1 | P87: =IF('03 Feature Comparison'!H18="Unknown",1,0) -> 1
B88: F04 | C88: SpO2 | D88: =IF('03 Feature Comparison'!I6="Unknown",1,0) -> 0 | E88: =IF('03 Feature Comparison'!I7="Unknown",1,0) -> 1 | F88: =IF('03 Feature Comparison'!I8="Unknown",1,0) -> 1 | G88: =IF('03 Feature Comparison'!I9="Unknown",1,0) -> 0 | H88: =IF('03 Feature Comparison'!I10="Unknown",1,0) -> 0 | I88: =IF('03 Feature Comparison'!I11="Unknown",1,0) -> 0 | J88: =IF('03 Feature Comparison'!I12="Unknown",1,0) -> 0 | K88: =IF('03 Feature Comparison'!I13="Unknown",1,0) -> 1 | L88: =IF('03 Feature Comparison'!I14="Unknown",1,0) -> 1 | M88: =IF('03 Feature Comparison'!I15="Unknown",1,0) -> 0 | N88: =IF('03 Feature Comparison'!I16="Unknown",1,0) -> 1 | O88: =IF('03 Feature Comparison'!I17="Unknown",1,0) -> 1 | P88: =IF('03 Feature Comparison'!I18="Unknown",1,0) -> 0
B89: F05 | C89: Blood pressure | D89: =IF('03 Feature Comparison'!J6="Unknown",1,0) -> 1 | E89: =IF('03 Feature Comparison'!J7="Unknown",1,0) -> 1 | F89: =IF('03 Feature Comparison'!J8="Unknown",1,0) -> 1 | G89: =IF('03 Feature Comparison'!J9="Unknown",1,0) -> 0 | H89: =IF('03 Feature Comparison'!J10="Unknown",1,0) -> 0 | I89: =IF('03 Feature Comparison'!J11="Unknown",1,0) -> 0 | J89: =IF('03 Feature Comparison'!J12="Unknown",1,0) -> 0 | K89: =IF('03 Feature Comparison'!J13="Unknown",1,0) -> 1 | L89: =IF('03 Feature Comparison'!J14="Unknown",1,0) -> 0 | M89: =IF('03 Feature Comparison'!J15="Unknown",1,0) -> 0 | N89: =IF('03 Feature Comparison'!J16="Unknown",1,0) -> 1 | O89: =IF('03 Feature Comparison'!J17="Unknown",1,0) -> 0 | P89: =IF('03 Feature Comparison'!J18="Unknown",1,0) -> 0
B90: F06 | C90: Body / skin temperature | D90: =IF('03 Feature Comparison'!K6="Unknown",1,0) -> 0 | E90: =IF('03 Feature Comparison'!K7="Unknown",1,0) -> 1 | F90: =IF('03 Feature Comparison'!K8="Unknown",1,0) -> 1 | G90: =IF('03 Feature Comparison'!K9="Unknown",1,0) -> 0 | H90: =IF('03 Feature Comparison'!K10="Unknown",1,0) -> 0 | I90: =IF('03 Feature Comparison'!K11="Unknown",1,0) -> 1 | J90: =IF('03 Feature Comparison'!K12="Unknown",1,0) -> 1 | K90: =IF('03 Feature Comparison'!K13="Unknown",1,0) -> 1 | L90: =IF('03 Feature Comparison'!K14="Unknown",1,0) -> 1 | M90: =IF('03 Feature Comparison'!K15="Unknown",1,0) -> 1 | N90: =IF('03 Feature Comparison'!K16="Unknown",1,0) -> 0 | O90: =IF('03 Feature Comparison'!K17="Unknown",1,0) -> 1 | P90: =IF('03 Feature Comparison'!K18="Unknown",1,0) -> 0
B91: F07 | C91: Sleep monitoring | D91: =IF('03 Feature Comparison'!L6="Unknown",1,0) -> 0 | E91: =IF('03 Feature Comparison'!L7="Unknown",1,0) -> 1 | F91: =IF('03 Feature Comparison'!L8="Unknown",1,0) -> 1 | G91: =IF('03 Feature Comparison'!L9="Unknown",1,0) -> 0 | H91: =IF('03 Feature Comparison'!L10="Unknown",1,0) -> 0 | I91: =IF('03 Feature Comparison'!L11="Unknown",1,0) -> 0 | J91: =IF('03 Feature Comparison'!L12="Unknown",1,0) -> 0 | K91: =IF('03 Feature Comparison'!L13="Unknown",1,0) -> 1 | L91: =IF('03 Feature Comparison'!L14="Unknown",1,0) -> 1 | M91: =IF('03 Feature Comparison'!L15="Unknown",1,0) -> 0 | N91: =IF('03 Feature Comparison'!L16="Unknown",1,0) -> 0 | O91: =IF('03 Feature Comparison'!L17="Unknown",1,0) -> 1 | P91: =IF('03 Feature Comparison'!L18="Unknown",1,0) -> 1
B92: F08 | C92: Steps & activity | D92: =IF('03 Feature Comparison'!M6="Unknown",1,0) -> 0 | E92: =IF('03 Feature Comparison'!M7="Unknown",1,0) -> 1 | F92: =IF('03 Feature Comparison'!M8="Unknown",1,0) -> 1 | G92: =IF('03 Feature Comparison'!M9="Unknown",1,0) -> 0 | H92: =IF('03 Feature Comparison'!M10="Unknown",1,0) -> 0 | I92: =IF('03 Feature Comparison'!M11="Unknown",1,0) -> 0 | J92: =IF('03 Feature Comparison'!M12="Unknown",1,0) -> 0 | K92: =IF('03 Feature Comparison'!M13="Unknown",1,0) -> 1 | L92: =IF('03 Feature Comparison'!M14="Unknown",1,0) -> 1 | M92: =IF('03 Feature Comparison'!M15="Unknown",1,0) -> 1 | N92: =IF('03 Feature Comparison'!M16="Unknown",1,0) -> 1 | O92: =IF('03 Feature Comparison'!M17="Unknown",1,0) -> 0 | P92: =IF('03 Feature Comparison'!M18="Unknown",1,0) -> 1
B93: F09 | C93: Stress indicator | D93: =IF('03 Feature Comparison'!N6="Unknown",1,0) -> 0 | E93: =IF('03 Feature Comparison'!N7="Unknown",1,0) -> 1 | F93: =IF('03 Feature Comparison'!N8="Unknown",1,0) -> 1 | G93: =IF('03 Feature Comparison'!N9="Unknown",1,0) -> 0 | H93: =IF('03 Feature Comparison'!N10="Unknown",1,0) -> 0 | I93: =IF('03 Feature Comparison'!N11="Unknown",1,0) -> 0 | J93: =IF('03 Feature Comparison'!N12="Unknown",1,0) -> 1 | K93: =IF('03 Feature Comparison'!N13="Unknown",1,0) -> 1 | L93: =IF('03 Feature Comparison'!N14="Unknown",1,0) -> 1 | M93: =IF('03 Feature Comparison'!N15="Unknown",1,0) -> 1 | N93: =IF('03 Feature Comparison'!N16="Unknown",1,0) -> 1 | O93: =IF('03 Feature Comparison'!N17="Unknown",1,0) -> 1 | P93: =IF('03 Feature Comparison'!N18="Unknown",1,0) -> 1
B94: F10 | C94: Automatic fall detection | D94: =IF('03 Feature Comparison'!O6="Unknown",1,0) -> 1 | E94: =IF('03 Feature Comparison'!O7="Unknown",1,0) -> 0 | F94: =IF('03 Feature Comparison'!O8="Unknown",1,0) -> 0 | G94: =IF('03 Feature Comparison'!O9="Unknown",1,0) -> 1 | H94: =IF('03 Feature Comparison'!O10="Unknown",1,0) -> 1 | I94: =IF('03 Feature Comparison'!O11="Unknown",1,0) -> 1 | J94: =IF('03 Feature Comparison'!O12="Unknown",1,0) -> 0 | K94: =IF('03 Feature Comparison'!O13="Unknown",1,0) -> 1 | L94: =IF('03 Feature Comparison'!O14="Unknown",1,0) -> 0 | M94: =IF('03 Feature Comparison'!O15="Unknown",1,0) -> 0 | N94: =IF('03 Feature Comparison'!O16="Unknown",1,0) -> 0 | O94: =IF('03 Feature Comparison'!O17="Unknown",1,0) -> 1 | P94: =IF('03 Feature Comparison'!O18="Unknown",1,0) -> 1
B95: F11 | C95: SOS button | D95: =IF('03 Feature Comparison'!P6="Unknown",1,0) -> 1 | E95: =IF('03 Feature Comparison'!P7="Unknown",1,0) -> 1 | F95: =IF('03 Feature Comparison'!P8="Unknown",1,0) -> 0 | G95: =IF('03 Feature Comparison'!P9="Unknown",1,0) -> 1 | H95: =IF('03 Feature Comparison'!P10="Unknown",1,0) -> 1 | I95: =IF('03 Feature Comparison'!P11="Unknown",1,0) -> 1 | J95: =IF('03 Feature Comparison'!P12="Unknown",1,0) -> 0 | K95: =IF('03 Feature Comparison'!P13="Unknown",1,0) -> 1 | L95: =IF('03 Feature Comparison'!P14="Unknown",1,0) -> 0 | M95: =IF('03 Feature Comparison'!P15="Unknown",1,0) -> 0 | N95: =IF('03 Feature Comparison'!P16="Unknown",1,0) -> 0 | O95: =IF('03 Feature Comparison'!P17="Unknown",1,0) -> 0 | P95: =IF('03 Feature Comparison'!P18="Unknown",1,0) -> 0
